Workbook
Name Slicer_Area: #N/A
Name Slicer_Area_Detail: #N/A
Name Slicer_Recruiter: #N/A
Name Slicer_Status: #N/A

Sheet Dashboard
H1: Hiring Request
H2: Total | J2: Non Staff | M2: Staff | Q2: Total Open Roles | U2: Total Hold / Cancel Roles | Z2: Total Closed Roles
B3: Bulan Terakhir | D3: ='Master Data HO & Site'!CE2 -> 45965.657
E9: Hiring Progress | M9: Progress Based on Request Month Date | U9: Hiring Progress Per Grade
E25: Hiring Progress Per Recruiter | M25: Additional Vs Replacement | U25: SLA (Service Level Agreement)
E43: Progress Rekrutment TPG | M43: Progress Rekrutment GLM

Sheet Dashboard 2
A1: Count of SLA Group | B1: Column Labels
B2: 61 - 90 Days | D2: 61 - 90 Days Total | E2: 0 - 30 Days | G2: 0 - 30 Days Total | H2: Hold/Cancel | J2: Hold/Cancel Total | K2: 31 - 60 Days | M2: 31 - 60 Days Total | N2: above 91 Days | P2: above 91 Days Total | Q2: (blank) | S2: (blank) Total | T2: Grand Total
A3: Row Labels | B3: Non Staff | C3: Staff | E3: Non Staff | F3: Staff | H3: Non Staff | I3: Staff | K3: Non Staff | L3: Staff | N3: Non Staff | O3: Staff | Q3: Staff | R3: (blank)
A4: Open | B4: 23 | C4: 49 | D4: 72 | F4: 45 | G4: 45 | H4: 2 | I4: 1 | J4: 3 | K4: 1 | L4: 6 | M4: 7 | N4: 1 | O4: 5 | P4: 6 | T4: 133
A5: HO | C5: 35 | D5: 35 | F5: 45 | G5: 45 | L5: 3 | M5: 3 | O5: 3 | P5: 3 | T5: 86
A6: Site | B6: 23 | C6: 14 | D6: 37 | H6: 2 | I6: 1 | J6: 3 | K6: 1 | L6: 3 | M6: 4 | N6: 1 | O6: 2 | P6: 3 | T6: 47
A7: Closed | B7: 11 | C7: 18 | D7: 29 | E7: 131 | F7: 12 | G7: 143 | H7: 3 | I7: 1 | J7: 4 | K7: 37 | L7: 22 | M7: 59 | N7: 12 | O7: 26 | P7: 38 | T7: 273
A8: HO | C8: 14 | D8: 14 | E8: 1 | F8: 7 | G8: 8 | L8: 9 | M8: 9 | N8: 1 | O8: 17 | P8: 18 | T8: 49
A9: Site | B9: 11 | C9: 4 | D9: 15 | E9: 130 | F9: 5 | G9: 135 | H9: 3 | I9: 1 | J9: 4 | K9: 37 | L9: 13 | M9: 50 | N9: 11 | O9: 9 | P9: 20 | T9: 224
A10: Hold / Cancel | H10: 19 | I10: 9 | J10: 28 | T10: 28
A11: HO | I11: 5 | J11: 5 | T11: 5
A12: Site | H12: 19 | I12: 4 | J12: 23 | T12: 23
A13: (blank)
A14: (blank)
A15: Grand Total | B15: 34 | C15: 67 | D15: 101 | E15: 131 | F15: 57 | G15: 188 | H15: 24 | I15: 11 | J15: 35 | K15: 38 | L15: 28 | M15: 66 | N15: 13 | O15: 31 | P15: 44 | T15: 434
A18: STATUS HO | B18: Count of Division | D18: STATUS SITE | E18: Count of Area Detail | J18: Close | S18: Lokasi | T18: 0 - 30 Days | U18: 31 - 60 Days | V18: 61 - 90 Days | W18: > 91 Days | X18: Total
A19: Open | B19: 86 | D19: Open | E19: 48 | G19: Admin | H19: Tj Pura | J19: HO | K19: =SUM(K20:K24) -> 8 | M19: Site | N19: =SUM(N20:N24) -> 5 | P19: HO | Q19: > 91 Days | R19: a | S19: HO | T19: =COUNTIFS($P$19:$P$57,$S19,$Q$19:$Q$57,T$18) -> 3 | U19: =COUNTIFS($P$19:$P$57,$S19,$Q$19:$Q$57,U$18) -> 1 | V19: =COUNTIFS($P$19:$P$57,$S19,$Q$19:$Q$57,V$18) -> 4 | W19: =COUNTIFS($P$19:$P$57,$S19,$R$19:$R$57,"a") -> 9 | X19: =SUM(T19:W19) -> 17
A20: HO | B20: 86 | D20: Site | E20: 48 | G20: Commercial | H20: Jakarta | J20: Commercial | K20: 3 | M20: Bontang | N20: 1 | P20: Site | Q20: > 91 Days | R20: a | S20: Site | T20: =COUNTIFS($P$19:$P$57,$S20,$Q$19:$Q$57,T$18) -> 13 | U20: =COUNTIFS($P$19:$P$57,$S20,$Q$19:$Q$57,U$18) -> 1 | V20: =COUNTIFS($P$19:$P$57,$S20,$Q$19:$Q$57,V$18) -> 3 | W20: =COUNTIFS($P$19:$P$57,$S20,$R$19:$R$57,"a") -> 5 | X20: =SUM(T20:W20) -> 22
A21: Commercial | B21: 64 | D21: Bontang | E21: 8 | G21: Commercial | H21: Jakarta | J21: FABTIC | K21: 3 | M21: Tanjung Pura | N21: 4 | P21: Site | Q21: > 91 Days | R21: a
A22: FABTIC | B22: 7 | D22: Karawaci | E22: 2 | G22: Commercial | H22: Jakarta | J22: Human Capital | K22: 1 | P22: Site | Q22: 61 - 90 Days | R22: 61 - 90 Days
A23: Operation | B23: 1 | D23: Lubuk Gaung | E23: 19 | G23: FABTIC | H23: Jakarta | J23: Procurement | K23: 1 | P23: HO | Q23: > 91 Days | R23: a
A24: Project | B24: 5 | D24: Tanjung Morawa | E24: 7 | G24: FABTIC | H24: Jakarta | P24: Site | Q24: > 91 Days | R24: a
A25: HC | B25: 1 | D25: Karawang | E25: 2 | G25: FABTIC | H25: Jakarta | J25: Open | P25: Site | Q25: > 91 Days | R25: a
A26: Procurement | B26: 1 | D26: Tanjung Pura | E26: 5 | G26: Human Capital | H26: Jakarta | J26: HO | K26: =SUM(K27:K33) -> 17 | M26: Site | N26: =SUM(N27:N33) -> 22 | P26: HO | Q26: 0 - 30 Days | R26: 0 - 30 Days
A27: Bonded Zone | B27: 2 | D27: Gresik | E27: 5 | G27: Procurement | H27: Jakarta | J27: Commercial | K27: 1 | M27: Bekasi | N27: 1 | P27: HO | Q27: > 91 Days | R27: a
A28: Legal | B28: 3 | D28: Closed | E28: 224 | G28: Production | H28: Tanjung Pura | J28: FABTIC | K28: 10 | M28: Bontang | N28: 8 | P28: Site | Q28: > 91 Days | R28: a
A29: Technical Services | B29: 2 | D29: Site | E29: 224 | G29: Production | H29: Tanjung Pura | J29: Human Capital | K29: 1 | M29: Karawang | N29: 1 | P29: HO | Q29: > 91 Days | R29: a
A30: Closed | B30: 49 | D30: Bekasi | E30: 6 | G30: Project | H30: Bontang | J30: Non-Palm Commercial | K30: 1 | M30: Tamora | N30: 3 | P30: HO | Q30: > 91 Days | R30: a
A31: HO | B31: 49 | D31: Bontang | E31: 33 | G31: Quality Control | H31: Tanjung Pura | J31: Export Import | K31: 2 | M31: Tangerang | N31: 3 | P31: HO | Q31: > 91 Days | R31: a
A32: Commercial | B32: 14 | D32: Karawaci | E32: 13 | J32: Dry Logistic | K32: 1 | M32: Tanjung Pura | N32: 3 | P32: HO | Q32: > 91 Days | R32: a
A33: EXIM | B33: 5 | D33: Lubuk Gaung | E33: 58 | J33: Technical Service | K33: 1 | M33: Sidoarjo | N33: 3 | P33: Site | Q33: 61 - 90 Days | R33: 61 - 90 Days
A34: FABTIC | B34: 12 | D34: Tanjung Morawa | E34: 23 | P34: Site | Q34: 61 - 90 Days | R34: 61 - 90 Days
A35: IT | B35: 1 | D35: Karawang | E35: 3 | J35: Total | P35: HO | Q35: 61 - 90 Days | R35: 61 - 90 Days
A36: Project | B36: 5 | D36: Tanjung Pura | E36: 68 | J36: HO | K36: =K26+K19 -> 25 | M36: Site | N36: =N26+N19 -> 27 | P36: HO | Q36: 61 - 90 Days | R36: 61 - 90 Days
A37: HC | B37: 5 | D37: Sidoarjo | E37: 5 | P37: HO | Q37: 61 - 90 Days | R37: 61 - 90 Days
A38: Procurement | B38: 1 | D38: Kumai | E38: 1 | P38: HO | Q38: 61 - 90 Days | R38: 61 - 90 Days
A39: Bonded Zone | B39: 2 | D39: Gresik | E39: 14 | P39: HO | Q39: > 91 Days | R39: a
A40: Legal | B40: 4 | D40: Hold / Cancel | E40: 23 | P40: HO | Q40: 31 - 60 Days | R40: 31 - 60 Days
A41: Hold / Cancel | B41: 5 | D41: Site | E41: 23 | P41: HO | Q41: 0 - 30 Days | R41: 0 - 30 Days
A42: HO | B42: 5 | D42: Bekasi | E42: 1 | P42: Site | Q42: 31 - 60 Days | R42: 31 - 60 Days
A43: Commercial | B43: 1 | D43: Bontang | E43: 8 | P43: Site | Q43: 0 - 30 Days | R43: 0 - 30 Days
A44: EXIM | B44: 1 | D44: Lubuk Gaung | E44: 1 | P44: Site | Q44: 0 - 30 Days | R44: 0 - 30 Days
A45: FABTIC | B45: 1 | D45: Tanjung Morawa | E45: 2 | P45: Site | Q45: 0 - 30 Days | R45: 0 - 30 Days
A46: Project | B46: 2 | D46: Karawang | E46: 7 | P46: Site | Q46: 0 - 30 Days | R46: 0 - 30 Days
A47: Grand Total | B47: 140 | D47: Tanjung Pura | E47: 2 | P47: HO | Q47: 0 - 30 Days | R47: 0 - 30 Days
D48: Gresik | E48: 2 | P48: HO | Q48: > 91 Days | R48: a
D49: Grand Total | E49: 295 | P49: Site | Q49: 0 - 30 Days | R49: 0 - 30 Days
P50: Site | Q50: 0 - 30 Days | R50: 0 - 30 Days
P51: Site | Q51: 0 - 30 Days | R51: 0 - 30 Days
P52: Site | Q52: 0 - 30 Days | R52: 0 - 30 Days
P53: Site | Q53: 0 - 30 Days | R53: 0 - 30 Days
P54: Site | Q54: 0 - 30 Days | R54: 0 - 30 Days
P55: Site | Q55: 0 - 30 Days | R55: 0 - 30 Days
P56: Site | Q56: 0 - 30 Days | R56: 0 - 30 Days
P57: Site | Q57: 0 - 30 Days | R57: 0 - 30 Days

Sheet Dashboard Report Custom
B1: Month Request Date | C1: (All) | J1: Month Request Date | K1: (Multiple Items) | O1: Month Request Date | P1: (Multiple Items)
B3: Count of Area | C3: Column Labels | J3: Count of Area | K3: Column Labels | O3: Count of Area | P3: Column Labels
B4: Row Labels | C4: Open | D4: Grand Total | J4: Row Labels | K4: Closed | L4: Open | M4: Grand Total | O4: Row Labels | P4: Closed | Q4: Open | R4: Grand Total
B5: HO | C5: 86 | D5: 86 | J5: Bekasi | K5: 4 | M5: 4 | O5: Bekasi | P5: 4 | R5: 4
B6: Site | C6: 48 | D6: 48 | J6: Bontang | K6: 21 | M6: 21 | O6: Bontang | P6: 21 | R6: 21
B7: Grand Total | C7: 134 | D7: 134 | J7: Gresik | K7: 1 | M7: 1 | O7: Gresik | P7: 1 | R7: 1
B8: Month Request Date | C8: (All) | J8: Jakarta | K8: 34 | M8: 34 | O8: Karawaci | P8: 9 | R8: 9
J9: Karawaci | K9: 9 | M9: 9 | O9: Karawang | P9: 2 | R9: 2
B10: Count of Area | C10: Column Labels | J10: Karawang | K10: 2 | M10: 2 | O10: Kumai | P10: 1 | R10: 1
B11: Row Labels | C11: Open | D11: Grand Total | J11: Kumai | K11: 1 | M11: 1 | O11: Lubuk Gaung | P11: 35 | Q11: 3 | R11: 38
B12: HO | C12: 86 | D12: 86 | J12: Lubuk Gaung | K12: 35 | L12: 3 | M12: 38 | O12: Sidoarjo | P12: 2 | R12: 2
B13: Jakarta | C13: 86 | D13: 86 | J13: Sidoarjo | K13: 2 | M13: 2 | O13: Tanjung Morawa | P13: 15 | Q13: 1 | R13: 16
B14: Site | C14: 48 | D14: 48 | J14: Tanjung Morawa | K14: 15 | L14: 1 | M14: 16 | O14: Tanjung Pura | P14: 57 | R14: 57
B15: Bontang | C15: 8 | D15: 8 | J15: Tanjung Pura | K15: 57 | M15: 57 | O15: Grand Total | P15: 147 | Q15: 4 | R15: 151
B16: Gresik | C16: 5 | D16: 5 | J16: Grand Total | K16: 181 | L16: 4 | M16: 185
B17: Karawaci | C17: 2 | D17: 2
B18: Karawang | C18: 2 | D18: 2 | O18: Area | P18: HO
B19: Lubuk Gaung | C19: 19 | D19: 19 | J19: AREA DETAIL | K19: Closed | L19: Open | M19: Grand Total
B20: Tanjung Morawa | C20: 7 | D20: 7 | J20: Jakarta | K20: =GETPIVOTDATA("Area",$J$3,"Area Detail","Jakarta","Status","Closed") -> 34 | L20: =GETPIVOTDATA("Area",$J$3,"Area Detail","Jakarta","Status","Open") -> 0 | M20: =K20+L20 -> 34 | O20: Count of Area | P20: Column Labels
B21: Tanjung Pura | C21: 5 | D21: 5 | J21: Bekasi | K21: =GETPIVOTDATA("Area",$J$3,"Area Detail","Bekasi","Status","Closed") -> 4 | L21: =GETPIVOTDATA("Area",$J$3,"Area Detail","Bekasi","Status","Open") -> 0 | M21: =K21+L21 -> 4 | O21: Row Labels | P21: Closed | Q21: Open | R21: Grand Total
B22: Grand Total | C22: 134 | D22: 134 | J22: Bontang | K22: =GETPIVOTDATA("Area",$J$3,"Area Detail","Bontang","Status","Closed") -> 21 | L22: =GETPIVOTDATA("Area",$J$3,"Area Detail","Bontang","Status","Open") -> 0 | M22: =K22+L22 -> 21 | O22: Bonded Zone | P22: 2 | Q22: 2 | R22: 4
J23: Bulking Palembang | K23: =GETPIVOTDATA("Area",$J$3,"Area Detail","Bulking Palembang","Status","Closed") -> #REF! | M23: =K23+L23 -> #REF! | O23: Commercial | P23: 14 | Q23: 64 | R23: 78
J24: Karawaci | K24: =GETPIVOTDATA("Area",$J$3,"Area Detail","Karawaci","Status","Closed") -> 9 | L24: =GETPIVOTDATA("Area",$J$3,"Area Detail","Karawaci","Status","Open") -> 0 | M24: =K24+L24 -> 9 | O24: EXIM | P24: 5 | R24: 5
J25: Karawang | K25: =GETPIVOTDATA("Area",$J$3,"Area Detail","Karawang","Status","Closed") -> 2 | M25: =K25+L25 -> 2 | O25: FABTIC | P25: 12 | Q25: 7 | R25: 19
J26: Kumai | K26: =GETPIVOTDATA("Area",$J$3,"Area Detail","Kumai","Status","Closed") -> 1 | M26: =K26+L26 -> 1 | O26: HC | P26: 5 | Q26: 1 | R26: 6
J27: Lubuk Gaung | K27: =GETPIVOTDATA("Area",$J$3,"Area Detail","Lubuk Gaung","Status","Closed") -> 35 | L27: =GETPIVOTDATA("Area",$J$3,"Area Detail","Lubuk Gaung","Status","Open") -> 3 | M27: =K27+L27 -> 38 | O27: IT | P27: 1 | R27: 1
J28: Sidoarjo | K28: =GETPIVOTDATA("Area",$J$3,"Area Detail","Sidoarjo","Status","Closed") -> 2 | L28: =GETPIVOTDATA("Area",$J$3,"Area Detail","Sidoarjo","Status","Open") -> 0 | M28: =K28+L28 -> 2 | O28: Legal | P28: 4 | Q28: 3 | R28: 7
J29: Tanjung Morawa | K29: =GETPIVOTDATA("Area",$J$3,"Area Detail","Tanjung Morawa","Status","Closed") -> 15 | L29: =GETPIVOTDATA("Area",$J$3,"Area Detail","Tanjung Morawa","Status","Open") -> 1 | M29: =K29+L29 -> 16 | O29: Operation | Q29: 1 | R29: 1
J30: Tanjung Pura | K30: =GETPIVOTDATA("Area",$J$3,"Area Detail","Tanjung Pura","Status","Closed") -> 57 | L30: =GETPIVOTDATA("Area",$J$3,"Area Detail","Tanjung Pura","Status","Open") -> 0 | M30: =K30+L30 -> 57 | O30: Procurement | P30: 1 | Q30: 1 | R30: 2
J31: Grand Total | K31: =SUM(K20:K30) -> #REF! | L31: =SUM(L20:L30) -> 4 | M31: =SUM(M20:M30) -> #REF! | O31: Project | P31: 5 | Q31: 5 | R31: 10
B32: Status | C32: Open | O32: Technical Services | Q32: 2 | R32: 2
B33: Month Request Date | C33: (Multiple Items) | O33: Grand Total | P33: 49 | Q33: 86 | R33: 135
B35: Count of Area | C35: Column Labels
B36: Row Labels | C36: Grand Total
B37: Grand Total
B50: Month Request Date | C50: (Multiple Items)
B51: Progress | C51: (Multiple Items)
B53: Count of Area | C53: Column Labels
B54: Row Labels | C54: Closed | D54: Grand Total
B55: HO | C55: 31 | D55: 31
B56: Site | C56: 131 | D56: 131
B57: Bekasi | C57: 5 | D57: 5
B58: Bontang | C58: 19 | D58: 19
B59: Gresik | C59: 8 | D59: 8
B60: Karawaci | C60: 7 | D60: 7
B61: Karawang | C61: 1 | D61: 1
B62: Kumai | C62: 1 | D62: 1
B63: Lubuk Gaung | C63: 39 | D63: 39
B64: Sidoarjo | C64: 4 | D64: 4
B65: Tanjung Morawa | C65: 10 | D65: 10
B66: Tanjung Pura | C66: 37 | D66: 37
B67: Grand Total | C67: 162 | D67: 162

Sheet Sheet4
A2: SLA Group | B2: All
A3: Status | B3: Closed
A5: Count of Position | B5: Column Labels
A6: Row Labels | B6: Bekasi | C6: Bontang | D6: Gresik | E6: Jakarta | F6: Karawaci | G6: Karawang | H6: Kumai | I6: Lubuk Gaung | J6: Sidoarjo | K6: Tanjung Morawa | L6: Tanjung Pura | M6: Grand Total
A7: 2 | B7: 2 | C7: 2 | D7: 9 | E7: 1 | F7: 1 | G7: 1 | H7: 1 | I7: 22 | J7: 2 | K7: 6 | L7: 27 | M7: 74
A8: 3 | C8: 28 | D8: 5 | E8: 1 | F8: 8 | G8: 1 | I8: 26 | J8: 3 | K8: 14 | L8: 34 | M8: 120
A9: 4 | B9: 2 | C9: 2 | E9: 26 | F9: 2 | G9: 1 | I9: 8 | K9: 2 | L9: 3 | M9: 46
A10: 5 | B10: 2 | E10: 4 | F10: 1 | I10: 1 | L10: 3 | M10: 11
A11: 6 | C11: 1 | E11: 8 | F11: 1 | I11: 1 | K11: 1 | L11: 1 | M11: 13
A12: 7 | E12: 7 | M12: 7
A13: 8 | E13: 2 | M13: 2
A14: Grand Total | B14: 6 | C14: 33 | D14: 14 | E14: 49 | F14: 13 | G14: 3 | H14: 1 | I14: 58 | J14: 5 | K14: 23 | L14: 68 | M14: 273

Sheet Summary to Mgmt
C2: Priority | H2: All
U3: Progress | AU3: SLA
B4: No | C4: Location | D4: Division | E4: Dept/Section | F4: Total Positions | G4: Total Closed Positions | H4: Total Open Positions | I4: Pending FKTK | J4: week 1 | K4: week 2 | L4: week 3 | M4: week 4 | N4: week 5 | O4: Total Sent CV To User | P4: week 1 | Q4: week 2 | R4: week 3 | S4: week 4 | T4: week 5 | U4: Interview | V4: week 1 | W4: week 2 | X4: week 3 | Y4: week 4 | Z4: week 5 | AA4: Psikotest | AB4: week 1 | AC4: week 2 | AD4: week 3 | AE4: week 4 | AF4: week 5 | AG4: Teknikal Tes | AH4: week 1 | AI4: week 2 | AJ4: week 3 | AK4: week 4 | AL4: week 5 | AM4: Offer | AN4: week 1 | AO4: week 2 | AP4: week 3 | AQ4: week 4 | AR4: week 5 | AS4: MCU | AU4: 0 - 30 Days | AV4: 31 - 60 Days | AW4: 61 - 90 Days | AX4: above 91 Days
B5: 1 | C5: Jakarta | F5: =G5+H5 -> 135 | G5: =SUM(G6:G50) -> 49 | H5: =SUM(H6:H50) -> 86 | I5: =SUM(I6:I50) -> 61 | J5: =SUM(J6:J50) -> 22 | K5: =SUM(K6:K50) -> 25 | L5: =SUM(L6:L50) -> 14 | M5: =SUM(M6:M50) -> 14 | N5: =SUM(N6:N50) -> 1 | ... AS5: =SUM(AS6:AS50) -> 6 | AU5: =SUM(AU6:AU50) -> 45 | AV5: =SUM(AV6:AV50) -> 0 | AW5: =SUM(AW6:AW50) -> 3 | AX5: =SUM(AX6:AX50) -> 39
C6: Jakarta | D6: Bonded Zone | E6: Bonded Zone | F6: =G6+H6 -> 3 | G6: =IF($H$2="All",IF(C6="Jakarta",SUMIFS('Master Data HO & Site'!$BM$1:$BM$437,'Master Data HO & Site'!$S$1:$S$437,'Summary to Mgmt'!C6,'Master Data HO & Site'!$F$1:$F$437,'Summary to Mgmt'!$D6,'Master Data HO & Site'!$H$1:$H$437,'Summary to Mgmt'!$E6,'Master Data HO & Site'!$Y$1:$Y$437,"Closed"),SUMIFS('Master Data HO & Site'!$BM$1:$BM$437,'Master Data HO & Site'!$S$1:$S$437,'Summary to Mgmt'!C6,'Master Data HO & Site'!$Y$1:$Y$437,"Closed")),IF(C6="Jakarta",SUMIFS('Master Data HO & Site'!$BM$1:$BM$437,'Master Data HO & Site'!$S$1:$S$437,'Summary to Mgmt'!C6,'Master Data HO & Site'!$F$1:$F$437,'Summary to Mgmt'!$D6,'Master Data HO & Site'!$H$1:$H$437,'Summary to Mgmt'!E6,'Master Data HO & Site'!$N$1:$N$437,'Summary to Mgmt'!$H$2,'Master Data HO & Site'!$Y$1:$Y$437,"Closed"),SUMIFS('Master Data HO & Site'!$BM$1:$BM$437,'Master Data HO & Site'!$S$1:$S$437,'Summary to Mgmt'!C6,'Master Data HO & Site'!$N$1:$N$437,'Summary to Mgmt'!$H$2,'Master Data HO & Site'!$Y$1:$Y$437,"Closed"))) -> 2 | H6: =IF($H$2="All",IF(C6="Jakarta",COUNTIFS('Master Data HO & Site'!$S$1:$S$437,'Summary to Mgmt'!$C6,'Master Data HO & Site'!$F$1:$F$437,'Summary to Mgmt'!$D6,'Master Data HO & Site'!$H$1:$H$437,'Summary to Mgmt'!$E6,'Master Data HO & Site'!$Y$1:$Y$437,"Open"),COUNTIFS('Master Data HO & Site'!$S$1:$S$437,'Summary to Mgmt'!$C6,'Master Data HO & Site'!$Y$1:$Y$437,"Open")),IF($H$2="Urgent",IF(C6="Jakarta",COUNTIFS('Master Data HO & Site'!$S$1:$S$437,'Summary to Mgmt'!$C6,'Master Data HO & Site'!$F$1:$F$437,'Summary to Mgmt'!$D6,'Master Data HO & Site'!$H$1:$H$437,'Summary to Mgmt'!$E6,'Master Data HO & Site'!$Y$1:$Y$437,"Open",'Master Data HO & Site'!$N$1:$N$437,$H$2),COUNTIFS('Master Data HO & Site'!$S$1:$S$437,'Summary to Mgmt'!$C6,'Master Data HO & Site'!$Y$1:$Y$437,"Open",'Master Data HO & Site'!$N$1:$N$437,$H$2)),IF(C6="Jakarta",COUNTIFS('Master Data HO & Site'!$F$1:$F$437,'Summary to Mgmt'!$D6,'Master Data HO & Site'!$H$1:$H$437,'Summary to Mgmt'!$E6,'Master Data HO & Site'!$Y$1:$Y$437,"Open",'Master Data HO & Site'!$N$1:$N$437,$H$2),COUNTIFS('Master Data HO & Site'!$S$1:$S$437,'Summary to Mgmt'!$C6,'Master Data HO & Site'!$Y$1:$Y$437,"Open",'Master Data HO & Site'!$N$1:$N$437,$H$2)))) -> 1 | I6: =IF($H$2="All",IF(C6="Jakarta",COUNTIFS('Master Data HO & Site'!$F$1:$F$437,'Summary to Mgmt'!$D6,'Master Data HO & Site'!$H$1:$H$437,'Summary to Mgmt'!$E6,'Master Data HO & Site'!$Y$1:$Y$437,"Open",'Master Data HO & Site'!$D$1:$D$437,"pending FKTK"),COUNTIFS('Master Data HO & Site'!$S$1:$S$437,'Summary to Mgmt'!$C6,'Master Data HO & Site'!$Y$1:$Y$437,"Open",'Master Data HO & Site'!$D$1:$D$437,"pending FKTK")),IF($H$2="Urgent",IF(C6="Jakarta",COUNTIFS('Master Data HO & Site'!$F$1:$F$437,'Summary to Mgmt'!$D6,'Master Data HO & Site'!$H$1:$H$437,'Summary to Mgmt'!$E6,'Master Data HO & Site'!$Y$1:$Y$437,"Open",'Master Data HO & Site'!$N$1:$N$437,$H$2,'Master Data HO & Site'!$D$1:$D$437,"pending FKTK"),COUNTIFS('Master Data HO & Site'!$S$1:$S$437,'Summary to Mgmt'!$C6,'Master Data HO & Site'!$Y$1:$Y$437,"Open",'Master Data HO & Site'!$N$1:$N$437,$H$2,'Master Data HO & Site'!$D$1:$D$437,"pending FKTK")),IF(C6="Jakarta",COUNTIFS('Master Data HO & Site'!$F$1:$F$437,'Summary to Mgmt'!$D6,'Master Data HO & Site'!$H$1:$H$437,'Summary to Mgmt'!$E6,'Master Data HO & Site'!$Y$1:$Y$437,"Open",'Master Data HO & Site'!$N$1:$N$437,$H$2,'Master Data HO & Site'!$D$1:$D$437,"pending FKTK"),COUNTIFS('Master Data HO & Site'!$S$1:$S$437,'Summary to Mgmt'!$C6,'Master Data HO & Site'!$Y$1:$Y$437,"Open",'Master Data HO & Site'!$N$1:$N$437,$H$2,'Master Data HO & Site'!$D$1:$D$437,"pending FKTK")))) -> 0 | J6: =IF($H$2="All",IF(C6="Jakarta",SUMIFS('Master Data HO & Site'!$AB$1:$AB$437,'Master Data HO & Site'!$F$1:$F$437,'Summary to Mgmt'!$D6,'Master Data HO & Site'!$H$1:$H$437,'Summary to Mgmt'!$E6,'Master Data HO & Site'!$Y$1:$Y$437,"Open"),SUMIFS('Master Data HO & Site'!$AB$1:$AB$437,'Master Data HO & Site'!$S$1:$S$437,'Summary to Mgmt'!$C6,'Master Data HO & Site'!$Y$1:$Y$437,"Open")),IF($H$2="Urgent",IF(C6="Jakarta",SUMIFS('Master Data HO & Site'!$AB$1:$AB$437,'Master Data HO & Site'!$F$1:$F$437,'Summary to Mgmt'!$D6,'Master Data HO & Site'!$H$1:$H$437,'Summary to Mgmt'!$E6,'Master Data HO & Site'!$Y$1:$Y$437,"Open",'Master Data HO & Site'!$N$1:$N$437,$H$2),SUMIFS('Master Data HO & Site'!$AB$1:$AB$437,'Master Data HO & Site'!$S$1:$S$437,'Summary to Mgmt'!$C6,'Master Data HO & Site'!$Y$1:$Y$437,"Open",'Master Data HO & Site'!$N$1:$N$437,$H$2)),IF(C6="Jakarta",SUMIFS('Master Data HO & Site'!$AB$1:$AB$437,'Master Data HO & Site'!$F$1:$F$437,'Summary to Mgmt'!$D6,'Master Data HO & Site'!$H$1:$H$437,'Summary to Mgmt'!$E6,'Master Data HO & Site'!$Y$1:$Y$437,"Open",'Master Data HO & Site'!$N$1:$N$437,$H$2),SUMIFS('Master Data HO & Site'!$AB$1:$AB$437,'Master Data HO & Site'!$S$1:$S$437,'Summary to Mgmt'!$C6,'Master Data HO & Site'!$Y$1:$Y$437,"Open",'Master Data HO & Site'!$N$1:$N$437,$H$2)))) -> 8 | K6: =IF($H$2="All",IF(C6="Jakarta",SUMIFS('Master Data HO & Site'!$AC$1:$AC$437,'Master Data HO & Site'!$F$1:$F$437,'Summary to Mgmt'!$D6,'Master Data HO & Site'!$H$1:$H$437,'Summary to Mgmt'!$E6,'Master Data HO & Site'!$Y$1:$Y$437,"Open"),SUMIFS('Master Data HO & Site'!$AC$1:$AC$437,'Master Data HO & Site'!$S$1:$S$437,'Summary to Mgmt'!$C6,'Master Data HO & Site'!$Y$1:$Y$437,"Open")),IF($H$2="Urgent",IF(C6="Jakarta",SUMIFS('Master Data HO & Site'!$AC$1:$AC$437,'Master Data HO & Site'!$F$1:$F$437,'Summary to Mgmt'!$D6,'Master Data HO & Site'!$H$1:$H$437,'Summary to Mgmt'!$E6,'Master Data HO & Site'!$Y$1:$Y$437,"Open",'Master Data HO & Site'!$N$1:$N$437,$H$2),SUMIFS('Master Data HO & Site'!$AC$1:$AC$437,'Master Data HO & Site'!$S$1:$S$437,'Summary to Mgmt'!$C6,'Master Data HO & Site'!$Y$1:$Y$437,"Open",'Master Data HO & Site'!$N$1:$N$437,$H$2)),IF(C6="Jakarta",SUMIFS('Master Data HO & Site'!$AC$1:$AC$437,'Master Data HO & Site'!$F$1:$F$437,'Summary to Mgmt'!$D6,'Master Data HO & Site'!$H$1:$H$437,'Summary to Mgmt'!$E6,'Master Data HO & Site'!$Y$1:$Y$437,"Open",'Master Data HO & Site'!$N$1:$N$437,$H$2),SUMIFS('Master Data HO & Site'!$AC$1:$AC$437,'Master Data HO & Site'!$S$1:$S$437,'Summary to Mgmt'!$C6,'Master Data HO & Site'!$Y$1:$Y$437,"Open",'Master Data HO & Site'!$N$1:$N$437,$H$2)))) -> 0 | L6: =IF($H$2="All",IF(C6="Jakarta",SUMIFS('Master Data HO & Site'!$AD$1:$AD$437,'Master Data HO & Site'!$F$1:$F$437,'Summary to Mgmt'!$D6,'Master Data HO & Site'!$H$1:$H$437,'Summary to Mgmt'!$E6,'Master Data HO & Site'!$Y$1:$Y$437,"Open"),SUMIFS('Master Data HO & Site'!$AD$1:$AD$437,'Master Data HO & Site'!$S$1:$S$437,'Summary to Mgmt'!$C6,'Master Data HO & Site'!$Y$1:$Y$437,"Open")),IF($H$2="Urgent",IF(C6="Jakarta",SUMIFS('Master Data HO & Site'!$AD$1:$AD$437,'Master Data HO & Site'!$F$1:$F$437,'Summary to Mgmt'!$D6,'Master Data HO & Site'!$H$1:$H$437,'Summary to Mgmt'!$E6,'Master Data HO & Site'!$Y$1:$Y$437,"Open",'Master Data HO & Site'!$N$1:$N$437,$H$2),SUMIFS('Master Data HO & Site'!$AD$1:$AD$437,'Master Data HO & Site'!$S$1:$S$437,'Summary to Mgmt'!$C6,'Master Data HO & Site'!$Y$1:$Y$437,"Open",'Master Data HO & Site'!$N$1:$N$437,$H$2)),IF(C6="Jakarta",SUMIFS('Master Data HO & Site'!$AD$1:$AD$437,'Master Data HO & Site'!$F$1:$F$437,'Summary to Mgmt'!$D6,'Master Data HO & Site'!$H$1:$H$437,'Summary to Mgmt'!$E6,'Master Data HO & Site'!$Y$1:$Y$437,"Open",'Master Data HO & Site'!$N$1:$N$437,$H$2),SUMIFS('Master Data HO & Site'!$AD$1:$AD$437,'Master Data HO & Site'!$S$1:$S$437,'Summary to Mgmt'!$C6,'Master Data HO & Site'!$Y$1:$Y$437,"Open",'Master Data HO & Site'!$N$1:$N$437,$H$2)))) -> 2 | M6: =IF($H$2="All",IF(C6="Jakarta",SUMIFS('Master Data HO & Site'!$AE$1:$AE$437,'Master Data HO & Site'!$F$1:$F$437,'Summary to Mgmt'!$D6,'Master Data HO & Site'!$H$1:$H$437,'Summary to Mgmt'!$E6,'Master Data HO & Site'!$Y$1:$Y$437,"Open"),SUMIFS('Master Data HO & Site'!$AE$1:$AE$437,'Master Data HO & Site'!$S$1:$S$437,'Summary to Mgmt'!$C6,'Master Data HO & Site'!$Y$1:$Y$437,"Open")),IF($H$2="Urgent",IF(C6="Jakarta",SUMIFS('Master Data HO & Site'!$AE$1:$AE$437,'Master Data HO & Site'!$F$1:$F$437,'Summary to Mgmt'!$D6,'Master Data HO & Site'!$H$1:$H$437,'Summary to Mgmt'!$E6,'Master Data HO & Site'!$Y$1:$Y$437,"Open",'Master Data HO & Site'!$N$1:$N$437,$H$2),SUMIFS('Master Data HO & Site'!$AE$1:$AE$437,'Master Data HO & Site'!$S$1:$S$437,'Summary to Mgmt'!$C6,'Master Data HO & Site'!$Y$1:$Y$437,"Open",'Master Data HO & Site'!$N$1:$N$437,$H$2)),IF(C6="Jakarta",SUMIFS('Master Data HO & Site'!$AE$1:$AE$437,'Master Data HO & Site'!$F$1:$F$437,'Summary to Mgmt'!$D6,'Master Data HO & Site'!$H$1:$H$437,'Summary to Mgmt'!$E6,'Master Data HO & Site'!$Y$1:$Y$437,"Open",'Master Data HO & Site'!$N$1:$N$437,$H$2),SUMIFS('Master Data HO & Site'!$AE$1:$AE$437,'Master Data HO & Site'!$S$1:$S$437,'Summary to Mgmt'!$C6,'Master Data HO & Site'!$Y$1:$Y$437,"Open",'Master Data HO & Site'!$N$1:$N$437,$H$2)))) -> 0 | N6: =IF($H$2="All",IF(C6="Jakarta",SUMIFS('Master Data HO & Site'!$AF$1:$AF$437,'Master Data HO & Site'!$F$1:$F$437,'Summary to Mgmt'!$D6,'Master Data HO & Site'!$H$1:$H$437,'Summary to Mgmt'!$E6,'Master Data HO & Site'!$Y$1:$Y$437,"Open"),SUMIFS('Master Data HO & Site'!$AF$1:$AF$437,'Master Data HO & Site'!$S$1:$S$437,'Summary to Mgmt'!$C6,'Master Data HO & Site'!$Y$1:$Y$437,"Open")),IF($H$2="Urgent",IF(C6="Jakarta",SUMIFS('Master Data HO & Site'!$AF$1:$AF$437,'Master Data HO & Site'!$F$1:$F$437,'Summary to Mgmt'!$D6,'Master Data HO & Site'!$H$1:$H$437,'Summary to Mgmt'!$E6,'Master Data HO & Site'!$Y$1:$Y$437,"Open",'Master Data HO & Site'!$N$1:$N$437,$H$2),SUMIFS('Master Data HO & Site'!$AF$1:$AF$437,'Master Data HO & Site'!$S$1:$S$437,'Summary to Mgmt'!$C6,'Master Data HO & Site'!$Y$1:$Y$437,"Open",'Master Data HO & Site'!$N$1:$N$437,$H$2)),IF(C6="Jakarta",SUMIFS('Master Data HO & Site'!$AF$1:$AF$437,'Master Data HO & Site'!$F$1:$F$437,'Summary to Mgmt'!$D6,'Master Data HO & Site'!$H$1:$H$437,'Summary to Mgmt'!$E6,'Master Data HO & Site'!$Y$1:$Y$437,"Open",'Master Data HO & Site'!$N$1:$N$437,$H$2),SUMIFS('Master Data HO & Site'!$AF$1:$AF$437,'Master Data HO & Site'!$S$1:$S$437,'Summary to Mgmt'!$C6,'Master Data HO & Site'!$Y$1:$Y$437,"Open",'Master Data HO & Site'!$N$1:$N$437,$H$2)))) -> 0 | O6: =IF($H$2="All",IF(C6="Jakarta",SUMIFS('Master Data HO & Site'!$AG$1:$AG$437,'Master Data HO & Site'!$S$1:$S$437,'Summary to Mgmt'!$C6,'Master Data HO & Site'!$F$1:$F$437,'Summary to Mgmt'!$D6,'Master Data HO & Site'!$H$1:$H$437,'Summary to Mgmt'!$E6,'Master Data HO & Site'!$Y$1:$Y$437,"Open"),SUMIFS('Master Data HO & Site'!$AG$1:$AG$437,'Master Data HO & Site'!$S$1:$S$437,'Summary to Mgmt'!$C6,'Master Data HO & Site'!$Y$1:$Y$437,"Open")),IF($H$2="Urgent",IF(C6="Jakarta",SUMIFS('Master Data HO & Site'!$AG$1:$AG$437,'Master Data HO & Site'!$F$1:$F$437,'Summary to Mgmt'!$D6,'Master Data HO & Site'!$H$1:$H$437,'Summary to Mgmt'!$E6,'Master Data HO & Site'!$Y$1:$Y$437,"Open",'Master Data HO & Site'!$N$1:$N$437,$H$2),SUMIFS('Master Data HO & Site'!$AG$1:$AG$437,'Master Data HO & Site'!$S$1:$S$437,'Summary to Mgmt'!$C6,'Master Data HO & Site'!$Y$1:$Y$437,"Open",'Master Data HO & Site'!$N$1:$N$437,$H$2)),IF(C6="Jakarta",SUMIFS('Master Data HO & Site'!$AG$1:$AG$437,'Master Data HO & Site'!$F$1:$F$437,'Summary to Mgmt'!$D6,'Master Data HO & Site'!$H$1:$H$437,'Summary to Mgmt'!$E6,'Master Data HO & Site'!$Y$1:$Y$437,"Open",'Master Data HO & Site'!$N$1:$N$437,$H$2),SUMIFS('Master Data HO & Site'!$AG$1:$AG$437,'Master Data HO & Site'!$S$1:$S$437,'Summary to Mgmt'!$C6,'Master Data HO & Site'!$Y$1:$Y$437,"Open",'Master Data HO & Site'!$N$1:$N$437,$H$2)))) -> 10 | P6: =IF($H$2="All",IF(C6="Jakarta",SUMIFS('Master Data HO & Site'!$AH$1:$AH$437,'Master Data HO & Site'!$F$1:$F$437,'Summary to Mgmt'!$D6,'Master Data HO & Site'!$H$1:$H$437,'Summary to Mgmt'!$E6,'Master Data HO & Site'!$Y$1:$Y$437,"Open"),SUMIFS('Master Data HO & Site'!$AH$1:$AH$437,'Master Data HO & Site'!$S$1:$S$437,'Summary to Mgmt'!$C6,'Master Data HO & Site'!$Y$1:$Y$437,"Open")),IF($H$2="Urgent",IF(C6="Jakarta",SUMIFS('Master Data HO & Site'!$AH$1:$AH$437,'Master Data HO & Site'!$F$1:$F$437,'Summary to Mgmt'!$D6,'Master Data HO & Site'!$H$1:$H$437,'Summary to Mgmt'!$E6,'Master Data HO & Site'!$Y$1:$Y$437,"Open",'Master Data HO & Site'!$N$1:$N$437,$H$2),SUMIFS('Master Data HO & Site'!$AH$1:$AH$437,'Master Data HO & Site'!$S$1:$S$437,'Summary to Mgmt'!$C6,'Master Data HO & Site'!$Y$1:$Y$437,"Open",'Master Data HO & Site'!$N$1:$N$437,$H$2)),IF(C6="Jakarta",SUMIFS('Master Data HO & Site'!$AH$1:$AH$437,'Master Data HO & Site'!$F$1:$F$437,'Summary to Mgmt'!$D6,'Master Data HO & Site'!$H$1:$H$437,'Summary to Mgmt'!$E6,'Master Data HO & Site'!$Y$1:$Y$437,"Open",'Master Data HO & Site'!$N$1:$N$437,$H$2),SUMIFS('Master Data HO & Site'!$AH$1:$AH$437,'Master Data HO & Site'!$S$1:$S$437,'Summary to Mgmt'!$C6,'Master Data HO & Site'!$Y$1:$Y$437,"Open",'Master Data HO & Site'!$N$1:$N$437,$H$2)))) -> 0 | Q6: =IF($H$2="All",IF(C6="Jakarta",SUMIFS('Master Data HO & Site'!$AI$1:$AI$437,'Master Data HO & Site'!$F$1:$F$437,'Summary to Mgmt'!$D6,'Master Data HO & Site'!$H$1:$H$437,'Summary to Mgmt'!$E6,'Master Data HO & Site'!$Y$1:$Y$437,"Open"),SUMIFS('Master Data HO & Site'!$AI$1:$AI$437,'Master Data HO & Site'!$S$1:$S$437,'Summary to Mgmt'!$C6,'Master Data HO & Site'!$Y$1:$Y$437,"Open")),IF($H$2="Urgent",IF(C6="Jakarta",SUMIFS('Master Data HO & Site'!$AI$1:$AI$437,'Master Data HO & Site'!$F$1:$F$437,'Summary to Mgmt'!$D6,'Master Data HO & Site'!$H$1:$H$437,'Summary to Mgmt'!$E6,'Master Data HO & Site'!$Y$1:$Y$437,"Open",'Master Data HO & Site'!$N$1:$N$437,$H$2),SUMIFS('Master Data HO & Site'!$AI$1:$AI$437,'Master Data HO & Site'!$S$1:$S$437,'Summary to Mgmt'!$C6,'Master Data HO & Site'!$Y$1:$Y$437,"Open",'Master Data HO & Site'!$N$1:$N$437,$H$2)),IF(C6="Jakarta",SUMIFS('Master Data HO & Site'!$AI$1:$AI$437,'Master Data HO & Site'!$F$1:$F$437,'Summary to Mgmt'!$D6,'Master Data HO & Site'!$H$1:$H$437,'Summary to Mgmt'!$E6,'Master Data HO & Site'!$Y$1:$Y$437,"Open",'Master Data HO & Site'!$N$1:$N$437,$H$2),SUMIFS('Master Data HO & Site'!$AI$1:$AI$437,'Master Data HO & Site'!$S$1:$S$437,'Summary to Mgmt'!$C6,'Master Data HO & Site'!$Y$1:$Y$437,"Open",'Master Data HO & Site'!$N$1:$N$437,$H$2)))) -> 2 | R6: =IF($H$2="All",IF(C6="Jakarta",SUMIFS('Master Data HO & Site'!$AJ$1:$AJ$437,'Master Data HO & Site'!$F$1:$F$437,'Summary to Mgmt'!$D6,'Master Data HO & Site'!$H$1:$H$437,'Summary to Mgmt'!$E6,'Master Data HO & Site'!$Y$1:$Y$437,"Open"),SUMIFS('Master Data HO & Site'!$AJ$1:$AJ$437,'Master Data HO & Site'!$S$1:$S$437,'Summary to Mgmt'!$C6,'Master Data HO & Site'!$Y$1:$Y$437,"Open")),IF($H$2="Urgent",IF(C6="Jakarta",SUMIFS('Master Data HO & Site'!$AJ$1:$AJ$437,'Master Data HO & Site'!$F$1:$F$437,'Summary to Mgmt'!$D6,'Master Data HO & Site'!$H$1:$H$437,'Summary to Mgmt'!$E6,'Master Data HO & Site'!$Y$1:$Y$437,"Open",'Master Data HO & Site'!$N$1:$N$437,$H$2),SUMIFS('Master Data HO & Site'!$AJ$1:$AJ$437,'Master Data HO & Site'!$S$1:$S$437,'Summary to Mgmt'!$C6,'Master Data HO & Site'!$Y$1:$Y$437,"Open",'Master Data HO & Site'!$N$1:$N$437,$H$2)),IF(C6="Jakarta",SUMIFS('Master Data HO & Site'!$AJ$1:$AJ$437,'Master Data HO & Site'!$F$1:$F$437,'Summary to Mgmt'!$D6,'Master Data HO & Site'!$H$1:$H$437,'Summary to Mgmt'!$E6,'Master Data HO & Site'!$Y$1:$Y$437,"Open",'Master Data HO & Site'!$N$1:$N$437,$H$2),SUMIFS('Master Data HO & Site'!$AJ$1:$AJ$437,'Master Data HO & Site'!$S$1:$S$437,'Summary to Mgmt'!$C6,'Master Data HO & Site'!$Y$1:$Y$437,"Open",'Master Data HO & Site'!$N$1:$N$437,$H$2)))) -> 1 | S6: =IF($H$2="All",IF(C6="Jakarta",SUMIFS('Master Data HO & Site'!$AK$1:$AK$437,'Master Data HO & Site'!$F$1:$F$437,'Summary to Mgmt'!$D6,'Master Data HO & Site'!$H$1:$H$437,'Summary to Mgmt'!$E6,'Master Data HO & Site'!$Y$1:$Y$437,"Open"),SUMIFS('Master Data HO & Site'!$AK$1:$AK$437,'Master Data HO & Site'!$S$1:$S$437,'Summary to Mgmt'!$C6,'Master Data HO & Site'!$Y$1:$Y$437,"Open")),IF($H$2="Urgent",IF(C6="Jakarta",SUMIFS('Master Data HO & Site'!$AK$1:$AK$437,'Master Data HO & Site'!$F$1:$F$437,'Summary to Mgmt'!$D6,'Master Data HO & Site'!$H$1:$H$437,'Summary to Mgmt'!$E6,'Master Data HO & Site'!$Y$1:$Y$437,"Open",'Master Data HO & Site'!$N$1:$N$437,$H$2),SUMIFS('Master Data HO & Site'!$AK$1:$AK$437,'Master Data HO & Site'!$S$1:$S$437,'Summary to Mgmt'!$C6,'Master Data HO & Site'!$Y$1:$Y$437,"Open",'Master Data HO & Site'!$N$1:$N$437,$H$2)),IF(C6="Jakarta",SUMIFS('Master Data HO & Site'!$AK$1:$AK$437,'Master Data HO & Site'!$F$1:$F$437,'Summary to Mgmt'!$D6,'Master Data HO & Site'!$H$1:$H$437,'Summary to Mgmt'!$E6,'Master Data HO & Site'!$Y$1:$Y$437,"Open",'Master Data HO & Site'!$N$1:$N$437,$H$2),SUMIFS('Master Data HO & Site'!$AK$1:$AK$437,'Master Data HO & Site'!$S$1:$S$437,'Summary to Mgmt'!$C6,'Master Data HO & Site'!$Y$1:$Y$437,"Open",'Master Data HO & Site'!$N$1:$N$437,$H$2)))) -> 0 | T6: =IF($H$2="All",IF(C6="Jakarta",SUMIFS('Master Data HO & Site'!$AL$1:$AL$437,'Master Data HO & Site'!$F$1:$F$437,'Summary to Mgmt'!$D6,'Master Data HO & Site'!$H$1:$H$437,'Summary to Mgmt'!$E6,'Master Data HO & Site'!$Y$1:$Y$437,"Open"),SUMIFS('Master Data HO & Site'!$AL$1:$AL$437,'Master Data HO & Site'!$S$1:$S$437,'Summary to Mgmt'!$C6,'Master Data HO & Site'!$Y$1:$Y$437,"Open")),IF($H$2="Urgent",IF(C6="Jakarta",SUMIFS('Master Data HO & Site'!$AL$1:$AL$437,'Master Data HO & Site'!$F$1:$F$437,'Summary to Mgmt'!$D6,'Master Data HO & Site'!$H$1:$H$437,'Summary to Mgmt'!$E6,'Master Data HO & Site'!$Y$1:$Y$437,"Open",'Master Data HO & Site'!$N$1:$N$437,$H$2),SUMIFS('Master Data HO & Site'!$AL$1:$AL$437,'Master Data HO & Site'!$S$1:$S$437,'Summary to Mgmt'!$C6,'Master Data HO & Site'!$Y$1:$Y$437,"Open",'Master Data HO & Site'!$N$1:$N$437,$H$2)),IF(C6="Jakarta",SUMIFS('Master Data HO & Site'!$AL$1:$AL$437,'Master Data HO & Site'!$F$1:$F$437,'Summary to Mgmt'!$D6,'Master Data HO & Site'!$H$1:$H$437,'Summary to Mgmt'!$E6,'Master Data HO & Site'!$Y$1:$Y$437,"Open",'Master Data HO & Site'!$N$1:$N$437,$H$2),SUMIFS('Master Data HO & Site'!$AL$1:$AL$437,'Master Data HO & Site'!$S$1:$S$437,'Summary to Mgmt'!$C6,'Master Data HO & Site'!$Y$1:$Y$437,"Open",'Master Data HO & Site'!$N$1:$N$437,$H$2)))) -> 0 | U6: =IF($H$2="All",IF(C6="Jakarta",SUMIFS('Master Data HO & Site'!$AM$1:$AM$437,'Master Data HO & Site'!$S$1:$S$437,'Summary to Mgmt'!$C6,'Master Data HO & Site'!$F$1:$F$437,'Summary to Mgmt'!$D6,'Master Data HO & Site'!$H$1:$H$437,'Summary to Mgmt'!$E6,'Master Data HO & Site'!$Y$1:$Y$437,"Open"),SUMIFS('Master Data HO & Site'!$AM$1:$AM$437,'Master Data HO & Site'!$S$1:$S$437,'Summary to Mgmt'!$C6,'Master Data HO & Site'!$Y$1:$Y$437,"Open")),IF($H$2="Urgent",IF(C6="Jakarta",SUMIFS('Master Data HO & Site'!$AM$1:$AM$437,'Master Data HO & Site'!$F$1:$F$437,'Summary to Mgmt'!$D6,'Master Data HO & Site'!$H$1:$H$437,'Summary to Mgmt'!$E6,'Master Data HO & Site'!$Y$1:$Y$437,"Open",'Master Data HO & Site'!$N$1:$N$437,$H$2),SUMIFS('Master Data HO & Site'!$AM$1:$AM$437,'Master Data HO & Site'!$S$1:$S$437,'Summary to Mgmt'!$C6,'Master Data HO & Site'!$Y$1:$Y$437,"Open",'Master Data HO & Site'!$N$1:$N$437,$H$2)),IF(C6="Jakarta",SUMIFS('Master Data HO & Site'!$AM$1:$AM$437,'Master Data HO & Site'!$F$1:$F$437,'Summary to Mgmt'!$D6,'Master Data HO & Site'!$H$1:$H$437,'Summary to Mgmt'!$E6,'Master Data HO & Site'!$Y$1:$Y$437,"Open",'Master Data HO & Site'!$N$1:$N$437,$H$2),SUMIFS('Master Data HO & Site'!$AM$1:$AM$437,'Master Data HO & Site'!$S$1:$S$437,'Summary to Mgmt'!$C6,'Master Data HO & Site'!$Y$1:$Y$437,"Open",'Master Data HO & Site'!$N$1:$N$437,$H$2)))) -> 3 | V6: =IF($H$2="All",IF(C6="Jakarta",SUMIFS('Master Data HO & Site'!$AN$1:$AN$437,'Master Data HO & Site'!$F$1:$F$437,'Summary to Mgmt'!$D6,'Master Data HO & Site'!$H$1:$H$437,'Summary to Mgmt'!$E6,'Master Data HO & Site'!$Y$1:$Y$437,"Open"),SUMIFS('Master Data HO & Site'!$AN$1:$AN$437,'Master Data HO & Site'!$S$1:$S$437,'Summary to Mgmt'!$C6,'Master Data HO & Site'!$Y$1:$Y$437,"Open")),IF($H$2="Urgent",IF(C6="Jakarta",SUMIFS('Master Data HO & Site'!$AN$1:$AN$437,'Master Data HO & Site'!$F$1:$F$437,'Summary to Mgmt'!$D6,'Master Data HO & Site'!$H$1:$H$437,'Summary to Mgmt'!$E6,'Master Data HO & Site'!$Y$1:$Y$437,"Open",'Master Data HO & Site'!$N$1:$N$437,$H$2),SUMIFS('Master Data HO & Site'!$AN$1:$AN$437,'Master Data HO & Site'!$S$1:$S$437,'Summary to Mgmt'!$C6,'Master Data HO & Site'!$Y$1:$Y$437,"Open",'Master Data HO & Site'!$N$1:$N$437,$H$2)),IF(C6="Jakarta",SUMIFS('Master Data HO & Site'!$AN$1:$AN$437,'Master Data HO & Site'!$F$1:$F$437,'Summary to Mgmt'!$D6,'Master Data HO & Site'!$H$1:$H$437,'Summary to Mgmt'!$E6,'Master Data HO & Site'!$Y$1:$Y$437,"Open",'Master Data HO & Site'!$N$1:$N$437,$H$2),SUMIFS('Master Data HO & Site'!$AN$1:$AN$437,'Master Data HO & Site'!$S$1:$S$437,'Summary to Mgmt'!$C6,'Master Data HO & Site'!$Y$1:$Y$437,"Open",'Master Data HO & Site'!$N$1:$N$437,$H$2)))) -> 0 | W6: =IF($H$2="All",IF(C6="Jakarta",SUMIFS('Master Data HO & Site'!$AO$1:$AO$437,'Master Data HO & Site'!$F$1:$F$437,'Summary to Mgmt'!$D6,'Master Data HO & Site'!$H$1:$H$437,'Summary to Mgmt'!$E6,'Master Data HO & Site'!$Y$1:$Y$437,"Open"),SUMIFS('Master Data HO & Site'!$AO$1:$AO$437,'Master Data HO & Site'!$S$1:$S$437,'Summary to Mgmt'!$C6,'Master Data HO & Site'!$Y$1:$Y$437,"Open")),IF($H$2="Urgent",IF(C6="Jakarta",SUMIFS('Master Data HO & Site'!$AO$1:$AO$437,'Master Data HO & Site'!$F$1:$F$437,'Summary to Mgmt'!$D6,'Master Data HO & Site'!$H$1:$H$437,'Summary to Mgmt'!$E6,'Master Data HO & Site'!$Y$1:$Y$437,"Open",'Master Data HO & Site'!$N$1:$N$437,$H$2),SUMIFS('Master Data HO & Site'!$AO$1:$AO$437,'Master Data HO & Site'!$S$1:$S$437,'Summary to Mgmt'!$C6,'Master Data HO & Site'!$Y$1:$Y$437,"Open",'Master Data HO & Site'!$N$1:$N$437,$H$2)),IF(C6="Jakarta",SUMIFS('Master Data HO & Site'!$AO$1:$AO$437,'Master Data HO & Site'!$F$1:$F$437,'Summary to Mgmt'!$D6,'Master Data HO & Site'!$H$1:$H$437,'Summary to Mgmt'!$E6,'Master Data HO & Site'!$Y$1:$Y$437,"Open",'Master Data HO & Site'!$N$1:$N$437,$H$2),SUMIFS('Master Data HO & Site'!$AO$1:$AO$437,'Master Data HO & Site'!$S$1:$S$437,'Summary to Mgmt'!$C6,'Master Data HO & Site'!$Y$1:$Y$437,"Open",'Master Data HO & Site'!$N$1:$N$437,$H$2)))) -> 0 | X6: =IF($H$2="All",IF(C6="Jakarta",SUMIFS('Master Data HO & Site'!$AP$1:$AP$437,'Master Data HO & Site'!$F$1:$F$437,'Summary to Mgmt'!$D6,'Master Data HO & Site'!$H$1:$H$437,'Summary to Mgmt'!$E6,'Master Data HO & Site'!$Y$1:$Y$437,"Open"),SUMIFS('Master Data HO & Site'!$AP$1:$AP$437,'Master Data HO & Site'!$S$1:$S$437,'Summary to Mgmt'!$C6,'Master Data HO & Site'!$Y$1:$Y$437,"Open")),IF($H$2="Urgent",IF(C6="Jakarta",SUMIFS('Master Data HO & Site'!$AP$1:$AP$437,'Master Data HO & Site'!$F$1:$F$437,'Summary to Mgmt'!$D6,'Master Data HO & Site'!$H$1:$H$437,'Summary to Mgmt'!$E6,'Master Data HO & Site'!$Y$1:$Y$437,"Open",'Master Data HO & Site'!$N$1:$N$437,$H$2),SUMIFS('Master Data HO & Site'!$AP$1:$AP$437,'Master Data HO & Site'!$S$1:$S$437,'Summary to Mgmt'!$C6,'Master Data HO & Site'!$Y$1:$Y$437,"Open",'Master Data HO & Site'!$N$1:$N$437,$H$2)),IF(C6="Jakarta",SUMIFS('Master Data HO & Site'!$AP$1:$AP$437,'Master Data HO & Site'!$F$1:$F$437,'Summary to Mgmt'!$D6,'Master Data HO & Site'!$H$1:$H$437,'Summary to Mgmt'!$E6,'Master Data HO & Site'!$Y$1:$Y$437,"Open",'Master Data HO & Site'!$N$1:$N$437,$H$2),SUMIFS('Master Data HO & Site'!$AP$1:$AP$437,'Master Data HO & Site'!$S$1:$S$437,'Summary to Mgmt'!$C6,'Master Data HO & Site'!$Y$1:$Y$437,"Open",'Master Data HO & Site'!$N$1:$N$437,$H$2)))) -> 1 | Y6: =IF($H$2="All",IF(C6="Jakarta",SUMIFS('Master Data HO & Site'!$AQ$1:$AQ$437,'Master Data HO & Site'!$F$1:$F$437,'Summary to Mgmt'!$D6,'Master Data HO & Site'!$H$1:$H$437,'Summary to Mgmt'!$E6,'Master Data HO & Site'!$Y$1:$Y$437,"Open"),SUMIFS('Master Data HO & Site'!$AQ$1:$AQ$437,'Master Data HO & Site'!$S$1:$S$437,'Summary to Mgmt'!$C6,'Master Data HO & Site'!$Y$1:$Y$437,"Open")),IF($H$2="Urgent",IF(C6="Jakarta",SUMIFS('Master Data HO & Site'!$AQ$1:$AQ$437,'Master Data HO & Site'!$F$1:$F$437,'Summary to Mgmt'!$D6,'Master Data HO & Site'!$H$1:$H$437,'Summary to Mgmt'!$E6,'Master Data HO & Site'!$Y$1:$Y$437,"Open",'Master Data HO & Site'!$N$1:$N$437,$H$2),SUMIFS('Master Data HO & Site'!$AQ$1:$AQ$437,'Master Data HO & Site'!$S$1:$S$437,'Summary to Mgmt'!$C6,'Master Data HO & Site'!$Y$1:$Y$437,"Open",'Master Data HO & Site'!$N$1:$N$437,$H$2)),IF(C6="Jakarta",SUMIFS('Master Data HO & Site'!$AQ$1:$AQ$437,'Master Data HO & Site'!$F$1:$F$437,'Summary to Mgmt'!$D6,'Master Data HO & Site'!$H$1:$H$437,'Summary to Mgmt'!$E6,'Master Data HO & Site'!$Y$1:$Y$437,"Open",'Master Data HO & Site'!$N$1:$N$437,$H$2),SUMIFS('Master Data HO & Site'!$AQ$1:$AQ$437,'Master Data HO & Site'!$S$1:$S$437,'Summary to Mgmt'!$C6,'Master Data HO & Site'!$Y$1:$Y$437,"Open",'Master Data HO & Site'!$N$1:$N$437,$H$2)))) -> 0 | Z6: =IF($H$2="All",IF(C6="Jakarta",SUMIFS('Master Data HO & Site'!$AR$1:$AR$437,'Master Data HO & Site'!$F$1:$F$437,'Summary to Mgmt'!$D6,'Master Data HO & Site'!$H$1:$H$437,'Summary to Mgmt'!$E6,'Master Data HO & Site'!$Y$1:$Y$437,"Open"),SUMIFS('Master Data HO & Site'!$AR$1:$AR$437,'Master Data HO & Site'!$S$1:$S$437,'Summary to Mgmt'!$C6,'Master Data HO & Site'!$Y$1:$Y$437,"Open")),IF($H$2="Urgent",IF(C6="Jakarta",SUMIFS('Master Data HO & Site'!$AR$1:$AR$437,'Master Data HO & Site'!$F$1:$F$437,'Summary to Mgmt'!$D6,'Master Data HO & Site'!$H$1:$H$437,'Summary to Mgmt'!$E6,'Master Data HO & Site'!$Y$1:$Y$437,"Open",'Master Data HO & Site'!$N$1:$N$437,$H$2),SUMIFS('Master Data HO & Site'!$AR$1:$AR$437,'Master Data HO & Site'!$S$1:$S$437,'Summary to Mgmt'!$C6,'Master Data HO & Site'!$Y$1:$Y$437,"Open",'Master Data HO & Site'!$N$1:$N$437,$H$2)),IF(C6="Jakarta",SUMIFS('Master Data HO & Site'!$AR$1:$AR$437,'Master Data HO & Site'!$F$1:$F$437,'Summary to Mgmt'!$D6,'Master Data HO & Site'!$H$1:$H$437,'Summary to Mgmt'!$E6,'Master Data HO & Site'!$Y$1:$Y$437,"Open",'Master Data HO & Site'!$N$1:$N$437,$H$2),SUMIFS('Master Data HO & Site'!$AR$1:$AR$437,'Master Data HO & Site'!$S$1:$S$437,'Summary to Mgmt'!$C6,'Master Data HO & Site'!$Y$1:$Y$437,"Open",'Master Data HO & Site'!$N$1:$N$437,$H$2)))) -> 0 | AA6: =IF($H$2="All",IF(C6="Jakarta",SUMIFS('Master Data HO & Site'!$AS$1:$AS$437,'Master Data HO & Site'!$S$1:$S$437,'Summary to Mgmt'!$C6,'Master Data HO & Site'!$F$1:$F$437,'Summary to Mgmt'!$D6,'Master Data HO & Site'!$H$1:$H$437,'Summary to Mgmt'!$E6,'Master Data HO & Site'!$Y$1:$Y$437,"Open"),SUMIFS('Master Data HO & Site'!$AS$1:$AS$437,'Master Data HO & Site'!$S$1:$S$437,'Summary to Mgmt'!$C6,'Master Data HO & Site'!$Y$1:$Y$437,"Open")),IF($H$2="Urgent",IF(C6="Jakarta",SUMIFS('Master Data HO & Site'!$AS$1:$AS$437,'Master Data HO & Site'!$F$1:$F$437,'Summary to Mgmt'!$D6,'Master Data HO & Site'!$H$1:$H$437,'Summary to Mgmt'!$E6,'Master Data HO & Site'!$Y$1:$Y$437,"Open",'Master Data HO & Site'!$N$1:$N$437,$H$2),SUMIFS('Master Data HO & Site'!$AS$1:$AS$437,'Master Data HO & Site'!$S$1:$S$437,'Summary to Mgmt'!$C6,'Master Data HO & Site'!$Y$1:$Y$437,"Open",'Master Data HO & Site'!$N$1:$N$437,$H$2)),IF(C6="Jakarta",SUMIFS('Master Data HO & Site'!$AS$1:$AS$437,'Master Data HO & Site'!$F$1:$F$437,'Summary to Mgmt'!$D6,'Master Data HO & Site'!$H$1:$H$437,'Summary to Mgmt'!$E6,'Master Data HO & Site'!$Y$1:$Y$437,"Open",'Master Data HO & Site'!$N$1:$N$437,$H$2),SUMIFS('Master Data HO & Site'!$AS$1:$AS$437,'Master Data HO & Site'!$S$1:$S$437,'Summary to Mgmt'!$C6,'Master Data HO & Site'!$Y$1:$Y$437,"Open",'Master Data HO & Site'!$N$1:$N$437,$H$2)))) -> 1 | AB6: =IF($H$2="All",IF(C6="Jakarta",SUMIFS('Master Data HO & Site'!$AT$1:$AT$437,'Master Data HO & Site'!$F$1:$F$437,'Summary to Mgmt'!$D6,'Master Data HO & Site'!$H$1:$H$437,'Summary to Mgmt'!$E6,'Master Data HO & Site'!$Y$1:$Y$437,"Open"),SUMIFS('Master Data HO & Site'!$AT$1:$AT$437,'Master Data HO & Site'!$S$1:$S$437,'Summary to Mgmt'!$C6,'Master Data HO & Site'!$Y$1:$Y$437,"Open")),IF($H$2="Urgent",IF(C6="Jakarta",SUMIFS('Master Data HO & Site'!$AT$1:$AT$437,'Master Data HO & Site'!$F$1:$F$437,'Summary to Mgmt'!$D6,'Master Data HO & Site'!$H$1:$H$437,'Summary to Mgmt'!$E6,'Master Data HO & Site'!$Y$1:$Y$437,"Open",'Master Data HO & Site'!$N$1:$N$437,$H$2),SUMIFS('Master Data HO & Site'!$AT$1:$AT$437,'Master Data HO & Site'!$S$1:$S$437,'Summary to Mgmt'!$C6,'Master Data HO & Site'!$Y$1:$Y$437,"Open",'Master Data HO & Site'!$N$1:$N$437,$H$2)),IF(C6="Jakarta",SUMIFS('Master Data HO & Site'!$AT$1:$AT$437,'Master Data HO & Site'!$F$1:$F$437,'Summary to Mgmt'!$D6,'Master Data HO & Site'!$H$1:$H$437,'Summary to Mgmt'!$E6,'Master Data HO & Site'!$Y$1:$Y$437,"Open",'Master Data HO & Site'!$N$1:$N$437,$H$2),SUMIFS('Master Data HO & Site'!$AT$1:$AT$437,'Master Data HO & Site'!$S$1:$S$437,'Summary to Mgmt'!$C6,'Master Data HO & Site'!$Y$1:$Y$437,"Open",'Master Data HO & Site'!$N$1:$N$437,$H$2)))) -> 0 | AC6: =IF($H$2="All",IF(C6="Jakarta",SUMIFS('Master Data HO & Site'!$AU$1:$AU$437,'Master Data HO & Site'!$F$1:$F$437,'Summary to Mgmt'!$D6,'Master Data HO & Site'!$H$1:$H$437,'Summary to Mgmt'!$E6,'Master Data HO & Site'!$Y$1:$Y$437,"Open"),SUMIFS('Master Data HO & Site'!$AU$1:$AU$437,'Master Data HO & Site'!$S$1:$S$437,'Summary to Mgmt'!$C6,'Master Data HO & Site'!$Y$1:$Y$437,"Open")),IF($H$2="Urgent",IF(C6="Jakarta",SUMIFS('Master Data HO & Site'!$AU$1:$AU$437,'Master Data HO & Site'!$F$1:$F$437,'Summary to Mgmt'!$D6,'Master Data HO & Site'!$H$1:$H$437,'Summary to Mgmt'!$E6,'Master Data HO & Site'!$Y$1:$Y$437,"Open",'Master Data HO & Site'!$N$1:$N$437,$H$2),SUMIFS('Master Data HO & Site'!$AU$1:$AU$437,'Master Data HO & Site'!$S$1:$S$437,'Summary to Mgmt'!$C6,'Master Data HO & Site'!$Y$1:$Y$437,"Open",'Master Data HO & Site'!$N$1:$N$437,$H$2)),IF(C6="Jakarta",SUMIFS('Master Data HO & Site'!$AU$1:$AU$437,'Master Data HO & Site'!$F$1:$F$437,'Summary to Mgmt'!$D6,'Master Data HO & Site'!$H$1:$H$437,'Summary to Mgmt'!$E6,'Master Data HO & Site'!$Y$1:$Y$437,"Open",'Master Data HO & Site'!$N$1:$N$437,$H$2),SUMIFS('Master Data HO & Site'!$AU$1:$AU$437,'Master Data HO & Site'!$S$1:$S$437,'Summary to Mgmt'!$C6,'Master Data HO & Site'!$Y$1:$Y$437,"Open",'Master Data HO & Site'!$N$1:$N$437,$H$2)))) -> 0 | AD6: =IF($H$2="All",IF(C6="Jakarta",SUMIFS('Master Data HO & Site'!$AV$1:$AV$437,'Master Data HO & Site'!$F$1:$F$437,'Summary to Mgmt'!$D6,'Master Data HO & Site'!$H$1:$H$437,'Summary to Mgmt'!$E6,'Master Data HO & Site'!$Y$1:$Y$437,"Open"),SUMIFS('Master Data HO & Site'!$AV$1:$AV$437,'Master Data HO & Site'!$S$1:$S$437,'Summary to Mgmt'!$C6,'Master Data HO & Site'!$Y$1:$Y$437,"Open")),IF($H$2="Urgent",IF(C6="Jakarta",SUMIFS('Master Data HO & Site'!$AV$1:$AV$437,'Master Data HO & Site'!$F$1:$F$437,'Summary to Mgmt'!$D6,'Master Data HO & Site'!$H$1:$H$437,'Summary to Mgmt'!$E6,'Master Data HO & Site'!$Y$1:$Y$437,"Open",'Master Data HO & Site'!$N$1:$N$437,$H$2),SUMIFS('Master Data HO & Site'!$AV$1:$AV$437,'Master Data HO & Site'!$S$1:$S$437,'Summary to Mgmt'!$C6,'Master Data HO & Site'!$Y$1:$Y$437,"Open",'Master Data HO & Site'!$N$1:$N$437,$H$2)),IF(C6="Jakarta",SUMIFS('Master Data HO & Site'!$AV$1:$AV$437,'Master Data HO & Site'!$F$1:$F$437,'Summary to Mgmt'!$D6,'Master Data HO & Site'!$H$1:$H$437,'Summary to Mgmt'!$E6,'Master Data HO & Site'!$Y$1:$Y$437,"Open",'Master Data HO & Site'!$N$1:$N$437,$H$2),SUMIFS('Master Data HO & Site'!$AV$1:$AV$437,'Master Data HO & Site'!$S$1:$S$437,'Summary to Mgmt'!$C6,'Master Data HO & Site'!$Y$1:$Y$437,"Open",'Master Data HO & Site'!$N$1:$N$437,$H$2)))) -> 0 | AE6: =IF($H$2="All",IF(C6="Jakarta",SUMIFS('Master Data HO & Site'!$AW$1:$AW$437,'Master Data HO & Site'!$F$1:$F$437,'Summary to Mgmt'!$D6,'Master Data HO & Site'!$H$1:$H$437,'Summary to Mgmt'!$E6,'Master Data HO & Site'!$Y$1:$Y$437,"Open"),SUMIFS('Master Data HO & Site'!$AW$1:$AW$437,'Master Data HO & Site'!$S$1:$S$437,'Summary to Mgmt'!$C6,'Master Data HO & Site'!$Y$1:$Y$437,"Open")),IF($H$2="Urgent",IF(C6="Jakarta",SUMIFS('Master Data HO & Site'!$AW$1:$AW$437,'Master Data HO & Site'!$F$1:$F$437,'Summary to Mgmt'!$D6,'Master Data HO & Site'!$H$1:$H$437,'Summary to Mgmt'!$E6,'Master Data HO & Site'!$Y$1:$Y$437,"Open",'Master Data HO & Site'!$N$1:$N$437,$H$2),SUMIFS('Master Data HO & Site'!$AW$1:$AW$437,'Master Data HO & Site'!$S$1:$S$437,'Summary to Mgmt'!$C6,'Master Data HO & Site'!$Y$1:$Y$437,"Open",'Master Data HO & Site'!$N$1:$N$437,$H$2)),IF(C6="Jakarta",SUMIFS('Master Data HO & Site'!$AW$1:$AW$437,'Master Data HO & Site'!$F$1:$F$437,'Summary to Mgmt'!$D6,'Master Data HO & Site'!$H$1:$H$437,'Summary to Mgmt'!$E6,'Master Data HO & Site'!$Y$1:$Y$437,"Open",'Master Data HO & Site'!$N$1:$N$437,$H$2),SUMIFS('Master Data HO & Site'!$AW$1:$AW$437,'Master Data HO & Site'!$S$1:$S$437,'Summary to Mgmt'!$C6,'Master Data HO & Site'!$Y$1:$Y$437,"Open",'Master Data HO & Site'!$N$1:$N$437,$H$2)))) -> 0 | AF6: =IF($H$2="All",IF(C6="Jakarta",SUMIFS('Master Data HO & Site'!$AX$1:$AX$437,'Master Data HO & Site'!$F$1:$F$437,'Summary to Mgmt'!$D6,'Master Data HO & Site'!$H$1:$H$437,'Summary to Mgmt'!$E6,'Master Data HO & Site'!$Y$1:$Y$437,"Open"),SUMIFS('Master Data HO & Site'!$AX$1:$AX$437,'Master Data HO & Site'!$S$1:$S$437,'Summary to Mgmt'!$C6,'Master Data HO & Site'!$Y$1:$Y$437,"Open")),IF($H$2="Urgent",IF(C6="Jakarta",SUMIFS('Master Data HO & Site'!$AX$1:$AX$437,'Master Data HO & Site'!$F$1:$F$437,'Summary to Mgmt'!$D6,'Master Data HO & Site'!$H$1:$H$437,'Summary to Mgmt'!$E6,'Master Data HO & Site'!$Y$1:$Y$437,"Open",'Master Data HO & Site'!$N$1:$N$437,$H$2),SUMIFS('Master Data HO & Site'!$AX$1:$AX$437,'Master Data HO & Site'!$S$1:$S$437,'Summary to Mgmt'!$C6,'Master Data HO & Site'!$Y$1:$Y$437,"Open",'Master Data HO & Site'!$N$1:$N$437,$H$2)),IF(C6="Jakarta",SUMIFS('Master Data HO & Site'!$AX$1:$AX$437,'Master Data HO & Site'!$F$1:$F$437,'Summary to Mgmt'!$D6,'Master Data HO & Site'!$H$1:$H$437,'Summary to Mgmt'!$E6,'Master Data HO & Site'!$Y$1:$Y$437,"Open",'Master Data HO & Site'!$N$1:$N$437,$H$2),SUMIFS('Master Data HO & Site'!$AX$1:$AX$437,'Master Data HO & Site'!$S$1:$S$437,'Summary to Mgmt'!$C6,'Master Data HO & Site'!$Y$1:$Y$437,"Open",'Master Data HO & Site'!$N$1:$N$437,$H$2)))) -> 0 | AG6: =IF($H$2="All",IF(C6="Jakarta",SUMIFS('Master Data HO & Site'!$AY$1:$AY$437,'Master Data HO & Site'!$S$1:$S$437,'Summary to Mgmt'!$C6,'Master Data HO & Site'!$F$1:$F$437,'Summary to Mgmt'!$D6,'Master Data HO & Site'!$H$1:$H$437,'Summary to Mgmt'!$E6,'Master Data HO & Site'!$Y$1:$Y$437,"Open"),SUMIFS('Master Data HO & Site'!$AY$1:$AY$437,'Master Data HO & Site'!$S$1:$S$437,'Summary to Mgmt'!$C6,'Master Data HO & Site'!$Y$1:$Y$437,"Open")),IF($H$2="Urgent",IF(C6="Jakarta",SUMIFS('Master Data HO & Site'!$AY$1:$AY$437,'Master Data HO & Site'!$F$1:$F$437,'Summary to Mgmt'!$D6,'Master Data HO & Site'!$H$1:$H$437,'Summary to Mgmt'!$E6,'Master Data HO & Site'!$Y$1:$Y$437,"Open",'Master Data HO & Site'!$N$1:$N$437,$H$2),SUMIFS('Master Data HO & Site'!$AY$1:$AY$437,'Master Data HO & Site'!$S$1:$S$437,'Summary to Mgmt'!$C6,'Master Data HO & Site'!$Y$1:$Y$437,"Open",'Master Data HO & Site'!$N$1:$N$437,$H$2)),IF(C6="Jakarta",SUMIFS('Master Data HO & Site'!$AY$1:$AY$437,'Master Data HO & Site'!$F$1:$F$437,'Summary to Mgmt'!$D6,'Master Data HO & Site'!$H$1:$H$437,'Summary to Mgmt'!$E6,'Master Data HO & Site'!$Y$1:$Y$437,"Open",'Master Data HO & Site'!$N$1:$N$437,$H$2),SUMIFS('Master Data HO & Site'!$AY$1:$AY$437,'Master Data HO & Site'!$S$1:$S$437,'Summary to Mgmt'!$C6,'Master Data HO & Site'!$Y$1:$Y$437,"Open",'Master Data HO & Site'!$N$1:$N$437,$H$2)))) -> 0 | AH6: =IF($H$2="All",IF(C6="Jakarta",SUMIFS('Master Data HO & Site'!$AZ$1:$AZ$437,'Master Data HO & Site'!$F$1:$F$437,'Summary to Mgmt'!$D6,'Master Data HO & Site'!$H$1:$H$437,'Summary to Mgmt'!$E6,'Master Data HO & Site'!$Y$1:$Y$437,"Open"),SUMIFS('Master Data HO & Site'!$AZ$1:$AZ$437,'Master Data HO & Site'!$S$1:$S$437,'Summary to Mgmt'!$C6,'Master Data HO & Site'!$Y$1:$Y$437,"Open")),IF($H$2="Urgent",IF(C6="Jakarta",SUMIFS('Master Data HO & Site'!$AZ$1:$AZ$437,'Master Data HO & Site'!$F$1:$F$437,'Summary to Mgmt'!$D6,'Master Data HO & Site'!$H$1:$H$437,'Summary to Mgmt'!$E6,'Master Data HO & Site'!$Y$1:$Y$437,"Open",'Master Data HO & Site'!$N$1:$N$437,$H$2),SUMIFS('Master Data HO & Site'!$AZ$1:$AZ$437,'Master Data HO & Site'!$S$1:$S$437,'Summary to Mgmt'!$C6,'Master Data HO & Site'!$Y$1:$Y$437,"Open",'Master Data HO & Site'!$N$1:$N$437,$H$2)),IF(C6="Jakarta",SUMIFS('Master Data HO & Site'!$AZ$1:$AZ$437,'Master Data HO & Site'!$F$1:$F$437,'Summary to Mgmt'!$D6,'Master Data HO & Site'!$H$1:$H$437,'Summary to Mgmt'!$E6,'Master Data HO & Site'!$Y$1:$Y$437,"Open",'Master Data HO & Site'!$N$1:$N$437,$H$2),SUMIFS('Master Data HO & Site'!$AZ$1:$AZ$437,'Master Data HO & Site'!$S$1:$S$437,'Summary to Mgmt'!$C6,'Master Data HO & Site'!$Y$1:$Y$437,"Open",'Master Data HO & Site'!$N$1:$N$437,$H$2)))) -> 0 | AI6: =IF($H$2="All",IF(C6="Jakarta",SUMIFS('Master Data HO & Site'!$AZ$1:$AZ$437,'Master Data HO & Site'!$F$1:$F$437,'Summary to Mgmt'!$D6,'Master Data HO & Site'!$H$1:$H$437,'Summary to Mgmt'!$E6,'Master Data HO & Site'!$Y$1:$Y$437,"Open"),SUMIFS('Master Data HO & Site'!$AZ$1:$AZ$437,'Master Data HO & Site'!$S$1:$S$437,'Summary to Mgmt'!$C6,'Master Data HO & Site'!$Y$1:$Y$437,"Open")),IF($H$2="Urgent",IF(C6="Jakarta",SUMIFS('Master Data HO & Site'!$AZ$1:$AZ$437,'Master Data HO & Site'!$F$1:$F$437,'Summary to Mgmt'!$D6,'Master Data HO & Site'!$H$1:$H$437,'Summary to Mgmt'!$E6,'Master Data HO & Site'!$Y$1:$Y$437,"Open",'Master Data HO & Site'!$N$1:$N$437,$H$2),SUMIFS('Master Data HO & Site'!$AZ$1:$AZ$437,'Master Data HO & Site'!$S$1:$S$437,'Summary to Mgmt'!$C6,'Master Data HO & Site'!$Y$1:$Y$437,"Open",'Master Data HO & Site'!$N$1:$N$437,$H$2)),IF(C6="Jakarta",SUMIFS('Master Data HO & Site'!$AZ$1:$AZ$437,'Master Data HO & Site'!$F$1:$F$437,'Summary to Mgmt'!$D6,'Master Data HO & Site'!$H$1:$H$437,'Summary to Mgmt'!$E6,'Master Data HO & Site'!$Y$1:$Y$437,"Open",'Master Data HO & Site'!$N$1:$N$437,$H$2),SUMIFS('Master Data HO & Site'!$AZ$1:$AZ$437,'Master Data HO & Site'!$S$1:$S$437,'Summary to Mgmt'!$C6,'Master Data HO & Site'!$Y$1:$Y$437,"Open",'Master Data HO & Site'!$N$1:$N$437,$H$2)))) -> 0 | AJ6: =IF($H$2="All",IF(C6="Jakarta",SUMIFS('Master Data HO & Site'!$BB$1:$BB$437,'Master Data HO & Site'!$F$1:$F$437,'Summary to Mgmt'!$D6,'Master Data HO & Site'!$H$1:$H$437,'Summary to Mgmt'!$E6,'Master Data HO & Site'!$Y$1:$Y$437,"Open"),SUMIFS('Master Data HO & Site'!$BB$1:$BB$437,'Master Data HO & Site'!$S$1:$S$437,'Summary to Mgmt'!$C6,'Master Data HO & Site'!$Y$1:$Y$437,"Open")),IF($H$2="Urgent",IF(C6="Jakarta",SUMIFS('Master Data HO & Site'!$BB$1:$BB$437,'Master Data HO & Site'!$F$1:$F$437,'Summary to Mgmt'!$D6,'Master Data HO & Site'!$H$1:$H$437,'Summary to Mgmt'!$E6,'Master Data HO & Site'!$Y$1:$Y$437,"Open",'Master Data HO & Site'!$N$1:$N$437,$H$2),SUMIFS('Master Data HO & Site'!$BB$1:$BB$437,'Master Data HO & Site'!$S$1:$S$437,'Summary to Mgmt'!$C6,'Master Data HO & Site'!$Y$1:$Y$437,"Open",'Master Data HO & Site'!$N$1:$N$437,$H$2)),IF(C6="Jakarta",SUMIFS('Master Data HO & Site'!$BB$1:$BB$437,'Master Data HO & Site'!$F$1:$F$437,'Summary to Mgmt'!$D6,'Master Data HO & Site'!$H$1:$H$437,'Summary to Mgmt'!$E6,'Master Data HO & Site'!$Y$1:$Y$437,"Open",'Master Data HO & Site'!$N$1:$N$437,$H$2),SUMIFS('Master Data HO & Site'!$BB$1:$BB$437,'Master Data HO & Site'!$S$1:$S$437,'Summary to Mgmt'!$C6,'Master Data HO & Site'!$Y$1:$Y$437,"Open",'Master Data HO & Site'!$N$1:$N$437,$H$2)))) -> 0 | AK6: =IF($H$2="All",IF(C6="Jakarta",SUMIFS('Master Data HO & Site'!$BC$1:$BC$437,'Master Data HO & Site'!$F$1:$F$437,'Summary to Mgmt'!$D6,'Master Data HO & Site'!$H$1:$H$437,'Summary to Mgmt'!$E6,'Master Data HO & Site'!$Y$1:$Y$437,"Open"),SUMIFS('Master Data HO & Site'!$BC$1:$BC$437,'Master Data HO & Site'!$S$1:$S$437,'Summary to Mgmt'!$C6,'Master Data HO & Site'!$Y$1:$Y$437,"Open")),IF($H$2="Urgent",IF(C6="Jakarta",SUMIFS('Master Data HO & Site'!$BC$1:$BC$437,'Master Data HO & Site'!$F$1:$F$437,'Summary to Mgmt'!$D6,'Master Data HO & Site'!$H$1:$H$437,'Summary to Mgmt'!$E6,'Master Data HO & Site'!$Y$1:$Y$437,"Open",'Master Data HO & Site'!$N$1:$N$437,$H$2),SUMIFS('Master Data HO & Site'!$BC$1:$BC$437,'Master Data HO & Site'!$S$1:$S$437,'Summary to Mgmt'!$C6,'Master Data HO & Site'!$Y$1:$Y$437,"Open",'Master Data HO & Site'!$N$1:$N$437,$H$2)),IF(C6="Jakarta",SUMIFS('Master Data HO & Site'!$BC$1:$BC$437,'Master Data HO & Site'!$F$1:$F$437,'Summary to Mgmt'!$D6,'Master Data HO & Site'!$H$1:$H$437,'Summary to Mgmt'!$E6,'Master Data HO & Site'!$Y$1:$Y$437,"Open",'Master Data HO & Site'!$N$1:$N$437,$H$2),SUMIFS('Master Data HO & Site'!$BC$1:$BC$437,'Master Data HO & Site'!$S$1:$S$437,'Summary to Mgmt'!$C6,'Master Data HO & Site'!$Y$1:$Y$437,"Open",'Master Data HO & Site'!$N$1:$N$437,$H$2)))) -> 0 | AL6: =IF($H$2="All",IF(C6="Jakarta",SUMIFS('Master Data HO & Site'!$BD$1:$BD$437,'Master Data HO & Site'!$F$1:$F$437,'Summary to Mgmt'!$D6,'Master Data HO & Site'!$H$1:$H$437,'Summary to Mgmt'!$E6,'Master Data HO & Site'!$Y$1:$Y$437,"Open"),SUMIFS('Master Data HO & Site'!$BD$1:$BD$437,'Master Data HO & Site'!$S$1:$S$437,'Summary to Mgmt'!$C6,'Master Data HO & Site'!$Y$1:$Y$437,"Open")),IF($H$2="Urgent",IF(C6="Jakarta",SUMIFS('Master Data HO & Site'!$BD$1:$BD$437,'Master Data HO & Site'!$F$1:$F$437,'Summary to Mgmt'!$D6,'Master Data HO & Site'!$H$1:$H$437,'Summary to Mgmt'!$E6,'Master Data HO & Site'!$Y$1:$Y$437,"Open",'Master Data HO & Site'!$N$1:$N$437,$H$2),SUMIFS('Master Data HO & Site'!$BD$1:$BD$437,'Master Data HO & Site'!$S$1:$S$437,'Summary to Mgmt'!$C6,'Master Data HO & Site'!$Y$1:$Y$437,"Open",'Master Data HO & Site'!$N$1:$N$437,$H$2)),IF(C6="Jakarta",SUMIFS('Master Data HO & Site'!$BD$1:$BD$437,'Master Data HO & Site'!$F$1:$F$437,'Summary to Mgmt'!$D6,'Master Data HO & Site'!$H$1:$H$437,'Summary to Mgmt'!$E6,'Master Data HO & Site'!$Y$1:$Y$437,"Open",'Master Data HO & Site'!$N$1:$N$437,$H$2),SUMIFS('Master Data HO & Site'!$BD$1:$BD$437,'Master Data HO & Site'!$S$1:$S$437,'Summary to Mgmt'!$C6,'Master Data HO & Site'!$Y$1:$Y$437,"Open",'Master Data HO & Site'!$N$1:$N$437,$H$2)))) -> 0 | AM6: =IF($H$2="All",IF(C6="Jakarta",SUMIFS('Master Data HO & Site'!$BE$1:$BE$437,'Master Data HO & Site'!$S$1:$S$437,'Summary to Mgmt'!$C6,'Master Data HO & Site'!$F$1:$F$437,'Summary to Mgmt'!$D6,'Master Data HO & Site'!$H$1:$H$437,'Summary to Mgmt'!$E6,'Master Data HO & Site'!$Y$1:$Y$437,"Open"),SUMIFS('Master Data HO & Site'!$BE$1:$BE$437,'Master Data HO & Site'!$S$1:$S$437,'Summary to Mgmt'!$C6,'Master Data HO & Site'!$Y$1:$Y$437,"Open")),IF($H$2="Urgent",IF(C6="Jakarta",SUMIFS('Master Data HO & Site'!$BE$1:$BE$437,'Master Data HO & Site'!$F$1:$F$437,'Summary to Mgmt'!$D6,'Master Data HO & Site'!$H$1:$H$437,'Summary to Mgmt'!$E6,'Master Data HO & Site'!$Y$1:$Y$437,"Open",'Master Data HO & Site'!$N$1:$N$437,$H$2),SUMIFS('Master Data HO & Site'!$BE$1:$BE$437,'Master Data HO & Site'!$S$1:$S$437,'Summary to Mgmt'!$C6,'Master Data HO & Site'!$Y$1:$Y$437,"Open",'Master Data HO & Site'!$N$1:$N$437,$H$2)),IF(C6="Jakarta",SUMIFS('Master Data HO & Site'!$BE$1:$BE$437,'Master Data HO & Site'!$F$1:$F$437,'Summary to Mgmt'!$D6,'Master Data HO & Site'!$H$1:$H$437,'Summary to Mgmt'!$E6,'Master Data HO & Site'!$Y$1:$Y$437,"Open",'Master Data HO & Site'!$N$1:$N$437,$H$2),SUMIFS('Master Data HO & Site'!$BE$1:$BE$437,'Master Data HO & Site'!$S$1:$S$437,'Summary to Mgmt'!$C6,'Master Data HO & Site'!$Y$1:$Y$437,"Open",'Master Data HO & Site'!$N$1:$N$437,$H$2)))) -> 0 | AN6: =IF($H$2="All",IF(C6="Jakarta",SUMIFS('Master Data HO & Site'!$BF$1:$BF$437,'Master Data HO & Site'!$F$1:$F$437,'Summary to Mgmt'!$D6,'Master Data HO & Site'!$H$1:$H$437,'Summary to Mgmt'!$E6,'Master Data HO & Site'!$Y$1:$Y$437,"Open"),SUMIFS('Master Data HO & Site'!$BF$1:$BF$437,'Master Data HO & Site'!$S$1:$S$437,'Summary to Mgmt'!$C6,'Master Data HO & Site'!$Y$1:$Y$437,"Open")),IF($H$2="Urgent",IF(C6="Jakarta",SUMIFS('Master Data HO & Site'!$BF$1:$BF$437,'Master Data HO & Site'!$F$1:$F$437,'Summary to Mgmt'!$D6,'Master Data HO & Site'!$H$1:$H$437,'Summary to Mgmt'!$E6,'Master Data HO & Site'!$Y$1:$Y$437,"Open",'Master Data HO & Site'!$N$1:$N$437,$H$2),SUMIFS('Master Data HO & Site'!$BF$1:$BF$437,'Master Data HO & Site'!$S$1:$S$437,'Summary to Mgmt'!$C6,'Master Data HO & Site'!$Y$1:$Y$437,"Open",'Master Data HO & Site'!$N$1:$N$437,$H$2)),IF(C6="Jakarta",SUMIFS('Master Data HO & Site'!$BF$1:$BF$437,'Master Data HO & Site'!$F$1:$F$437,'Summary to Mgmt'!$D6,'Master Data HO & Site'!$H$1:$H$437,'Summary to Mgmt'!$E6,'Master Data HO & Site'!$Y$1:$Y$437,"Open",'Master Data HO & Site'!$N$1:$N$437,$H$2),SUMIFS('Master Data HO & Site'!$BF$1:$BF$437,'Master Data HO & Site'!$S$1:$S$437,'Summary to Mgmt'!$C6,'Master Data HO & Site'!$Y$1:$Y$437,"Open",'Master Data HO & Site'!$N$1:$N$437,$H$2)))) -> 0 | AO6: =IF($H$2="All",IF(C6="Jakarta",SUMIFS('Master Data HO & Site'!$BG$1:$BG$437,'Master Data HO & Site'!$F$1:$F$437,'Summary to Mgmt'!$D6,'Master Data HO & Site'!$H$1:$H$437,'Summary to Mgmt'!$E6,'Master Data HO & Site'!$Y$1:$Y$437,"Open"),SUMIFS('Master Data HO & Site'!$BG$1:$BG$437,'Master Data HO & Site'!$S$1:$S$437,'Summary to Mgmt'!$C6,'Master Data HO & Site'!$Y$1:$Y$437,"Open")),IF($H$2="Urgent",IF(C6="Jakarta",SUMIFS('Master Data HO & Site'!$BG$1:$BG$437,'Master Data HO & Site'!$F$1:$F$437,'Summary to Mgmt'!$D6,'Master Data HO & Site'!$H$1:$H$437,'Summary to Mgmt'!$E6,'Master Data HO & Site'!$Y$1:$Y$437,"Open",'Master Data HO & Site'!$N$1:$N$437,$H$2),SUMIFS('Master Data HO & Site'!$BG$1:$BG$437,'Master Data HO & Site'!$S$1:$S$437,'Summary to Mgmt'!$C6,'Master Data HO & Site'!$Y$1:$Y$437,"Open",'Master Data HO & Site'!$N$1:$N$437,$H$2)),IF(C6="Jakarta",SUMIFS('Master Data HO & Site'!$BG$1:$BG$437,'Master Data HO & Site'!$F$1:$F$437,'Summary to Mgmt'!$D6,'Master Data HO & Site'!$H$1:$H$437,'Summary to Mgmt'!$E6,'Master Data HO & Site'!$Y$1:$Y$437,"Open",'Master Data HO & Site'!$N$1:$N$437,$H$2),SUMIFS('Master Data HO & Site'!$BG$1:$BG$437,'Master Data HO & Site'!$S$1:$S$437,'Summary to Mgmt'!$C6,'Master Data HO & Site'!$Y$1:$Y$437,"Open",'Master Data HO & Site'!$N$1:$N$437,$H$2)))) -> 0 | AP6: =IF($H$2="All",IF(C6="Jakarta",SUMIFS('Master Data HO & Site'!$BH$1:$BH$437,'Master Data HO & Site'!$F$1:$F$437,'Summary to Mgmt'!$D6,'Master Data HO & Site'!$H$1:$H$437,'Summary to Mgmt'!$E6,'Master Data HO & Site'!$Y$1:$Y$437,"Open"),SUMIFS('Master Data HO & Site'!$BH$1:$BH$437,'Master Data HO & Site'!$S$1:$S$437,'Summary to Mgmt'!$C6,'Master Data HO & Site'!$Y$1:$Y$437,"Open")),IF($H$2="Urgent",IF(C6="Jakarta",SUMIFS('Master Data HO & Site'!$BH$1:$BH$437,'Master Data HO & Site'!$F$1:$F$437,'Summary to Mgmt'!$D6,'Master Data HO & Site'!$H$1:$H$437,'Summary to Mgmt'!$E6,'Master Data HO & Site'!$Y$1:$Y$437,"Open",'Master Data HO & Site'!$N$1:$N$437,$H$2),SUMIFS('Master Data HO & Site'!$BH$1:$BH$437,'Master Data HO & Site'!$S$1:$S$437,'Summary to Mgmt'!$C6,'Master Data HO & Site'!$Y$1:$Y$437,"Open",'Master Data HO & Site'!$N$1:$N$437,$H$2)),IF(C6="Jakarta",SUMIFS('Master Data HO & Site'!$BH$1:$BH$437,'Master Data HO & Site'!$F$1:$F$437,'Summary to Mgmt'!$D6,'Master Data HO & Site'!$H$1:$H$437,'Summary to Mgmt'!$E6,'Master Data HO & Site'!$Y$1:$Y$437,"Open",'Master Data HO & Site'!$N$1:$N$437,$H$2),SUMIFS('Master Data HO & Site'!$BH$1:$BH$437,'Master Data HO & Site'!$S$1:$S$437,'Summary to Mgmt'!$C6,'Master Data HO & Site'!$Y$1:$Y$437,"Open",'Master Data HO & Site'!$N$1:$N$437,$H$2)))) -> 0 | AQ6: =IF($H$2="All",IF(C6="Jakarta",SUMIFS('Master Data HO & Site'!$BI$1:$BI$437,'Master Data HO & Site'!$F$1:$F$437,'Summary to Mgmt'!$D6,'Master Data HO & Site'!$H$1:$H$437,'Summary to Mgmt'!$E6,'Master Data HO & Site'!$Y$1:$Y$437,"Open"),SUMIFS('Master Data HO & Site'!$BI$1:$BI$437,'Master Data HO & Site'!$S$1:$S$437,'Summary to Mgmt'!$C6,'Master Data HO & Site'!$Y$1:$Y$437,"Open")),IF($H$2="Urgent",IF(C6="Jakarta",SUMIFS('Master Data HO & Site'!$BI$1:$BI$437,'Master Data HO & Site'!$F$1:$F$437,'Summary to Mgmt'!$D6,'Master Data HO & Site'!$H$1:$H$437,'Summary to Mgmt'!$E6,'Master Data HO & Site'!$Y$1:$Y$437,"Open",'Master Data HO & Site'!$N$1:$N$437,$H$2),SUMIFS('Master Data HO & Site'!$BI$1:$BI$437,'Master Data HO & Site'!$S$1:$S$437,'Summary to Mgmt'!$C6,'Master Data HO & Site'!$Y$1:$Y$437,"Open",'Master Data HO & Site'!$N$1:$N$437,$H$2)),IF(C6="Jakarta",SUMIFS('Master Data HO & Site'!$BI$1:$BI$437,'Master Data HO & Site'!$F$1:$F$437,'Summary to Mgmt'!$D6,'Master Data HO & Site'!$H$1:$H$437,'Summary to Mgmt'!$E6,'Master Data HO & Site'!$Y$1:$Y$437,"Open",'Master Data HO & Site'!$N$1:$N$437,$H$2),SUMIFS('Master Data HO & Site'!$BI$1:$BI$437,'Master Data HO & Site'!$S$1:$S$437,'Summary to Mgmt'!$C6,'Master Data HO & Site'!$Y$1:$Y$437,"Open",'Master Data HO & Site'!$N$1:$N$437,$H$2)))) -> 0 | AR6: =IF($H$2="All",IF(C6="Jakarta",SUMIFS('Master Data HO & Site'!$BJ$1:$BJ$437,'Master Data HO & Site'!$F$1:$F$437,'Summary to Mgmt'!$D6,'Master Data HO & Site'!$H$1:$H$437,'Summary to Mgmt'!$E6,'Master Data HO & Site'!$Y$1:$Y$437,"Open"),SUMIFS('Master Data HO & Site'!$BJ$1:$BJ$437,'Master Data HO & Site'!$S$1:$S$437,'Summary to Mgmt'!$C6,'Master Data HO & Site'!$Y$1:$Y$437,"Open")),IF($H$2="Urgent",IF(C6="Jakarta",SUMIFS('Master Data HO & Site'!$BJ$1:$BJ$437,'Master Data HO & Site'!$F$1:$F$437,'Summary to Mgmt'!$D6,'Master Data HO & Site'!$H$1:$H$437,'Summary to Mgmt'!$E6,'Master Data HO & Site'!$Y$1:$Y$437,"Open",'Master Data HO & Site'!$N$1:$N$437,$H$2),SUMIFS('Master Data HO & Site'!$BJ$1:$BJ$437,'Master Data HO & Site'!$S$1:$S$437,'Summary to Mgmt'!$C6,'Master Data HO & Site'!$Y$1:$Y$437,"Open",'Master Data HO & Site'!$N$1:$N$437,$H$2)),IF(C6="Jakarta",SUMIFS('Master Data HO & Site'!$BJ$1:$BJ$437,'Master Data HO & Site'!$F$1:$F$437,'Summary to Mgmt'!$D6,'Master Data HO & Site'!$H$1:$H$437,'Summary to Mgmt'!$E6,'Master Data HO & Site'!$Y$1:$Y$437,"Open",'Master Data HO & Site'!$N$1:$N$437,$H$2),SUMIFS('Master Data HO & Site'!$BJ$1:$BJ$437,'Master Data HO & Site'!$S$1:$S$437,'Summary to Mgmt'!$C6,'Master Data HO & Site'!$Y$1:$Y$437,"Open",'Master Data HO & Site'!$N$1:$N$437,$H$2)))) -> 0 | AS6: =IF($H$2="All",IF(C6="Jakarta",SUMIFS('Master Data HO & Site'!$BK$1:$BK$437,'Master Data HO & Site'!$S$1:$S$437,'Summary to Mgmt'!$C6,'Master Data HO & Site'!$F$1:$F$437,'Summary to Mgmt'!$D6,'Master Data HO & Site'!$H$1:$H$437,'Summary to Mgmt'!$E6,'Master Data HO & Site'!$Y$1:$Y$437,"Open"),SUMIFS('Master Data HO & Site'!$BK$1:$BK$437,'Master Data HO & Site'!$S$1:$S$437,'Summary to Mgmt'!$C6,'Master Data HO & Site'!$Y$1:$Y$437,"Open")),IF($H$2="Urgent",IF(C6="Jakarta",SUMIFS('Master Data HO & Site'!$BK$1:$BK$437,'Master Data HO & Site'!$F$1:$F$437,'Summary to Mgmt'!$D6,'Master Data HO & Site'!$H$1:$H$437,'Summary to Mgmt'!$E6,'Master Data HO & Site'!$Y$1:$Y$437,"Open",'Master Data HO & Site'!$N$1:$N$437,$H$2),SUMIFS('Master Data HO & Site'!$BK$1:$BK$437,'Master Data HO & Site'!$S$1:$S$437,'Summary to Mgmt'!$C6,'Master Data HO & Site'!$Y$1:$Y$437,"Open",'Master Data HO & Site'!$N$1:$N$437,$H$2)),IF(C6="Jakarta",SUMIFS('Master Data HO & Site'!$BK$1:$BK$437,'Master Data HO & Site'!$F$1:$F$437,'Summary to Mgmt'!$D6,'Master Data HO & Site'!$H$1:$H$437,'Summary to Mgmt'!$E6,'Master Data HO & Site'!$Y$1:$Y$437,"Open",'Master Data HO & Site'!$N$1:$N$437,$H$2),SUMIFS('Master Data HO & Site'!$BK$1:$BK$437,'Master Data HO & Site'!$S$1:$S$437,'Summary to Mgmt'!$C6,'Master Data HO & Site'!$Y$1:$Y$437,"Open",'Master Data HO & Site'!$N$1:$N$437,$H$2)))) -> 0 | AU6: =IF($H$2="All",IF(C6="Jakarta",COUNTIFS('Master Data HO & Site'!$F$1:$F$437,'Summary to Mgmt'!$D6,'Master Data HO & Site'!$H$1:$H$437,'Summary to Mgmt'!$E6,'Master Data HO & Site'!$Y$1:$Y$437,"Open",'Master Data HO & Site'!$BZ$1:$BZ$437,'Summary to Mgmt'!$AU$4),COUNTIFS('Master Data HO & Site'!$S$1:$S$437,'Summary to Mgmt'!$C6,'Master Data HO & Site'!$Y$1:$Y$437,"Open",'Master Data HO & Site'!$BZ$1:$BZ$437,'Summary to Mgmt'!$AU$4)),IF($H$2="Urgent",IF(C6="Jakarta",COUNTIFS('Master Data HO & Site'!$F$1:$F$437,'Summary to Mgmt'!$D6,'Master Data HO & Site'!$H$1:$H$437,'Summary to Mgmt'!$E6,'Master Data HO & Site'!$Y$1:$Y$437,"Open",'Master Data HO & Site'!$BZ$1:$BZ$437,'Summary to Mgmt'!$AU$4,'Master Data HO & Site'!$N$1:$N$437,$H$2),COUNTIFS('Master Data HO & Site'!$S$1:$S$437,'Summary to Mgmt'!$C6,'Master Data HO & Site'!$Y$1:$Y$437,"Open",'Master Data HO & Site'!$BZ$1:$BZ$437,'Summary to Mgmt'!$AU$4,'Master Data HO & Site'!$N$1:$N$437,$H$2)),IF(C6="Jakarta",COUNTIFS('Master Data HO & Site'!$F$1:$F$437,'Summary to Mgmt'!$D6,'Master Data HO & Site'!$H$1:$H$437,'Summary to Mgmt'!$E6,'Master Data HO & Site'!$Y$1:$Y$437,"Open",'Master Data HO & Site'!$BZ$1:$BZ$437,'Summary to Mgmt'!$AU$4,'Master Data HO & Site'!$N$1:$N$437,$H$2),COUNTIFS('Master Data HO & Site'!$S$1:$S$437,'Summary to Mgmt'!$C6,'Master Data HO & Site'!$Y$1:$Y$437,"Open",'Master Data HO & Site'!$BZ$1:$BZ$437,'Summary to Mgmt'!$AU$4,'Master Data HO & Site'!$N$1:$N$437,$H$2)))) -> 0 | AV6: =IF($H$2="All",IF(C6="Jakarta",COUNTIFS('Master Data HO & Site'!$F$1:$F$437,'Summary to Mgmt'!$D6,'Master Data HO & Site'!$H$1:$H$437,'Summary to Mgmt'!$E6,'Master Data HO & Site'!$Y$1:$Y$437,"Open",'Master Data HO & Site'!$BZ$1:$BZ$437,'Summary to Mgmt'!$AV$4),COUNTIFS('Master Data HO & Site'!$S$1:$S$437,'Summary to Mgmt'!$C6,'Master Data HO & Site'!$Y$1:$Y$437,"Open",'Master Data HO & Site'!$BZ$1:$BZ$437,'Summary to Mgmt'!$AV$4)),IF($H$2="Urgent",IF(C6="Jakarta",COUNTIFS('Master Data HO & Site'!$F$1:$F$437,'Summary to Mgmt'!$D6,'Master Data HO & Site'!$H$1:$H$437,'Summary to Mgmt'!$E6,'Master Data HO & Site'!$Y$1:$Y$437,"Open",'Master Data HO & Site'!$BZ$1:$BZ$437,'Summary to Mgmt'!$AV$4,'Master Data HO & Site'!$N$1:$N$437,$H$2),COUNTIFS('Master Data HO & Site'!$S$1:$S$437,'Summary to Mgmt'!$C6,'Master Data HO & Site'!$Y$1:$Y$437,"Open",'Master Data HO & Site'!$BZ$1:$BZ$437,'Summary to Mgmt'!$AV$4,'Master Data HO & Site'!$N$1:$N$437,$H$2)),IF(C6="Jakarta",COUNTIFS('Master Data HO & Site'!$F$1:$F$437,'Summary to Mgmt'!$D6,'Master Data HO & Site'!$H$1:$H$437,'Summary to Mgmt'!$E6,'Master Data HO & Site'!$Y$1:$Y$437,"Open",'Master Data HO & Site'!$BZ$1:$BZ$437,'Summary to Mgmt'!$AV$4,'Master Data HO & Site'!$N$1:$N$437,$H$2),COUNTIFS('Master Data HO & Site'!$S$1:$S$437,'Summary to Mgmt'!$C6,'Master Data HO & Site'!$Y$1:$Y$437,"Open",'Master Data HO & Site'!$BZ$1:$BZ$437,'Summary to Mgmt'!$AV$4,'Master Data HO & Site'!$N$1:$N$437,$H$2)))) -> 0 | AW6: =IF($H$2="All",IF(C6="Jakarta",COUNTIFS('Master Data HO & Site'!$F$1:$F$437,'Summary to Mgmt'!$D6,'Master Data HO & Site'!$H$1:$H$437,'Summary to Mgmt'!$E6,'Master Data HO & Site'!$Y$1:$Y$437,"Open",'Master Data HO & Site'!$BZ$1:$BZ$437,'Summary to Mgmt'!$AW$4),COUNTIFS('Master Data HO & Site'!$S$1:$S$437,'Summary to Mgmt'!$C6,'Master Data HO & Site'!$Y$1:$Y$437,"Open",'Master Data HO & Site'!$BZ$1:$BZ$437,'Summary to Mgmt'!$AW$4)),IF($H$2="Urgent",IF(C6="Jakarta",COUNTIFS('Master Data HO & Site'!$F$1:$F$437,'Summary to Mgmt'!$D6,'Master Data HO & Site'!$H$1:$H$437,'Summary to Mgmt'!$E6,'Master Data HO & Site'!$Y$1:$Y$437,"Open",'Master Data HO & Site'!$BZ$1:$BZ$437,'Summary to Mgmt'!$AW$4,'Master Data HO & Site'!$N$1:$N$437,$H$2),COUNTIFS('Master Data HO & Site'!$S$1:$S$437,'Summary to Mgmt'!$C6,'Master Data HO & Site'!$Y$1:$Y$437,"Open",'Master Data HO & Site'!$BZ$1:$BZ$437,'Summary to Mgmt'!$AW$4,'Master Data HO & Site'!$N$1:$N$437,$H$2)),IF(C6="Jakarta",COUNTIFS('Master Data HO & Site'!$F$1:$F$437,'Summary to Mgmt'!$D6,'Master Data HO & Site'!$H$1:$H$437,'Summary to Mgmt'!$E6,'Master Data HO & Site'!$Y$1:$Y$437,"Open",'Master Data HO & Site'!$BZ$1:$BZ$437,'Summary to Mgmt'!$AW$4,'Master Data HO & Site'!$N$1:$N$437,$H$2),COUNTIFS('Master Data HO & Site'!$S$1:$S$437,'Summary to Mgmt'!$C6,'Master Data HO & Site'!$Y$1:$Y$437,"Open",'Master Data HO & Site'!$BZ$1:$BZ$437,'Summary to Mgmt'!$AW$4,'Master Data HO & Site'!$N$1:$N$437,$H$2)))) -> 0 | AX6: =IF($H$2="All",IF(C6="Jakarta",COUNTIFS('Master Data HO & Site'!$F$1:$F$437,'Summary to Mgmt'!$D6,'Master Data HO & Site'!$H$1:$H$437,'Summary to Mgmt'!$E6,'Master Data HO & Site'!$Y$1:$Y$437,"Open",'Master Data HO & Site'!$BZ$1:$BZ$437,'Summary to Mgmt'!$AX$4),COUNTIFS('Master Data HO & Site'!$S$1:$S$437,'Summary to Mgmt'!$C6,'Master Data HO & Site'!$Y$1:$Y$437,"Open",'Master Data HO & Site'!$BZ$1:$BZ$437,'Summary to Mgmt'!$AX$4)),IF($H$2="Urgent",IF(C6="Jakarta",COUNTIFS('Master Data HO & Site'!$F$1:$F$437,'Summary to Mgmt'!$D6,'Master Data HO & Site'!$H$1:$H$437,'Summary to Mgmt'!$E6,'Master Data HO & Site'!$Y$1:$Y$437,"Open",'Master Data HO & Site'!$BZ$1:$BZ$437,'Summary to Mgmt'!$AX$4,'Master Data HO & Site'!$N$1:$N$437,$H$2),COUNTIFS('Master Data HO & Site'!$S$1:$S$437,'Summary to Mgmt'!$C6,'Master Data HO & Site'!$Y$1:$Y$437,"Open",'Master Data HO & Site'!$BZ$1:$BZ$437,'Summary to Mgmt'!$AX$4,'Master Data HO & Site'!$N$1:$N$437,$H$2)),IF(C6="Jakarta",COUNTIFS('Master Data HO & Site'!$F$1:$F$437,'Summary to Mgmt'!$D6,'Master Data HO & Site'!$H$1:$H$437,'Summary to Mgmt'!$E6,'Master Data HO & Site'!$Y$1:$Y$437,"Open",'Master Data HO & Site'!$BZ$1:$BZ$437,'Summary to Mgmt'!$AX$4,'Master Data HO & Site'!$N$1:$N$437,$H$2),COUNTIFS('Master Data HO & Site'!$S$1:$S$437,'Summary to Mgmt'!$C6,'Master Data HO & Site'!$Y$1:$Y$437,"Open",'Master Data HO & Site'!$BZ$1:$BZ$437,'Summary to Mgmt'!$AX$4,'Master Data HO & Site'!$N$1:$N$437,$H$2)))) -> 1
C7: Jakarta | D7: Bonded Zone | E7: Custom Dispute | F7: =G7+H7 -> 1 | G7: =IF($H$2="All",IF(C7="Jakarta",SUMIFS('Master Data HO & Site'!$BM$1:$BM$437,'Master Data HO & Site'!$S$1:$S$437,'Summary to Mgmt'!C7,'Master Data HO & Site'!$F$1:$F$437,'Summary to Mgmt'!$D7,'Master Data HO & Site'!$H$1:$H$437,'Summary to Mgmt'!$E7,'Master Data HO & Site'!$Y$1:$Y$437,"Closed"),SUMIFS('Master Data HO & Site'!$BM$1:$BM$437,'Master Data HO & Site'!$S$1:$S$437,'Summary to Mgmt'!C7,'Master Data HO & Site'!$Y$1:$Y$437,"Closed")),IF(C7="Jakarta",SUMIFS('Master Data HO & Site'!$BM$1:$BM$437,'Master Data HO & Site'!$S$1:$S$437,'Summary to Mgmt'!C7,'Master Data HO & Site'!$F$1:$F$437,'Summary to Mgmt'!$D7,'Master Data HO & Site'!$H$1:$H$437,'Summary to Mgmt'!E7,'Master Data HO & Site'!$N$1:$N$437,'Summary to Mgmt'!$H$2,'Master Data HO & Site'!$Y$1:$Y$437,"Closed"),SUMIFS('Master Data HO & Site'!$BM$1:$BM$437,'Master Data HO & Site'!$S$1:$S$437,'Summary to Mgmt'!C7,'Master Data HO & Site'!$N$1:$N$437,'Summary to Mgmt'!$H$2,'Master Data HO & Site'!$Y$1:$Y$437,"Closed"))) -> 0 | H7: =IF($H$2="All",IF(C7="Jakarta",COUNTIFS('Master Data HO & Site'!$S$1:$S$437,'Summary to Mgmt'!$C7,'Master Data HO & Site'!$F$1:$F$437,'Summary to Mgmt'!$D7,'Master Data HO & Site'!$H$1:$H$437,'Summary to Mgmt'!$E7,'Master Data HO & Site'!$Y$1:$Y$437,"Open"),COUNTIFS('Master Data HO & Site'!$S$1:$S$437,'Summary to Mgmt'!$C7,'Master Data HO & Site'!$Y$1:$Y$437,"Open")),IF($H$2="Urgent",IF(C7="Jakarta",COUNTIFS('Master Data HO & Site'!$S$1:$S$437,'Summary to Mgmt'!$C7,'Master Data HO & Site'!$F$1:$F$437,'Summary to Mgmt'!$D7,'Master Data HO & Site'!$H$1:$H$437,'Summary to Mgmt'!$E7,'Master Data HO & Site'!$Y$1:$Y$437,"Open",'Master Data HO & Site'!$N$1:$N$437,$H$2),COUNTIFS('Master Data HO & Site'!$S$1:$S$437,'Summary to Mgmt'!$C7,'Master Data HO & Site'!$Y$1:$Y$437,"Open",'Master Data HO & Site'!$N$1:$N$437,$H$2)),IF(C7="Jakarta",COUNTIFS('Master Data HO & Site'!$F$1:$F$437,'Summary to Mgmt'!$D7,'Master Data HO & Site'!$H$1:$H$437,'Summary to Mgmt'!$E7,'Master Data HO & Site'!$Y$1:$Y$437,"Open",'Master Data HO & Site'!$N$1:$N$437,$H$2),COUNTIFS('Master Data HO & Site'!$S$1:$S$437,'Summary to Mgmt'!$C7,'Master Data HO & Site'!$Y$1:$Y$437,"Open",'Master Data HO & Site'!$N$1:$N$437,$H$2)))) -> 1 | I7: =IF($H$2="All",IF(C7="Jakarta",COUNTIFS('Master Data HO & Site'!$F$1:$F$437,'Summary to Mgmt'!$D7,'Master Data HO & Site'!$H$1:$H$437,'Summary to Mgmt'!$E7,'Master Data HO & Site'!$Y$1:$Y$437,"Open",'Master Data HO & Site'!$D$1:$D$437,"pending FKTK"),COUNTIFS('Master Data HO & Site'!$S$1:$S$437,'Summary to Mgmt'!$C7,'Master Data HO & Site'!$Y$1:$Y$437,"Open",'Master Data HO & Site'!$D$1:$D$437,"pending FKTK")),IF($H$2="Urgent",IF(C7="Jakarta",COUNTIFS('Master Data HO & Site'!$F$1:$F$437,'Summary to Mgmt'!$D7,'Master Data HO & Site'!$H$1:$H$437,'Summary to Mgmt'!$E7,'Master Data HO & Site'!$Y$1:$Y$437,"Open",'Master Data HO & Site'!$N$1:$N$437,$H$2,'Master Data HO & Site'!$D$1:$D$437,"pending FKTK"),COUNTIFS('Master Data HO & Site'!$S$1:$S$437,'Summary to Mgmt'!$C7,'Master Data HO & Site'!$Y$1:$Y$437,"Open",'Master Data HO & Site'!$N$1:$N$437,$H$2,'Master Data HO & Site'!$D$1:$D$437,"pending FKTK")),IF(C7="Jakarta",COUNTIFS('Master Data HO & Site'!$F$1:$F$437,'Summary to Mgmt'!$D7,'Master Data HO & Site'!$H$1:$H$437,'Summary to Mgmt'!$E7,'Master Data HO & Site'!$Y$1:$Y$437,"Open",'Master Data HO & Site'!$N$1:$N$437,$H$2,'Master Data HO & Site'!$D$1:$D$437,"pending FKTK"),COUNTIFS('Master Data HO & Site'!$S$1:$S$437,'Summary to Mgmt'!$C7,'Master Data HO & Site'!$Y$1:$Y$437,"Open",'Master Data HO & Site'!$N$1:$N$437,$H$2,'Master Data HO & Site'!$D$1:$D$437,"pending FKTK")))) -> 0 | J7: =IF($H$2="All",IF(C7="Jakarta",SUMIFS('Master Data HO & Site'!$AB$1:$AB$437,'Master Data HO & Site'!$F$1:$F$437,'Summary to Mgmt'!$D7,'Master Data HO & Site'!$H$1:$H$437,'Summary to Mgmt'!$E7,'Master Data HO & Site'!$Y$1:$Y$437,"Open"),SUMIFS('Master Data HO & Site'!$AB$1:$AB$437,'Master Data HO & Site'!$S$1:$S$437,'Summary to Mgmt'!$C7,'Master Data HO & Site'!$Y$1:$Y$437,"Open")),IF($H$2="Urgent",IF(C7="Jakarta",SUMIFS('Master Data HO & Site'!$AB$1:$AB$437,'Master Data HO & Site'!$F$1:$F$437,'Summary to Mgmt'!$D7,'Master Data HO & Site'!$H$1:$H$437,'Summary to Mgmt'!$E7,'Master Data HO & Site'!$Y$1:$Y$437,"Open",'Master Data HO & Site'!$N$1:$N$437,$H$2),SUMIFS('Master Data HO & Site'!$AB$1:$AB$437,'Master Data HO & Site'!$S$1:$S$437,'Summary to Mgmt'!$C7,'Master Data HO & Site'!$Y$1:$Y$437,"Open",'Master Data HO & Site'!$N$1:$N$437,$H$2)),IF(C7="Jakarta",SUMIFS('Master Data HO & Site'!$AB$1:$AB$437,'Master Data HO & Site'!$F$1:$F$437,'Summary to Mgmt'!$D7,'Master Data HO & Site'!$H$1:$H$437,'Summary to Mgmt'!$E7,'Master Data HO & Site'!$Y$1:$Y$437,"Open",'Master Data HO & Site'!$N$1:$N$437,$H$2),SUMIFS('Master Data HO & Site'!$AB$1:$AB$437,'Master Data HO & Site'!$S$1:$S$437,'Summary to Mgmt'!$C7,'Master Data HO & Site'!$Y$1:$Y$437,"Open",'Master Data HO & Site'!$N$1:$N$437,$H$2)))) -> 0 | K7: =IF($H$2="All",IF(C7="Jakarta",SUMIFS('Master Data HO & Site'!$AC$1:$AC$437,'Master Data HO & Site'!$F$1:$F$437,'Summary to Mgmt'!$D7,'Master Data HO & Site'!$H$1:$H$437,'Summary to Mgmt'!$E7,'Master Data HO & Site'!$Y$1:$Y$437,"Open"),SUMIFS('Master Data HO & Site'!$AC$1:$AC$437,'Master Data HO & Site'!$S$1:$S$437,'Summary to Mgmt'!$C7,'Master Data HO & Site'!$Y$1:$Y$437,"Open")),IF($H$2="Urgent",IF(C7="Jakarta",SUMIFS('Master Data HO & Site'!$AC$1:$AC$437,'Master Data HO & Site'!$F$1:$F$437,'Summary to Mgmt'!$D7,'Master Data HO & Site'!$H$1:$H$437,'Summary to Mgmt'!$E7,'Master Data HO & Site'!$Y$1:$Y$437,"Open",'Master Data HO & Site'!$N$1:$N$437,$H$2),SUMIFS('Master Data HO & Site'!$AC$1:$AC$437,'Master Data HO & Site'!$S$1:$S$437,'Summary to Mgmt'!$C7,'Master Data HO & Site'!$Y$1:$Y$437,"Open",'Master Data HO & Site'!$N$1:$N$437,$H$2)),IF(C7="Jakarta",SUMIFS('Master Data HO & Site'!$AC$1:$AC$437,'Master Data HO & Site'!$F$1:$F$437,'Summary to Mgmt'!$D7,'Master Data HO & Site'!$H$1:$H$437,'Summary to Mgmt'!$E7,'Master Data HO & Site'!$Y$1:$Y$437,"Open",'Master Data HO & Site'!$N$1:$N$437,$H$2),SUMIFS('Master Data HO & Site'!$AC$1:$AC$437,'Master Data HO & Site'!$S$1:$S$437,'Summary to Mgmt'!$C7,'Master Data HO & Site'!$Y$1:$Y$437,"Open",'Master Data HO & Site'!$N$1:$N$437,$H$2)))) -> 0 | L7: =IF($H$2="All",IF(C7="Jakarta",SUMIFS('Master Data HO & Site'!$AD$1:$AD$437,'Master Data HO & Site'!$F$1:$F$437,'Summary to Mgmt'!$D7,'Master Data HO & Site'!$H$1:$H$437,'Summary to Mgmt'!$E7,'Master Data HO & Site'!$Y$1:$Y$437,"Open"),SUMIFS('Master Data HO & Site'!$AD$1:$AD$437,'Master Data HO & Site'!$S$1:$S$437,'Summary to Mgmt'!$C7,'Master Data HO & Site'!$Y$1:$Y$437,"Open")),IF($H$2="Urgent",IF(C7="Jakarta",SUMIFS('Master Data HO & Site'!$AD$1:$AD$437,'Master Data HO & Site'!$F$1:$F$437,'Summary to Mgmt'!$D7,'Master Data HO & Site'!$H$1:$H$437,'Summary to Mgmt'!$E7,'Master Data HO & Site'!$Y$1:$Y$437,"Open",'Master Data HO & Site'!$N$1:$N$437,$H$2),SUMIFS('Master Data HO & Site'!$AD$1:$AD$437,'Master Data HO & Site'!$S$1:$S$437,'Summary to Mgmt'!$C7,'Master Data HO & Site'!$Y$1:$Y$437,"Open",'Master Data HO & Site'!$N$1:$N$437,$H$2)),IF(C7="Jakarta",SUMIFS('Master Data HO & Site'!$AD$1:$AD$437,'Master Data HO & Site'!$F$1:$F$437,'Summary to Mgmt'!$D7,'Master Data HO & Site'!$H$1:$H$437,'Summary to Mgmt'!$E7,'Master Data HO & Site'!$Y$1:$Y$437,"Open",'Master Data HO & Site'!$N$1:$N$437,$H$2),SUMIFS('Master Data HO & Site'!$AD$1:$AD$437,'Master Data HO & Site'!$S$1:$S$437,'Summary to Mgmt'!$C7,'Master Data HO & Site'!$Y$1:$Y$437,"Open",'Master Data HO & Site'!$N$1:$N$437,$H$2)))) -> 0 | M7: =IF($H$2="All",IF(C7="Jakarta",SUMIFS('Master Data HO & Site'!$AE$1:$AE$437,'Master Data HO & Site'!$F$1:$F$437,'Summary to Mgmt'!$D7,'Master Data HO & Site'!$H$1:$H$437,'Summary to Mgmt'!$E7,'Master Data HO & Site'!$Y$1:$Y$437,"Open"),SUMIFS('Master Data HO & Site'!$AE$1:$AE$437,'Master Data HO & Site'!$S$1:$S$437,'Summary to Mgmt'!$C7,'Master Data HO & Site'!$Y$1:$Y$437,"Open")),IF($H$2="Urgent",IF(C7="Jakarta",SUMIFS('Master Data HO & Site'!$AE$1:$AE$437,'Master Data HO & Site'!$F$1:$F$437,'Summary to Mgmt'!$D7,'Master Data HO & Site'!$H$1:$H$437,'Summary to Mgmt'!$E7,'Master Data HO & Site'!$Y$1:$Y$437,"Open",'Master Data HO & Site'!$N$1:$N$437,$H$2),SUMIFS('Master Data HO & Site'!$AE$1:$AE$437,'Master Data HO & Site'!$S$1:$S$437,'Summary to Mgmt'!$C7,'Master Data HO & Site'!$Y$1:$Y$437,"Open",'Master Data HO & Site'!$N$1:$N$437,$H$2)),IF(C7="Jakarta",SUMIFS('Master Data HO & Site'!$AE$1:$AE$437,'Master Data HO & Site'!$F$1:$F$437,'Summary to Mgmt'!$D7,'Master Data HO & Site'!$H$1:$H$437,'Summary to Mgmt'!$E7,'Master Data HO & Site'!$Y$1:$Y$437,"Open",'Master Data HO & Site'!$N$1:$N$437,$H$2),SUMIFS('Master Data HO & Site'!$AE$1:$AE$437,'Master Data HO & Site'!$S$1:$S$437,'Summary to Mgmt'!$C7,'Master Data HO & Site'!$Y$1:$Y$437,"Open",'Master Data HO & Site'!$N$1:$N$437,$H$2)))) -> 0 | N7: =IF($H$2="All",IF(C7="Jakarta",SUMIFS('Master Data HO & Site'!$AF$1:$AF$437,'Master Data HO & Site'!$F$1:$F$437,'Summary to Mgmt'!$D7,'Master Data HO & Site'!$H$1:$H$437,'Summary to Mgmt'!$E7,'Master Data HO & Site'!$Y$1:$Y$437,"Open"),SUMIFS('Master Data HO & Site'!$AF$1:$AF$437,'Master Data HO & Site'!$S$1:$S$437,'Summary to Mgmt'!$C7,'Master Data HO & Site'!$Y$1:$Y$437,"Open")),IF($H$2="Urgent",IF(C7="Jakarta",SUMIFS('Master Data HO & Site'!$AF$1:$AF$437,'Master Data HO & Site'!$F$1:$F$437,'Summary to Mgmt'!$D7,'Master Data HO & Site'!$H$1:$H$437,'Summary to Mgmt'!$E7,'Master Data HO & Site'!$Y$1:$Y$437,"Open",'Master Data HO & Site'!$N$1:$N$437,$H$2),SUMIFS('Master Data HO & Site'!$AF$1:$AF$437,'Master Data HO & Site'!$S$1:$S$437,'Summary to Mgmt'!$C7,'Master Data HO & Site'!$Y$1:$Y$437,"Open",'Master Data HO & Site'!$N$1:$N$437,$H$2)),IF(C7="Jakarta",SUMIFS('Master Data HO & Site'!$AF$1:$AF$437,'Master Data HO & Site'!$F$1:$F$437,'Summary to Mgmt'!$D7,'Master Data HO & Site'!$H$1:$H$437,'Summary to Mgmt'!$E7,'Master Data HO & Site'!$Y$1:$Y$437,"Open",'Master Data HO & Site'!$N$1:$N$437,$H$2),SUMIFS('Master Data HO & Site'!$AF$1:$AF$437,'Master Data HO & Site'!$S$1:$S$437,'Summary to Mgmt'!$C7,'Master Data HO & Site'!$Y$1:$Y$437,"Open",'Master Data HO & Site'!$N$1:$N$437,$H$2)))) -> 0 | O7: =IF($H$2="All",IF(C7="Jakarta",SUMIFS('Master Data HO & Site'!$AG$1:$AG$437,'Master Data HO & Site'!$S$1:$S$437,'Summary to Mgmt'!$C7,'Master Data HO & Site'!$F$1:$F$437,'Summary to Mgmt'!$D7,'Master Data HO & Site'!$H$1:$H$437,'Summary to Mgmt'!$E7,'Master Data HO & Site'!$Y$1:$Y$437,"Open"),SUMIFS('Master Data HO & Site'!$AG$1:$AG$437,'Master Data HO & Site'!$S$1:$S$437,'Summary to Mgmt'!$C7,'Master Data HO & Site'!$Y$1:$Y$437,"Open")),IF($H$2="Urgent",IF(C7="Jakarta",SUMIFS('Master Data HO & Site'!$AG$1:$AG$437,'Master Data HO & Site'!$F$1:$F$437,'Summary to Mgmt'!$D7,'Master Data HO & Site'!$H$1:$H$437,'Summary to Mgmt'!$E7,'Master Data HO & Site'!$Y$1:$Y$437,"Open",'Master Data HO & Site'!$N$1:$N$437,$H$2),SUMIFS('Master Data HO & Site'!$AG$1:$AG$437,'Master Data HO & Site'!$S$1:$S$437,'Summary to Mgmt'!$C7,'Master Data HO & Site'!$Y$1:$Y$437,"Open",'Master Data HO & Site'!$N$1:$N$437,$H$2)),IF(C7="Jakarta",SUMIFS('Master Data HO & Site'!$AG$1:$AG$437,'Master Data HO & Site'!$F$1:$F$437,'Summary to Mgmt'!$D7,'Master Data HO & Site'!$H$1:$H$437,'Summary to Mgmt'!$E7,'Master Data HO & Site'!$Y$1:$Y$437,"Open",'Master Data HO & Site'!$N$1:$N$437,$H$2),SUMIFS('Master Data HO & Site'!$AG$1:$AG$437,'Master Data HO & Site'!$S$1:$S$437,'Summary to Mgmt'!$C7,'Master Data HO & Site'!$Y$1:$Y$437,"Open",'Master Data HO & Site'!$N$1:$N$437,$H$2)))) -> 0 | P7: =IF($H$2="All",IF(C7="Jakarta",SUMIFS('Master Data HO & Site'!$AH$1:$AH$437,'Master Data HO & Site'!$F$1:$F$437,'Summary to Mgmt'!$D7,'Master Data HO & Site'!$H$1:$H$437,'Summary to Mgmt'!$E7,'Master Data HO & Site'!$Y$1:$Y$437,"Open"),SUMIFS('Master Data HO & Site'!$AH$1:$AH$437,'Master Data HO & Site'!$S$1:$S$437,'Summary to Mgmt'!$C7,'Master Data HO & Site'!$Y$1:$Y$437,"Open")),IF($H$2="Urgent",IF(C7="Jakarta",SUMIFS('Master Data HO & Site'!$AH$1:$AH$437,'Master Data HO & Site'!$F$1:$F$437,'Summary to Mgmt'!$D7,'Master Data HO & Site'!$H$1:$H$437,'Summary to Mgmt'!$E7,'Master Data HO & Site'!$Y$1:$Y$437,"Open",'Master Data HO & Site'!$N$1:$N$437,$H$2),SUMIFS('Master Data HO & Site'!$AH$1:$AH$437,'Master Data HO & Site'!$S$1:$S$437,'Summary to Mgmt'!$C7,'Master Data HO & Site'!$Y$1:$Y$437,"Open",'Master Data HO & Site'!$N$1:$N$437,$H$2)),IF(C7="Jakarta",SUMIFS('Master Data HO & Site'!$AH$1:$AH$437,'Master Data HO & Site'!$F$1:$F$437,'Summary to Mgmt'!$D7,'Master Data HO & Site'!$H$1:$H$437,'Summary to Mgmt'!$E7,'Master Data HO & Site'!$Y$1:$Y$437,"Open",'Master Data HO & Site'!$N$1:$N$437,$H$2),SUMIFS('Master Data HO & Site'!$AH$1:$AH$437,'Master Data HO & Site'!$S$1:$S$437,'Summary to Mgmt'!$C7,'Master Data HO & Site'!$Y$1:$Y$437,"Open",'Master Data HO & Site'!$N$1:$N$437,$H$2)))) -> 0 | Q7: =IF($H$2="All",IF(C7="Jakarta",SUMIFS('Master Data HO & Site'!$AI$1:$AI$437,'Master Data HO & Site'!$F$1:$F$437,'Summary to Mgmt'!$D7,'Master Data HO & Site'!$H$1:$H$437,'Summary to Mgmt'!$E7,'Master Data HO & Site'!$Y$1:$Y$437,"Open"),SUMIFS('Master Data HO & Site'!$AI$1:$AI$437,'Master Data HO & Site'!$S$1:$S$437,'Summary to Mgmt'!$C7,'Master Data HO & Site'!$Y$1:$Y$437,"Open")),IF($H$2="Urgent",IF(C7="Jakarta",SUMIFS('Master Data HO & Site'!$AI$1:$AI$437,'Master Data HO & Site'!$F$1:$F$437,'Summary to Mgmt'!$D7,'Master Data HO & Site'!$H$1:$H$437,'Summary to Mgmt'!$E7,'Master Data HO & Site'!$Y$1:$Y$437,"Open",'Master Data HO & Site'!$N$1:$N$437,$H$2),SUMIFS('Master Data HO & Site'!$AI$1:$AI$437,'Master Data HO & Site'!$S$1:$S$437,'Summary to Mgmt'!$C7,'Master Data HO & Site'!$Y$1:$Y$437,"Open",'Master Data HO & Site'!$N$1:$N$437,$H$2)),IF(C7="Jakarta",SUMIFS('Master Data HO & Site'!$AI$1:$AI$437,'Master Data HO & Site'!$F$1:$F$437,'Summary to Mgmt'!$D7,'Master Data HO & Site'!$H$1:$H$437,'Summary to Mgmt'!$E7,'Master Data HO & Site'!$Y$1:$Y$437,"Open",'Master Data HO & Site'!$N$1:$N$437,$H$2),SUMIFS('Master Data HO & Site'!$AI$1:$AI$437,'Master Data HO & Site'!$S$1:$S$437,'Summary to Mgmt'!$C7,'Master Data HO & Site'!$Y$1:$Y$437,"Open",'Master Data HO & Site'!$N$1:$N$437,$H$2)))) -> 0 | R7: =IF($H$2="All",IF(C7="Jakarta",SUMIFS('Master Data HO & Site'!$AJ$1:$AJ$437,'Master Data HO & Site'!$F$1:$F$437,'Summary to Mgmt'!$D7,'Master Data HO & Site'!$H$1:$H$437,'Summary to Mgmt'!$E7,'Master Data HO & Site'!$Y$1:$Y$437,"Open"),SUMIFS('Master Data HO & Site'!$AJ$1:$AJ$437,'Master Data HO & Site'!$S$1:$S$437,'Summary to Mgmt'!$C7,'Master Data HO & Site'!$Y$1:$Y$437,"Open")),IF($H$2="Urgent",IF(C7="Jakarta",SUMIFS('Master Data HO & Site'!$AJ$1:$AJ$437,'Master Data HO & Site'!$F$1:$F$437,'Summary to Mgmt'!$D7,'Master Data HO & Site'!$H$1:$H$437,'Summary to Mgmt'!$E7,'Master Data HO & Site'!$Y$1:$Y$437,"Open",'Master Data HO & Site'!$N$1:$N$437,$H$2),SUMIFS('Master Data HO & Site'!$AJ$1:$AJ$437,'Master Data HO & Site'!$S$1:$S$437,'Summary to Mgmt'!$C7,'Master Data HO & Site'!$Y$1:$Y$437,"Open",'Master Data HO & Site'!$N$1:$N$437,$H$2)),IF(C7="Jakarta",SUMIFS('Master Data HO & Site'!$AJ$1:$AJ$437,'Master Data HO & Site'!$F$1:$F$437,'Summary to Mgmt'!$D7,'Master Data HO & Site'!$H$1:$H$437,'Summary to Mgmt'!$E7,'Master Data HO & Site'!$Y$1:$Y$437,"Open",'Master Data HO & Site'!$N$1:$N$437,$H$2),SUMIFS('Master Data HO & Site'!$AJ$1:$AJ$437,'Master Data HO & Site'!$S$1:$S$437,'Summary to Mgmt'!$C7,'Master Data HO & Site'!$Y$1:$Y$437,"Open",'Master Data HO & Site'!$N$1:$N$437,$H$2)))) -> 0 | S7: =IF($H$2="All",IF(C7="Jakarta",SUMIFS('Master Data HO & Site'!$AK$1:$AK$437,'Master Data HO & Site'!$F$1:$F$437,'Summary to Mgmt'!$D7,'Master Data HO & Site'!$H$1:$H$437,'Summary to Mgmt'!$E7,'Master Data HO & Site'!$Y$1:$Y$437,"Open"),SUMIFS('Master Data HO & Site'!$AK$1:$AK$437,'Master Data HO & Site'!$S$1:$S$437,'Summary to Mgmt'!$C7,'Master Data HO & Site'!$Y$1:$Y$437,"Open")),IF($H$2="Urgent",IF(C7="Jakarta",SUMIFS('Master Data HO & Site'!$AK$1:$AK$437,'Master Data HO & Site'!$F$1:$F$437,'Summary to Mgmt'!$D7,'Master Data HO & Site'!$H$1:$H$437,'Summary to Mgmt'!$E7,'Master Data HO & Site'!$Y$1:$Y$437,"Open",'Master Data HO & Site'!$N$1:$N$437,$H$2),SUMIFS('Master Data HO & Site'!$AK$1:$AK$437,'Master Data HO & Site'!$S$1:$S$437,'Summary to Mgmt'!$C7,'Master Data HO & Site'!$Y$1:$Y$437,"Open",'Master Data HO & Site'!$N$1:$N$437,$H$2)),IF(C7="Jakarta",SUMIFS('Master Data HO & Site'!$AK$1:$AK$437,'Master Data HO & Site'!$F$1:$F$437,'Summary to Mgmt'!$D7,'Master Data HO & Site'!$H$1:$H$437,'Summary to Mgmt'!$E7,'Master Data HO & Site'!$Y$1:$Y$437,"Open",'Master Data HO & Site'!$N$1:$N$437,$H$2),SUMIFS('Master Data HO & Site'!$AK$1:$AK$437,'Master Data HO & Site'!$S$1:$S$437,'Summary to Mgmt'!$C7,'Master Data HO & Site'!$Y$1:$Y$437,"Open",'Master Data HO & Site'!$N$1:$N$437,$H$2)))) -> 0 | T7: =IF($H$2="All",IF(C7="Jakarta",SUMIFS('Master Data HO & Site'!$AL$1:$AL$437,'Master Data HO & Site'!$F$1:$F$437,'Summary to Mgmt'!$D7,'Master Data HO & Site'!$H$1:$H$437,'Summary to Mgmt'!$E7,'Master Data HO & Site'!$Y$1:$Y$437,"Open"),SUMIFS('Master Data HO & Site'!$AL$1:$AL$437,'Master Data HO & Site'!$S$1:$S$437,'Summary to Mgmt'!$C7,'Master Data HO & Site'!$Y$1:$Y$437,"Open")),IF($H$2="Urgent",IF(C7="Jakarta",SUMIFS('Master Data HO & Site'!$AL$1:$AL$437,'Master Data HO & Site'!$F$1:$F$437,'Summary to Mgmt'!$D7,'Master Data HO & Site'!$H$1:$H$437,'Summary to Mgmt'!$E7,'Master Data HO & Site'!$Y$1:$Y$437,"Open",'Master Data HO & Site'!$N$1:$N$437,$H$2),SUMIFS('Master Data HO & Site'!$AL$1:$AL$437,'Master Data HO & Site'!$S$1:$S$437,'Summary to Mgmt'!$C7,'Master Data HO & Site'!$Y$1:$Y$437,"Open",'Master Data HO & Site'!$N$1:$N$437,$H$2)),IF(C7="Jakarta",SUMIFS('Master Data HO & Site'!$AL$1:$AL$437,'Master Data HO & Site'!$F$1:$F$437,'Summary to Mgmt'!$D7,'Master Data HO & Site'!$H$1:$H$437,'Summary to Mgmt'!$E7,'Master Data HO & Site'!$Y$1:$Y$437,"Open",'Master Data HO & Site'!$N$1:$N$437,$H$2),SUMIFS('Master Data HO & Site'!$AL$1:$AL$437,'Master Data HO & Site'!$S$1:$S$437,'Summary to Mgmt'!$C7,'Master Data HO & Site'!$Y$1:$Y$437,"Open",'Master Data HO & Site'!$N$1:$N$437,$H$2)))) -> 0 | U7: =IF($H$2="All",IF(C7="Jakarta",SUMIFS('Master Data HO & Site'!$AM$1:$AM$437,'Master Data HO & Site'!$S$1:$S$437,'Summary to Mgmt'!$C7,'Master Data HO & Site'!$F$1:$F$437,'Summary to Mgmt'!$D7,'Master Data HO & Site'!$H$1:$H$437,'Summary to Mgmt'!$E7,'Master Data HO & Site'!$Y$1:$Y$437,"Open"),SUMIFS('Master Data HO & Site'!$AM$1:$AM$437,'Master Data HO & Site'!$S$1:$S$437,'Summary to Mgmt'!$C7,'Master Data HO & Site'!$Y$1:$Y$437,"Open")),IF($H$2="Urgent",IF(C7="Jakarta",SUMIFS('Master Data HO & Site'!$AM$1:$AM$437,'Master Data HO & Site'!$F$1:$F$437,'Summary to Mgmt'!$D7,'Master Data HO & Site'!$H$1:$H$437,'Summary to Mgmt'!$E7,'Master Data HO & Site'!$Y$1:$Y$437,"Open",'Master Data HO & Site'!$N$1:$N$437,$H$2),SUMIFS('Master Data HO & Site'!$AM$1:$AM$437,'Master Data HO & Site'!$S$1:$S$437,'Summary to Mgmt'!$C7,'Master Data HO & Site'!$Y$1:$Y$437,"Open",'Master Data HO & Site'!$N$1:$N$437,$H$2)),IF(C7="Jakarta",SUMIFS('Master Data HO & Site'!$AM$1:$AM$437,'Master Data HO & Site'!$F$1:$F$437,'Summary to Mgmt'!$D7,'Master Data HO & Site'!$H$1:$H$437,'Summary to Mgmt'!$E7,'Master Data HO & Site'!$Y$1:$Y$437,"Open",'Master Data HO & Site'!$N$1:$N$437,$H$2),SUMIFS('Master Data HO & Site'!$AM$1:$AM$437,'Master Data HO & Site'!$S$1:$S$437,'Summary to Mgmt'!$C7,'Master Data HO & Site'!$Y$1:$Y$437,"Open",'Master Data HO & Site'!$N$1:$N$437,$H$2)))) -> 0 | V7: =IF($H$2="All",IF(C7="Jakarta",SUMIFS('Master Data HO & Site'!$AN$1:$AN$437,'Master Data HO & Site'!$F$1:$F$437,'Summary to Mgmt'!$D7,'Master Data HO & Site'!$H$1:$H$437,'Summary to Mgmt'!$E7,'Master Data HO & Site'!$Y$1:$Y$437,"Open"),SUMIFS('Master Data HO & Site'!$AN$1:$AN$437,'Master Data HO & Site'!$S$1:$S$437,'Summary to Mgmt'!$C7,'Master Data HO & Site'!$Y$1:$Y$437,"Open")),IF($H$2="Urgent",IF(C7="Jakarta",SUMIFS('Master Data HO & Site'!$AN$1:$AN$437,'Master Data HO & Site'!$F$1:$F$437,'Summary to Mgmt'!$D7,'Master Data HO & Site'!$H$1:$H$437,'Summary to Mgmt'!$E7,'Master Data HO & Site'!$Y$1:$Y$437,"Open",'Master Data HO & Site'!$N$1:$N$437,$H$2),SUMIFS('Master Data HO & Site'!$AN$1:$AN$437,'Master Data HO & Site'!$S$1:$S$437,'Summary to Mgmt'!$C7,'Master Data HO & Site'!$Y$1:$Y$437,"Open",'Master Data HO & Site'!$N$1:$N$437,$H$2)),IF(C7="Jakarta",SUMIFS('Master Data HO & Site'!$AN$1:$AN$437,'Master Data HO & Site'!$F$1:$F$437,'Summary to Mgmt'!$D7,'Master Data HO & Site'!$H$1:$H$437,'Summary to Mgmt'!$E7,'Master Data HO & Site'!$Y$1:$Y$437,"Open",'Master Data HO & Site'!$N$1:$N$437,$H$2),SUMIFS('Master Data HO & Site'!$AN$1:$AN$437,'Master Data HO & Site'!$S$1:$S$437,'Summary to Mgmt'!$C7,'Master Data HO & Site'!$Y$1:$Y$437,"Open",'Master Data HO & Site'!$N$1:$N$437,$H$2)))) -> 0 | W7: =IF($H$2="All",IF(C7="Jakarta",SUMIFS('Master Data HO & Site'!$AO$1:$AO$437,'Master Data HO & Site'!$F$1:$F$437,'Summary to Mgmt'!$D7,'Master Data HO & Site'!$H$1:$H$437,'Summary to Mgmt'!$E7,'Master Data HO & Site'!$Y$1:$Y$437,"Open"),SUMIFS('Master Data HO & Site'!$AO$1:$AO$437,'Master Data HO & Site'!$S$1:$S$437,'Summary to Mgmt'!$C7,'Master Data HO & Site'!$Y$1:$Y$437,"Open")),IF($H$2="Urgent",IF(C7="Jakarta",SUMIFS('Master Data HO & Site'!$AO$1:$AO$437,'Master Data HO & Site'!$F$1:$F$437,'Summary to Mgmt'!$D7,'Master Data HO & Site'!$H$1:$H$437,'Summary to Mgmt'!$E7,'Master Data HO & Site'!$Y$1:$Y$437,"Open",'Master Data HO & Site'!$N$1:$N$437,$H$2),SUMIFS('Master Data HO & Site'!$AO$1:$AO$437,'Master Data HO & Site'!$S$1:$S$437,'Summary to Mgmt'!$C7,'Master Data HO & Site'!$Y$1:$Y$437,"Open",'Master Data HO & Site'!$N$1:$N$437,$H$2)),IF(C7="Jakarta",SUMIFS('Master Data HO & Site'!$AO$1:$AO$437,'Master Data HO & Site'!$F$1:$F$437,'Summary to Mgmt'!$D7,'Master Data HO & Site'!$H$1:$H$437,'Summary to Mgmt'!$E7,'Master Data HO & Site'!$Y$1:$Y$437,"Open",'Master Data HO & Site'!$N$1:$N$437,$H$2),SUMIFS('Master Data HO & Site'!$AO$1:$AO$437,'Master Data HO & Site'!$S$1:$S$437,'Summary to Mgmt'!$C7,'Master Data HO & Site'!$Y$1:$Y$437,"Open",'Master Data HO & Site'!$N$1:$N$437,$H$2)))) -> 0 | X7: =IF($H$2="All",IF(C7="Jakarta",SUMIFS('Master Data HO & Site'!$AP$1:$AP$437,'Master Data HO & Site'!$F$1:$F$437,'Summary to Mgmt'!$D7,'Master Data HO & Site'!$H$1:$H$437,'Summary to Mgmt'!$E7,'Master Data HO & Site'!$Y$1:$Y$437,"Open"),SUMIFS('Master Data HO & Site'!$AP$1:$AP$437,'Master Data HO & Site'!$S$1:$S$437,'Summary to Mgmt'!$C7,'Master Data HO & Site'!$Y$1:$Y$437,"Open")),IF($H$2="Urgent",IF(C7="Jakarta",SUMIFS('Master Data HO & Site'!$AP$1:$AP$437,'Master Data HO & Site'!$F$1:$F$437,'Summary to Mgmt'!$D7,'Master Data HO & Site'!$H$1:$H$437,'Summary to Mgmt'!$E7,'Master Data HO & Site'!$Y$1:$Y$437,"Open",'Master Data HO & Site'!$N$1:$N$437,$H$2),SUMIFS('Master Data HO & Site'!$AP$1:$AP$437,'Master Data HO & Site'!$S$1:$S$437,'Summary to Mgmt'!$C7,'Master Data HO & Site'!$Y$1:$Y$437,"Open",'Master Data HO & Site'!$N$1:$N$437,$H$2)),IF(C7="Jakarta",SUMIFS('Master Data HO & Site'!$AP$1:$AP$437,'Master Data HO & Site'!$F$1:$F$437,'Summary to Mgmt'!$D7,'Master Data HO & Site'!$H$1:$H$437,'Summary to Mgmt'!$E7,'Master Data HO & Site'!$Y$1:$Y$437,"Open",'Master Data HO & Site'!$N$1:$N$437,$H$2),SUMIFS('Master Data HO & Site'!$AP$1:$AP$437,'Master Data HO & Site'!$S$1:$S$437,'Summary to Mgmt'!$C7,'Master Data HO & Site'!$Y$1:$Y$437,"Open",'Master Data HO & Site'!$N$1:$N$437,$H$2)))) -> 0 | Y7: =IF($H$2="All",IF(C7="Jakarta",SUMIFS('Master Data HO & Site'!$AQ$1:$AQ$437,'Master Data HO & Site'!$F$1:$F$437,'Summary to Mgmt'!$D7,'Master Data HO & Site'!$H$1:$H$437,'Summary to Mgmt'!$E7,'Master Data HO & Site'!$Y$1:$Y$437,"Open"),SUMIFS('Master Data HO & Site'!$AQ$1:$AQ$437,'Master Data HO & Site'!$S$1:$S$437,'Summary to Mgmt'!$C7,'Master Data HO & Site'!$Y$1:$Y$437,"Open")),IF($H$2="Urgent",IF(C7="Jakarta",SUMIFS('Master Data HO & Site'!$AQ$1:$AQ$437,'Master Data HO & Site'!$F$1:$F$437,'Summary to Mgmt'!$D7,'Master Data HO & Site'!$H$1:$H$437,'Summary to Mgmt'!$E7,'Master Data HO & Site'!$Y$1:$Y$437,"Open",'Master Data HO & Site'!$N$1:$N$437,$H$2),SUMIFS('Master Data HO & Site'!$AQ$1:$AQ$437,'Master Data HO & Site'!$S$1:$S$437,'Summary to Mgmt'!$C7,'Master Data HO & Site'!$Y$1:$Y$437,"Open",'Master Data HO & Site'!$N$1:$N$437,$H$2)),IF(C7="Jakarta",SUMIFS('Master Data HO & Site'!$AQ$1:$AQ$437,'Master Data HO & Site'!$F$1:$F$437,'Summary to Mgmt'!$D7,'Master Data HO & Site'!$H$1:$H$437,'Summary to Mgmt'!$E7,'Master Data HO & Site'!$Y$1:$Y$437,"Open",'Master Data HO & Site'!$N$1:$N$437,$H$2),SUMIFS('Master Data HO & Site'!$AQ$1:$AQ$437,'Master Data HO & Site'!$S$1:$S$437,'Summary to Mgmt'!$C7,'Master Data HO & Site'!$Y$1:$Y$437,"Open",'Master Data HO & Site'!$N$1:$N$437,$H$2)))) -> 0 | Z7: =IF($H$2="All",IF(C7="Jakarta",SUMIFS('Master Data HO & Site'!$AR$1:$AR$437,'Master Data HO & Site'!$F$1:$F$437,'Summary to Mgmt'!$D7,'Master Data HO & Site'!$H$1:$H$437,'Summary to Mgmt'!$E7,'Master Data HO & Site'!$Y$1:$Y$437,"Open"),SUMIFS('Master Data HO & Site'!$AR$1:$AR$437,'Master Data HO & Site'!$S$1:$S$437,'Summary to Mgmt'!$C7,'Master Data HO & Site'!$Y$1:$Y$437,"Open")),IF($H$2="Urgent",IF(C7="Jakarta",SUMIFS('Master Data HO & Site'!$AR$1:$AR$437,'Master Data HO & Site'!$F$1:$F$437,'Summary to Mgmt'!$D7,'Master Data HO & Site'!$H$1:$H$437,'Summary to Mgmt'!$E7,'Master Data HO & Site'!$Y$1:$Y$437,"Open",'Master Data HO & Site'!$N$1:$N$437,$H$2),SUMIFS('Master Data HO & Site'!$AR$1:$AR$437,'Master Data HO & Site'!$S$1:$S$437,'Summary to Mgmt'!$C7,'Master Data HO & Site'!$Y$1:$Y$437,"Open",'Master Data HO & Site'!$N$1:$N$437,$H$2)),IF(C7="Jakarta",SUMIFS('Master Data HO & Site'!$AR$1:$AR$437,'Master Data HO & Site'!$F$1:$F$437,'Summary to Mgmt'!$D7,'Master Data HO & Site'!$H$1:$H$437,'Summary to Mgmt'!$E7,'Master Data HO & Site'!$Y$1:$Y$437,"Open",'Master Data HO & Site'!$N$1:$N$437,$H$2),SUMIFS('Master Data HO & Site'!$AR$1:$AR$437,'Master Data HO & Site'!$S$1:$S$437,'Summary to Mgmt'!$C7,'Master Data HO & Site'!$Y$1:$Y$437,"Open",'Master Data HO & Site'!$N$1:$N$437,$H$2)))) -> 0 | AA7: =IF($H$2="All",IF(C7="Jakarta",SUMIFS('Master Data HO & Site'!$AS$1:$AS$437,'Master Data HO & Site'!$S$1:$S$437,'Summary to Mgmt'!$C7,'Master Data HO & Site'!$F$1:$F$437,'Summary to Mgmt'!$D7,'Master Data HO & Site'!$H$1:$H$437,'Summary to Mgmt'!$E7,'Master Data HO & Site'!$Y$1:$Y$437,"Open"),SUMIFS('Master Data HO & Site'!$AS$1:$AS$437,'Master Data HO & Site'!$S$1:$S$437,'Summary to Mgmt'!$C7,'Master Data HO & Site'!$Y$1:$Y$437,"Open")),IF($H$2="Urgent",IF(C7="Jakarta",SUMIFS('Master Data HO & Site'!$AS$1:$AS$437,'Master Data HO & Site'!$F$1:$F$437,'Summary to Mgmt'!$D7,'Master Data HO & Site'!$H$1:$H$437,'Summary to Mgmt'!$E7,'Master Data HO & Site'!$Y$1:$Y$437,"Open",'Master Data HO & Site'!$N$1:$N$437,$H$2),SUMIFS('Master Data HO & Site'!$AS$1:$AS$437,'Master Data HO & Site'!$S$1:$S$437,'Summary to Mgmt'!$C7,'Master Data HO & Site'!$Y$1:$Y$437,"Open",'Master Data HO & Site'!$N$1:$N$437,$H$2)),IF(C7="Jakarta",SUMIFS('Master Data HO & Site'!$AS$1:$AS$437,'Master Data HO & Site'!$F$1:$F$437,'Summary to Mgmt'!$D7,'Master Data HO & Site'!$H$1:$H$437,'Summary to Mgmt'!$E7,'Master Data HO & Site'!$Y$1:$Y$437,"Open",'Master Data HO & Site'!$N$1:$N$437,$H$2),SUMIFS('Master Data HO & Site'!$AS$1:$AS$437,'Master Data HO & Site'!$S$1:$S$437,'Summary to Mgmt'!$C7,'Master Data HO & Site'!$Y$1:$Y$437,"Open",'Master Data HO & Site'!$N$1:$N$437,$H$2)))) -> 0 | AB7: =IF($H$2="All",IF(C7="Jakarta",SUMIFS('Master Data HO & Site'!$AT$1:$AT$437,'Master Data HO & Site'!$F$1:$F$437,'Summary to Mgmt'!$D7,'Master Data HO & Site'!$H$1:$H$437,'Summary to Mgmt'!$E7,'Master Data HO & Site'!$Y$1:$Y$437,"Open"),SUMIFS('Master Data HO & Site'!$AT$1:$AT$437,'Master Data HO & Site'!$S$1:$S$437,'Summary to Mgmt'!$C7,'Master Data HO & Site'!$Y$1:$Y$437,"Open")),IF($H$2="Urgent",IF(C7="Jakarta",SUMIFS('Master Data HO & Site'!$AT$1:$AT$437,'Master Data HO & Site'!$F$1:$F$437,'Summary to Mgmt'!$D7,'Master Data HO & Site'!$H$1:$H$437,'Summary to Mgmt'!$E7,'Master Data HO & Site'!$Y$1:$Y$437,"Open",'Master Data HO & Site'!$N$1:$N$437,$H$2),SUMIFS('Master Data HO & Site'!$AT$1:$AT$437,'Master Data HO & Site'!$S$1:$S$437,'Summary to Mgmt'!$C7,'Master Data HO & Site'!$Y$1:$Y$437,"Open",'Master Data HO & Site'!$N$1:$N$437,$H$2)),IF(C7="Jakarta",SUMIFS('Master Data HO & Site'!$AT$1:$AT$437,'Master Data HO & Site'!$F$1:$F$437,'Summary to Mgmt'!$D7,'Master Data HO & Site'!$H$1:$H$437,'Summary to Mgmt'!$E7,'Master Data HO & Site'!$Y$1:$Y$437,"Open",'Master Data HO & Site'!$N$1:$N$437,$H$2),SUMIFS('Master Data HO & Site'!$AT$1:$AT$437,'Master Data HO & Site'!$S$1:$S$437,'Summary to Mgmt'!$C7,'Master Data HO & Site'!$Y$1:$Y$437,"Open",'Master Data HO & Site'!$N$1:$N$437,$H$2)))) -> 0 | AC7: =IF($H$2="All",IF(C7="Jakarta",SUMIFS('Master Data HO & Site'!$AU$1:$AU$437,'Master Data HO & Site'!$F$1:$F$437,'Summary to Mgmt'!$D7,'Master Data HO & Site'!$H$1:$H$437,'Summary to Mgmt'!$E7,'Master Data HO & Site'!$Y$1:$Y$437,"Open"),SUMIFS('Master Data HO & Site'!$AU$1:$AU$437,'Master Data HO & Site'!$S$1:$S$437,'Summary to Mgmt'!$C7,'Master Data HO & Site'!$Y$1:$Y$437,"Open")),IF($H$2="Urgent",IF(C7="Jakarta",SUMIFS('Master Data HO & Site'!$AU$1:$AU$437,'Master Data HO & Site'!$F$1:$F$437,'Summary to Mgmt'!$D7,'Master Data HO & Site'!$H$1:$H$437,'Summary to Mgmt'!$E7,'Master Data HO & Site'!$Y$1:$Y$437,"Open",'Master Data HO & Site'!$N$1:$N$437,$H$2),SUMIFS('Master Data HO & Site'!$AU$1:$AU$437,'Master Data HO & Site'!$S$1:$S$437,'Summary to Mgmt'!$C7,'Master Data HO & Site'!$Y$1:$Y$437,"Open",'Master Data HO & Site'!$N$1:$N$437,$H$2)),IF(C7="Jakarta",SUMIFS('Master Data HO & Site'!$AU$1:$AU$437,'Master Data HO & Site'!$F$1:$F$437,'Summary to Mgmt'!$D7,'Master Data HO & Site'!$H$1:$H$437,'Summary to Mgmt'!$E7,'Master Data HO & Site'!$Y$1:$Y$437,"Open",'Master Data HO & Site'!$N$1:$N$437,$H$2),SUMIFS('Master Data HO & Site'!$AU$1:$AU$437,'Master Data HO & Site'!$S$1:$S$437,'Summary to Mgmt'!$C7,'Master Data HO & Site'!$Y$1:$Y$437,"Open",'Master Data HO & Site'!$N$1:$N$437,$H$2)))) -> 0 | AD7: =IF($H$2="All",IF(C7="Jakarta",SUMIFS('Master Data HO & Site'!$AV$1:$AV$437,'Master Data HO & Site'!$F$1:$F$437,'Summary to Mgmt'!$D7,'Master Data HO & Site'!$H$1:$H$437,'Summary to Mgmt'!$E7,'Master Data HO & Site'!$Y$1:$Y$437,"Open"),SUMIFS('Master Data HO & Site'!$AV$1:$AV$437,'Master Data HO & Site'!$S$1:$S$437,'Summary to Mgmt'!$C7,'Master Data HO & Site'!$Y$1:$Y$437,"Open")),IF($H$2="Urgent",IF(C7="Jakarta",SUMIFS('Master Data HO & Site'!$AV$1:$AV$437,'Master Data HO & Site'!$F$1:$F$437,'Summary to Mgmt'!$D7,'Master Data HO & Site'!$H$1:$H$437,'Summary to Mgmt'!$E7,'Master Data HO & Site'!$Y$1:$Y$437,"Open",'Master Data HO & Site'!$N$1:$N$437,$H$2),SUMIFS('Master Data HO & Site'!$AV$1:$AV$437,'Master Data HO & Site'!$S$1:$S$437,'Summary to Mgmt'!$C7,'Master Data HO & Site'!$Y$1:$Y$437,"Open",'Master Data HO & Site'!$N$1:$N$437,$H$2)),IF(C7="Jakarta",SUMIFS('Master Data HO & Site'!$AV$1:$AV$437,'Master Data HO & Site'!$F$1:$F$437,'Summary to Mgmt'!$D7,'Master Data HO & Site'!$H$1:$H$437,'Summary to Mgmt'!$E7,'Master Data HO & Site'!$Y$1:$Y$437,"Open",'Master Data HO & Site'!$N$1:$N$437,$H$2),SUMIFS('Master Data HO & Site'!$AV$1:$AV$437,'Master Data HO & Site'!$S$1:$S$437,'Summary to Mgmt'!$C7,'Master Data HO & Site'!$Y$1:$Y$437,"Open",'Master Data HO & Site'!$N$1:$N$437,$H$2)))) -> 0 | AE7: =IF($H$2="All",IF(C7="Jakarta",SUMIFS('Master Data HO & Site'!$AW$1:$AW$437,'Master Data HO & Site'!$F$1:$F$437,'Summary to Mgmt'!$D7,'Master Data HO & Site'!$H$1:$H$437,'Summary to Mgmt'!$E7,'Master Data HO & Site'!$Y$1:$Y$437,"Open"),SUMIFS('Master Data HO & Site'!$AW$1:$AW$437,'Master Data HO & Site'!$S$1:$S$437,'Summary to Mgmt'!$C7,'Master Data HO & Site'!$Y$1:$Y$437,"Open")),IF($H$2="Urgent",IF(C7="Jakarta",SUMIFS('Master Data HO & Site'!$AW$1:$AW$437,'Master Data HO & Site'!$F$1:$F$437,'Summary to Mgmt'!$D7,'Master Data HO & Site'!$H$1:$H$437,'Summary to Mgmt'!$E7,'Master Data HO & Site'!$Y$1:$Y$437,"Open",'Master Data HO & Site'!$N$1:$N$437,$H$2),SUMIFS('Master Data HO & Site'!$AW$1:$AW$437,'Master Data HO & Site'!$S$1:$S$437,'Summary to Mgmt'!$C7,'Master Data HO & Site'!$Y$1:$Y$437,"Open",'Master Data HO & Site'!$N$1:$N$437,$H$2)),IF(C7="Jakarta",SUMIFS('Master Data HO & Site'!$AW$1:$AW$437,'Master Data HO & Site'!$F$1:$F$437,'Summary to Mgmt'!$D7,'Master Data HO & Site'!$H$1:$H$437,'Summary to Mgmt'!$E7,'Master Data HO & Site'!$Y$1:$Y$437,"Open",'Master Data HO & Site'!$N$1:$N$437,$H$2),SUMIFS('Master Data HO & Site'!$AW$1:$AW$437,'Master Data HO & Site'!$S$1:$S$437,'Summary to Mgmt'!$C7,'Master Data HO & Site'!$Y$1:$Y$437,"Open",'Master Data HO & Site'!$N$1:$N$437,$H$2)))) -> 0 | AF7: =IF($H$2="All",IF(C7="Jakarta",SUMIFS('Master Data HO & Site'!$AX$1:$AX$437,'Master Data HO & Site'!$F$1:$F$437,'Summary to Mgmt'!$D7,'Master Data HO & Site'!$H$1:$H$437,'Summary to Mgmt'!$E7,'Master Data HO & Site'!$Y$1:$Y$437,"Open"),SUMIFS('Master Data HO & Site'!$AX$1:$AX$437,'Master Data HO & Site'!$S$1:$S$437,'Summary to Mgmt'!$C7,'Master Data HO & Site'!$Y$1:$Y$437,"Open")),IF($H$2="Urgent",IF(C7="Jakarta",SUMIFS('Master Data HO & Site'!$AX$1:$AX$437,'Master Data HO & Site'!$F$1:$F$437,'Summary to Mgmt'!$D7,'Master Data HO & Site'!$H$1:$H$437,'Summary to Mgmt'!$E7,'Master Data HO & Site'!$Y$1:$Y$437,"Open",'Master Data HO & Site'!$N$1:$N$437,$H$2),SUMIFS('Master Data HO & Site'!$AX$1:$AX$437,'Master Data HO & Site'!$S$1:$S$437,'Summary to Mgmt'!$C7,'Master Data HO & Site'!$Y$1:$Y$437,"Open",'Master Data HO & Site'!$N$1:$N$437,$H$2)),IF(C7="Jakarta",SUMIFS('Master Data HO & Site'!$AX$1:$AX$437,'Master Data HO & Site'!$F$1:$F$437,'Summary to Mgmt'!$D7,'Master Data HO & Site'!$H$1:$H$437,'Summary to Mgmt'!$E7,'Master Data HO & Site'!$Y$1:$Y$437,"Open",'Master Data HO & Site'!$N$1:$N$437,$H$2),SUMIFS('Master Data HO & Site'!$AX$1:$AX$437,'Master Data HO & Site'!$S$1:$S$437,'Summary to Mgmt'!$C7,'Master Data HO & Site'!$Y$1:$Y$437,"Open",'Master Data HO & Site'!$N$1:$N$437,$H$2)))) -> 0 | AG7: =IF($H$2="All",IF(C7="Jakarta",SUMIFS('Master Data HO & Site'!$AY$1:$AY$437,'Master Data HO & Site'!$S$1:$S$437,'Summary to Mgmt'!$C7,'Master Data HO & Site'!$F$1:$F$437,'Summary to Mgmt'!$D7,'Master Data HO & Site'!$H$1:$H$437,'Summary to Mgmt'!$E7,'Master Data HO & Site'!$Y$1:$Y$437,"Open"),SUMIFS('Master Data HO & Site'!$AY$1:$AY$437,'Master Data HO & Site'!$S$1:$S$437,'Summary to Mgmt'!$C7,'Master Data HO & Site'!$Y$1:$Y$437,"Open")),IF($H$2="Urgent",IF(C7="Jakarta",SUMIFS('Master Data HO & Site'!$AY$1:$AY$437,'Master Data HO & Site'!$F$1:$F$437,'Summary to Mgmt'!$D7,'Master Data HO & Site'!$H$1:$H$437,'Summary to Mgmt'!$E7,'Master Data HO & Site'!$Y$1:$Y$437,"Open",'Master Data HO & Site'!$N$1:$N$437,$H$2),SUMIFS('Master Data HO & Site'!$AY$1:$AY$437,'Master Data HO & Site'!$S$1:$S$437,'Summary to Mgmt'!$C7,'Master Data HO & Site'!$Y$1:$Y$437,"Open",'Master Data HO & Site'!$N$1:$N$437,$H$2)),IF(C7="Jakarta",SUMIFS('Master Data HO & Site'!$AY$1:$AY$437,'Master Data HO & Site'!$F$1:$F$437,'Summary to Mgmt'!$D7,'Master Data HO & Site'!$H$1:$H$437,'Summary to Mgmt'!$E7,'Master Data HO & Site'!$Y$1:$Y$437,"Open",'Master Data HO & Site'!$N$1:$N$437,$H$2),SUMIFS('Master Data HO & Site'!$AY$1:$AY$437,'Master Data HO & Site'!$S$1:$S$437,'Summary to Mgmt'!$C7,'Master Data HO & Site'!$Y$1:$Y$437,"Open",'Master Data HO & Site'!$N$1:$N$437,$H$2)))) -> 0 | AH7: =IF($H$2="All",IF(C7="Jakarta",SUMIFS('Master Data HO & Site'!$AZ$1:$AZ$437,'Master Data HO & Site'!$F$1:$F$437,'Summary to Mgmt'!$D7,'Master Data HO & Site'!$H$1:$H$437,'Summary to Mgmt'!$E7,'Master Data HO & Site'!$Y$1:$Y$437,"Open"),SUMIFS('Master Data HO & Site'!$AZ$1:$AZ$437,'Master Data HO & Site'!$S$1:$S$437,'Summary to Mgmt'!$C7,'Master Data HO & Site'!$Y$1:$Y$437,"Open")),IF($H$2="Urgent",IF(C7="Jakarta",SUMIFS('Master Data HO & Site'!$AZ$1:$AZ$437,'Master Data HO & Site'!$F$1:$F$437,'Summary to Mgmt'!$D7,'Master Data HO & Site'!$H$1:$H$437,'Summary to Mgmt'!$E7,'Master Data HO & Site'!$Y$1:$Y$437,"Open",'Master Data HO & Site'!$N$1:$N$437,$H$2),SUMIFS('Master Data HO & Site'!$AZ$1:$AZ$437,'Master Data HO & Site'!$S$1:$S$437,'Summary to Mgmt'!$C7,'Master Data HO & Site'!$Y$1:$Y$437,"Open",'Master Data HO & Site'!$N$1:$N$437,$H$2)),IF(C7="Jakarta",SUMIFS('Master Data HO & Site'!$AZ$1:$AZ$437,'Master Data HO & Site'!$F$1:$F$437,'Summary to Mgmt'!$D7,'Master Data HO & Site'!$H$1:$H$437,'Summary to Mgmt'!$E7,'Master Data HO & Site'!$Y$1:$Y$437,"Open",'Master Data HO & Site'!$N$1:$N$437,$H$2),SUMIFS('Master Data HO & Site'!$AZ$1:$AZ$437,'Master Data HO & Site'!$S$1:$S$437,'Summary to Mgmt'!$C7,'Master Data HO & Site'!$Y$1:$Y$437,"Open",'Master Data HO & Site'!$N$1:$N$437,$H$2)))) -> 0 | AI7: =IF($H$2="All",IF(C7="Jakarta",SUMIFS('Master Data HO & Site'!$AZ$1:$AZ$437,'Master Data HO & Site'!$F$1:$F$437,'Summary to Mgmt'!$D7,'Master Data HO & Site'!$H$1:$H$437,'Summary to Mgmt'!$E7,'Master Data HO & Site'!$Y$1:$Y$437,"Open"),SUMIFS('Master Data HO & Site'!$AZ$1:$AZ$437,'Master Data HO & Site'!$S$1:$S$437,'Summary to Mgmt'!$C7,'Master Data HO & Site'!$Y$1:$Y$437,"Open")),IF($H$2="Urgent",IF(C7="Jakarta",SUMIFS('Master Data HO & Site'!$AZ$1:$AZ$437,'Master Data HO & Site'!$F$1:$F$437,'Summary to Mgmt'!$D7,'Master Data HO & Site'!$H$1:$H$437,'Summary to Mgmt'!$E7,'Master Data HO & Site'!$Y$1:$Y$437,"Open",'Master Data HO & Site'!$N$1:$N$437,$H$2),SUMIFS('Master Data HO & Site'!$AZ$1:$AZ$437,'Master Data HO & Site'!$S$1:$S$437,'Summary to Mgmt'!$C7,'Master Data HO & Site'!$Y$1:$Y$437,"Open",'Master Data HO & Site'!$N$1:$N$437,$H$2)),IF(C7="Jakarta",SUMIFS('Master Data HO & Site'!$AZ$1:$AZ$437,'Master Data HO & Site'!$F$1:$F$437,'Summary to Mgmt'!$D7,'Master Data HO & Site'!$H$1:$H$437,'Summary to Mgmt'!$E7,'Master Data HO & Site'!$Y$1:$Y$437,"Open",'Master Data HO & Site'!$N$1:$N$437,$H$2),SUMIFS('Master Data HO & Site'!$AZ$1:$AZ$437,'Master Data HO & Site'!$S$1:$S$437,'Summary to Mgmt'!$C7,'Master Data HO & Site'!$Y$1:$Y$437,"Open",'Master Data HO & Site'!$N$1:$N$437,$H$2)))) -> 0 | AJ7: =IF($H$2="All",IF(C7="Jakarta",SUMIFS('Master Data HO & Site'!$BB$1:$BB$437,'Master Data HO & Site'!$F$1:$F$437,'Summary to Mgmt'!$D7,'Master Data HO & Site'!$H$1:$H$437,'Summary to Mgmt'!$E7,'Master Data HO & Site'!$Y$1:$Y$437,"Open"),SUMIFS('Master Data HO & Site'!$BB$1:$BB$437,'Master Data HO & Site'!$S$1:$S$437,'Summary to Mgmt'!$C7,'Master Data HO & Site'!$Y$1:$Y$437,"Open")),IF($H$2="Urgent",IF(C7="Jakarta",SUMIFS('Master Data HO & Site'!$BB$1:$BB$437,'Master Data HO & Site'!$F$1:$F$437,'Summary to Mgmt'!$D7,'Master Data HO & Site'!$H$1:$H$437,'Summary to Mgmt'!$E7,'Master Data HO & Site'!$Y$1:$Y$437,"Open",'Master Data HO & Site'!$N$1:$N$437,$H$2),SUMIFS('Master Data HO & Site'!$BB$1:$BB$437,'Master Data HO & Site'!$S$1:$S$437,'Summary to Mgmt'!$C7,'Master Data HO & Site'!$Y$1:$Y$437,"Open",'Master Data HO & Site'!$N$1:$N$437,$H$2)),IF(C7="Jakarta",SUMIFS('Master Data HO & Site'!$BB$1:$BB$437,'Master Data HO & Site'!$F$1:$F$437,'Summary to Mgmt'!$D7,'Master Data HO & Site'!$H$1:$H$437,'Summary to Mgmt'!$E7,'Master Data HO & Site'!$Y$1:$Y$437,"Open",'Master Data HO & Site'!$N$1:$N$437,$H$2),SUMIFS('Master Data HO & Site'!$BB$1:$BB$437,'Master Data HO & Site'!$S$1:$S$437,'Summary to Mgmt'!$C7,'Master Data HO & Site'!$Y$1:$Y$437,"Open",'Master Data HO & Site'!$N$1:$N$437,$H$2)))) -> 0 | AK7: =IF($H$2="All",IF(C7="Jakarta",SUMIFS('Master Data HO & Site'!$BC$1:$BC$437,'Master Data HO & Site'!$F$1:$F$437,'Summary to Mgmt'!$D7,'Master Data HO & Site'!$H$1:$H$437,'Summary to Mgmt'!$E7,'Master Data HO & Site'!$Y$1:$Y$437,"Open"),SUMIFS('Master Data HO & Site'!$BC$1:$BC$437,'Master Data HO & Site'!$S$1:$S$437,'Summary to Mgmt'!$C7,'Master Data HO & Site'!$Y$1:$Y$437,"Open")),IF($H$2="Urgent",IF(C7="Jakarta",SUMIFS('Master Data HO & Site'!$BC$1:$BC$437,'Master Data HO & Site'!$F$1:$F$437,'Summary to Mgmt'!$D7,'Master Data HO & Site'!$H$1:$H$437,'Summary to Mgmt'!$E7,'Master Data HO & Site'!$Y$1:$Y$437,"Open",'Master Data HO & Site'!$N$1:$N$437,$H$2),SUMIFS('Master Data HO & Site'!$BC$1:$BC$437,'Master Data HO & Site'!$S$1:$S$437,'Summary to Mgmt'!$C7,'Master Data HO & Site'!$Y$1:$Y$437,"Open",'Master Data HO & Site'!$N$1:$N$437,$H$2)),IF(C7="Jakarta",SUMIFS('Master Data HO & Site'!$BC$1:$BC$437,'Master Data HO & Site'!$F$1:$F$437,'Summary to Mgmt'!$D7,'Master Data HO & Site'!$H$1:$H$437,'Summary to Mgmt'!$E7,'Master Data HO & Site'!$Y$1:$Y$437,"Open",'Master Data HO & Site'!$N$1:$N$437,$H$2),SUMIFS('Master Data HO & Site'!$BC$1:$BC$437,'Master Data HO & Site'!$S$1:$S$437,'Summary to Mgmt'!$C7,'Master Data HO & Site'!$Y$1:$Y$437,"Open",'Master Data HO & Site'!$N$1:$N$437,$H$2)))) -> 0 | AL7: =IF($H$2="All",IF(C7="Jakarta",SUMIFS('Master Data HO & Site'!$BD$1:$BD$437,'Master Data HO & Site'!$F$1:$F$437,'Summary to Mgmt'!$D7,'Master Data HO & Site'!$H$1:$H$437,'Summary to Mgmt'!$E7,'Master Data HO & Site'!$Y$1:$Y$437,"Open"),SUMIFS('Master Data HO & Site'!$BD$1:$BD$437,'Master Data HO & Site'!$S$1:$S$437,'Summary to Mgmt'!$C7,'Master Data HO & Site'!$Y$1:$Y$437,"Open")),IF($H$2="Urgent",IF(C7="Jakarta",SUMIFS('Master Data HO & Site'!$BD$1:$BD$437,'Master Data HO & Site'!$F$1:$F$437,'Summary to Mgmt'!$D7,'Master Data HO & Site'!$H$1:$H$437,'Summary to Mgmt'!$E7,'Master Data HO & Site'!$Y$1:$Y$437,"Open",'Master Data HO & Site'!$N$1:$N$437,$H$2),SUMIFS('Master Data HO & Site'!$BD$1:$BD$437,'Master Data HO & Site'!$S$1:$S$437,'Summary to Mgmt'!$C7,'Master Data HO & Site'!$Y$1:$Y$437,"Open",'Master Data HO & Site'!$N$1:$N$437,$H$2)),IF(C7="Jakarta",SUMIFS('Master Data HO & Site'!$BD$1:$BD$437,'Master Data HO & Site'!$F$1:$F$437,'Summary to Mgmt'!$D7,'Master Data HO & Site'!$H$1:$H$437,'Summary to Mgmt'!$E7,'Master Data HO & Site'!$Y$1:$Y$437,"Open",'Master Data HO & Site'!$N$1:$N$437,$H$2),SUMIFS('Master Data HO & Site'!$BD$1:$BD$437,'Master Data HO & Site'!$S$1:$S$437,'Summary to Mgmt'!$C7,'Master Data HO & Site'!$Y$1:$Y$437,"Open",'Master Data HO & Site'!$N$1:$N$437,$H$2)))) -> 0 | AM7: =IF($H$2="All",IF(C7="Jakarta",SUMIFS('Master Data HO & Site'!$BE$1:$BE$437,'Master Data HO & Site'!$S$1:$S$437,'Summary to Mgmt'!$C7,'Master Data HO & Site'!$F$1:$F$437,'Summary to Mgmt'!$D7,'Master Data HO & Site'!$H$1:$H$437,'Summary to Mgmt'!$E7,'Master Data HO & Site'!$Y$1:$Y$437,"Open"),SUMIFS('Master Data HO & Site'!$BE$1:$BE$437,'Master Data HO & Site'!$S$1:$S$437,'Summary to Mgmt'!$C7,'Master Data HO & Site'!$Y$1:$Y$437,"Open")),IF($H$2="Urgent",IF(C7="Jakarta",SUMIFS('Master Data HO & Site'!$BE$1:$BE$437,'Master Data HO & Site'!$F$1:$F$437,'Summary to Mgmt'!$D7,'Master Data HO & Site'!$H$1:$H$437,'Summary to Mgmt'!$E7,'Master Data HO & Site'!$Y$1:$Y$437,"Open",'Master Data HO & Site'!$N$1:$N$437,$H$2),SUMIFS('Master Data HO & Site'!$BE$1:$BE$437,'Master Data HO & Site'!$S$1:$S$437,'Summary to Mgmt'!$C7,'Master Data HO & Site'!$Y$1:$Y$437,"Open",'Master Data HO & Site'!$N$1:$N$437,$H$2)),IF(C7="Jakarta",SUMIFS('Master Data HO & Site'!$BE$1:$BE$437,'Master Data HO & Site'!$F$1:$F$437,'Summary to Mgmt'!$D7,'Master Data HO & Site'!$H$1:$H$437,'Summary to Mgmt'!$E7,'Master Data HO & Site'!$Y$1:$Y$437,"Open",'Master Data HO & Site'!$N$1:$N$437,$H$2),SUMIFS('Master Data HO & Site'!$BE$1:$BE$437,'Master Data HO & Site'!$S$1:$S$437,'Summary to Mgmt'!$C7,'Master Data HO & Site'!$Y$1:$Y$437,"Open",'Master Data HO & Site'!$N$1:$N$437,$H$2)))) -> 0 | AN7: =IF($H$2="All",IF(C7="Jakarta",SUMIFS('Master Data HO & Site'!$BF$1:$BF$437,'Master Data HO & Site'!$F$1:$F$437,'Summary to Mgmt'!$D7,'Master Data HO & Site'!$H$1:$H$437,'Summary to Mgmt'!$E7,'Master Data HO & Site'!$Y$1:$Y$437,"Open"),SUMIFS('Master Data HO & Site'!$BF$1:$BF$437,'Master Data HO & Site'!$S$1:$S$437,'Summary to Mgmt'!$C7,'Master Data HO & Site'!$Y$1:$Y$437,"Open")),IF($H$2="Urgent",IF(C7="Jakarta",SUMIFS('Master Data HO & Site'!$BF$1:$BF$437,'Master Data HO & Site'!$F$1:$F$437,'Summary to Mgmt'!$D7,'Master Data HO & Site'!$H$1:$H$437,'Summary to Mgmt'!$E7,'Master Data HO & Site'!$Y$1:$Y$437,"Open",'Master Data HO & Site'!$N$1:$N$437,$H$2),SUMIFS('Master Data HO & Site'!$BF$1:$BF$437,'Master Data HO & Site'!$S$1:$S$437,'Summary to Mgmt'!$C7,'Master Data HO & Site'!$Y$1:$Y$437,"Open",'Master Data HO & Site'!$N$1:$N$437,$H$2)),IF(C7="Jakarta",SUMIFS('Master Data HO & Site'!$BF$1:$BF$437,'Master Data HO & Site'!$F$1:$F$437,'Summary to Mgmt'!$D7,'Master Data HO & Site'!$H$1:$H$437,'Summary to Mgmt'!$E7,'Master Data HO & Site'!$Y$1:$Y$437,"Open",'Master Data HO & Site'!$N$1:$N$437,$H$2),SUMIFS('Master Data HO & Site'!$BF$1:$BF$437,'Master Data HO & Site'!$S$1:$S$437,'Summary to Mgmt'!$C7,'Master Data HO & Site'!$Y$1:$Y$437,"Open",'Master Data HO & Site'!$N$1:$N$437,$H$2)))) -> 0 | AO7: =IF($H$2="All",IF(C7="Jakarta",SUMIFS('Master Data HO & Site'!$BG$1:$BG$437,'Master Data HO & Site'!$F$1:$F$437,'Summary to Mgmt'!$D7,'Master Data HO & Site'!$H$1:$H$437,'Summary to Mgmt'!$E7,'Master Data HO & Site'!$Y$1:$Y$437,"Open"),SUMIFS('Master Data HO & Site'!$BG$1:$BG$437,'Master Data HO & Site'!$S$1:$S$437,'Summary to Mgmt'!$C7,'Master Data HO & Site'!$Y$1:$Y$437,"Open")),IF($H$2="Urgent",IF(C7="Jakarta",SUMIFS('Master Data HO & Site'!$BG$1:$BG$437,'Master Data HO & Site'!$F$1:$F$437,'Summary to Mgmt'!$D7,'Master Data HO & Site'!$H$1:$H$437,'Summary to Mgmt'!$E7,'Master Data HO & Site'!$Y$1:$Y$437,"Open",'Master Data HO & Site'!$N$1:$N$437,$H$2),SUMIFS('Master Data HO & Site'!$BG$1:$BG$437,'Master Data HO & Site'!$S$1:$S$437,'Summary to Mgmt'!$C7,'Master Data HO & Site'!$Y$1:$Y$437,"Open",'Master Data HO & Site'!$N$1:$N$437,$H$2)),IF(C7="Jakarta",SUMIFS('Master Data HO & Site'!$BG$1:$BG$437,'Master Data HO & Site'!$F$1:$F$437,'Summary to Mgmt'!$D7,'Master Data HO & Site'!$H$1:$H$437,'Summary to Mgmt'!$E7,'Master Data HO & Site'!$Y$1:$Y$437,"Open",'Master Data HO & Site'!$N$1:$N$437,$H$2),SUMIFS('Master Data HO & Site'!$BG$1:$BG$437,'Master Data HO & Site'!$S$1:$S$437,'Summary to Mgmt'!$C7,'Master Data HO & Site'!$Y$1:$Y$437,"Open",'Master Data HO & Site'!$N$1:$N$437,$H$2)))) -> 0 | AP7: =IF($H$2="All",IF(C7="Jakarta",SUMIFS('Master Data HO & Site'!$BH$1:$BH$437,'Master Data HO & Site'!$F$1:$F$437,'Summary to Mgmt'!$D7,'Master Data HO & Site'!$H$1:$H$437,'Summary to Mgmt'!$E7,'Master Data HO & Site'!$Y$1:$Y$437,"Open"),SUMIFS('Master Data HO & Site'!$BH$1:$BH$437,'Master Data HO & Site'!$S$1:$S$437,'Summary to Mgmt'!$C7,'Master Data HO & Site'!$Y$1:$Y$437,"Open")),IF($H$2="Urgent",IF(C7="Jakarta",SUMIFS('Master Data HO & Site'!$BH$1:$BH$437,'Master Data HO & Site'!$F$1:$F$437,'Summary to Mgmt'!$D7,'Master Data HO & Site'!$H$1:$H$437,'Summary to Mgmt'!$E7,'Master Data HO & Site'!$Y$1:$Y$437,"Open",'Master Data HO & Site'!$N$1:$N$437,$H$2),SUMIFS('Master Data HO & Site'!$BH$1:$BH$437,'Master Data HO & Site'!$S$1:$S$437,'Summary to Mgmt'!$C7,'Master Data HO & Site'!$Y$1:$Y$437,"Open",'Master Data HO & Site'!$N$1:$N$437,$H$2)),IF(C7="Jakarta",SUMIFS('Master Data HO & Site'!$BH$1:$BH$437,'Master Data HO & Site'!$F$1:$F$437,'Summary to Mgmt'!$D7,'Master Data HO & Site'!$H$1:$H$437,'Summary to Mgmt'!$E7,'Master Data HO & Site'!$Y$1:$Y$437,"Open",'Master Data HO & Site'!$N$1:$N$437,$H$2),SUMIFS('Master Data HO & Site'!$BH$1:$BH$437,'Master Data HO & Site'!$S$1:$S$437,'Summary to Mgmt'!$C7,'Master Data HO & Site'!$Y$1:$Y$437,"Open",'Master Data HO & Site'!$N$1:$N$437,$H$2)))) -> 0 | AQ7: =IF($H$2="All",IF(C7="Jakarta",SUMIFS('Master Data HO & Site'!$BI$1:$BI$437,'Master Data HO & Site'!$F$1:$F$437,'Summary to Mgmt'!$D7,'Master Data HO & Site'!$H$1:$H$437,'Summary to Mgmt'!$E7,'Master Data HO & Site'!$Y$1:$Y$437,"Open"),SUMIFS('Master Data HO & Site'!$BI$1:$BI$437,'Master Data HO & Site'!$S$1:$S$437,'Summary to Mgmt'!$C7,'Master Data HO & Site'!$Y$1:$Y$437,"Open")),IF($H$2="Urgent",IF(C7="Jakarta",SUMIFS('Master Data HO & Site'!$BI$1:$BI$437,'Master Data HO & Site'!$F$1:$F$437,'Summary to Mgmt'!$D7,'Master Data HO & Site'!$H$1:$H$437,'Summary to Mgmt'!$E7,'Master Data HO & Site'!$Y$1:$Y$437,"Open",'Master Data HO & Site'!$N$1:$N$437,$H$2),SUMIFS('Master Data HO & Site'!$BI$1:$BI$437,'Master Data HO & Site'!$S$1:$S$437,'Summary to Mgmt'!$C7,'Master Data HO & Site'!$Y$1:$Y$437,"Open",'Master Data HO & Site'!$N$1:$N$437,$H$2)),IF(C7="Jakarta",SUMIFS('Master Data HO & Site'!$BI$1:$BI$437,'Master Data HO & Site'!$F$1:$F$437,'Summary to Mgmt'!$D7,'Master Data HO & Site'!$H$1:$H$437,'Summary to Mgmt'!$E7,'Master Data HO & Site'!$Y$1:$Y$437,"Open",'Master Data HO & Site'!$N$1:$N$437,$H$2),SUMIFS('Master Data HO & Site'!$BI$1:$BI$437,'Master Data HO & Site'!$S$1:$S$437,'Summary to Mgmt'!$C7,'Master Data HO & Site'!$Y$1:$Y$437,"Open",'Master Data HO & Site'!$N$1:$N$437,$H$2)))) -> 0 | AR7: =IF($H$2="All",IF(C7="Jakarta",SUMIFS('Master Data HO & Site'!$BJ$1:$BJ$437,'Master Data HO & Site'!$F$1:$F$437,'Summary to Mgmt'!$D7,'Master Data HO & Site'!$H$1:$H$437,'Summary to Mgmt'!$E7,'Master Data HO & Site'!$Y$1:$Y$437,"Open"),SUMIFS('Master Data HO & Site'!$BJ$1:$BJ$437,'Master Data HO & Site'!$S$1:$S$437,'Summary to Mgmt'!$C7,'Master Data HO & Site'!$Y$1:$Y$437,"Open")),IF($H$2="Urgent",IF(C7="Jakarta",SUMIFS('Master Data HO & Site'!$BJ$1:$BJ$437,'Master Data HO & Site'!$F$1:$F$437,'Summary to Mgmt'!$D7,'Master Data HO & Site'!$H$1:$H$437,'Summary to Mgmt'!$E7,'Master Data HO & Site'!$Y$1:$Y$437,"Open",'Master Data HO & Site'!$N$1:$N$437,$H$2),SUMIFS('Master Data HO & Site'!$BJ$1:$BJ$437,'Master Data HO & Site'!$S$1:$S$437,'Summary to Mgmt'!$C7,'Master Data HO & Site'!$Y$1:$Y$437,"Open",'Master Data HO & Site'!$N$1:$N$437,$H$2)),IF(C7="Jakarta",SUMIFS('Master Data HO & Site'!$BJ$1:$BJ$437,'Master Data HO & Site'!$F$1:$F$437,'Summary to Mgmt'!$D7,'Master Data HO & Site'!$H$1:$H$437,'Summary to Mgmt'!$E7,'Master Data HO & Site'!$Y$1:$Y$437,"Open",'Master Data HO & Site'!$N$1:$N$437,$H$2),SUMIFS('Master Data HO & Site'!$BJ$1:$BJ$437,'Master Data HO & Site'!$S$1:$S$437,'Summary to Mgmt'!$C7,'Master Data HO & Site'!$Y$1:$Y$437,"Open",'Master Data HO & Site'!$N$1:$N$437,$H$2)))) -> 0 | AS7: =IF($H$2="All",IF(C7="Jakarta",SUMIFS('Master Data HO & Site'!$BK$1:$BK$437,'Master Data HO & Site'!$S$1:$S$437,'Summary to Mgmt'!$C7,'Master Data HO & Site'!$F$1:$F$437,'Summary to Mgmt'!$D7,'Master Data HO & Site'!$H$1:$H$437,'Summary to Mgmt'!$E7,'Master Data HO & Site'!$Y$1:$Y$437,"Open"),SUMIFS('Master Data HO & Site'!$BK$1:$BK$437,'Master Data HO & Site'!$S$1:$S$437,'Summary to Mgmt'!$C7,'Master Data HO & Site'!$Y$1:$Y$437,"Open")),IF($H$2="Urgent",IF(C7="Jakarta",SUMIFS('Master Data HO & Site'!$BK$1:$BK$437,'Master Data HO & Site'!$F$1:$F$437,'Summary to Mgmt'!$D7,'Master Data HO & Site'!$H$1:$H$437,'Summary to Mgmt'!$E7,'Master Data HO & Site'!$Y$1:$Y$437,"Open",'Master Data HO & Site'!$N$1:$N$437,$H$2),SUMIFS('Master Data HO & Site'!$BK$1:$BK$437,'Master Data HO & Site'!$S$1:$S$437,'Summary to Mgmt'!$C7,'Master Data HO & Site'!$Y$1:$Y$437,"Open",'Master Data HO & Site'!$N$1:$N$437,$H$2)),IF(C7="Jakarta",SUMIFS('Master Data HO & Site'!$BK$1:$BK$437,'Master Data HO & Site'!$F$1:$F$437,'Summary to Mgmt'!$D7,'Master Data HO & Site'!$H$1:$H$437,'Summary to Mgmt'!$E7,'Master Data HO & Site'!$Y$1:$Y$437,"Open",'Master Data HO & Site'!$N$1:$N$437,$H$2),SUMIFS('Master Data HO & Site'!$BK$1:$BK$437,'Master Data HO & Site'!$S$1:$S$437,'Summary to Mgmt'!$C7,'Master Data HO & Site'!$Y$1:$Y$437,"Open",'Master Data HO & Site'!$N$1:$N$437,$H$2)))) -> 0 | AU7: =IF($H$2="All",IF(C7="Jakarta",COUNTIFS('Master Data HO & Site'!$F$1:$F$437,'Summary to Mgmt'!$D7,'Master Data HO & Site'!$H$1:$H$437,'Summary to Mgmt'!$E7,'Master Data HO & Site'!$Y$1:$Y$437,"Open",'Master Data HO & Site'!$BZ$1:$BZ$437,'Summary to Mgmt'!$AU$4),COUNTIFS('Master Data HO & Site'!$S$1:$S$437,'Summary to Mgmt'!$C7,'Master Data HO & Site'!$Y$1:$Y$437,"Open",'Master Data HO & Site'!$BZ$1:$BZ$437,'Summary to Mgmt'!$AU$4)),IF($H$2="Urgent",IF(C7="Jakarta",COUNTIFS('Master Data HO & Site'!$F$1:$F$437,'Summary to Mgmt'!$D7,'Master Data HO & Site'!$H$1:$H$437,'Summary to Mgmt'!$E7,'Master Data HO & Site'!$Y$1:$Y$437,"Open",'Master Data HO & Site'!$BZ$1:$BZ$437,'Summary to Mgmt'!$AU$4,'Master Data HO & Site'!$N$1:$N$437,$H$2),COUNTIFS('Master Data HO & Site'!$S$1:$S$437,'Summary to Mgmt'!$C7,'Master Data HO & Site'!$Y$1:$Y$437,"Open",'Master Data HO & Site'!$BZ$1:$BZ$437,'Summary to Mgmt'!$AU$4,'Master Data HO & Site'!$N$1:$N$437,$H$2)),IF(C7="Jakarta",COUNTIFS('Master Data HO & Site'!$F$1:$F$437,'Summary to Mgmt'!$D7,'Master Data HO & Site'!$H$1:$H$437,'Summary to Mgmt'!$E7,'Master Data HO & Site'!$Y$1:$Y$437,"Open",'Master Data HO & Site'!$BZ$1:$BZ$437,'Summary to Mgmt'!$AU$4,'Master Data HO & Site'!$N$1:$N$437,$H$2),COUNTIFS('Master Data HO & Site'!$S$1:$S$437,'Summary to Mgmt'!$C7,'Master Data HO & Site'!$Y$1:$Y$437,"Open",'Master Data HO & Site'!$BZ$1:$BZ$437,'Summary to Mgmt'!$AU$4,'Master Data HO & Site'!$N$1:$N$437,$H$2)))) -> 0 | AV7: =IF($H$2="All",IF(C7="Jakarta",COUNTIFS('Master Data HO & Site'!$F$1:$F$437,'Summary to Mgmt'!$D7,'Master Data HO & Site'!$H$1:$H$437,'Summary to Mgmt'!$E7,'Master Data HO & Site'!$Y$1:$Y$437,"Open",'Master Data HO & Site'!$BZ$1:$BZ$437,'Summary to Mgmt'!$AV$4),COUNTIFS('Master Data HO & Site'!$S$1:$S$437,'Summary to Mgmt'!$C7,'Master Data HO & Site'!$Y$1:$Y$437,"Open",'Master Data HO & Site'!$BZ$1:$BZ$437,'Summary to Mgmt'!$AV$4)),IF($H$2="Urgent",IF(C7="Jakarta",COUNTIFS('Master Data HO & Site'!$F$1:$F$437,'Summary to Mgmt'!$D7,'Master Data HO & Site'!$H$1:$H$437,'Summary to Mgmt'!$E7,'Master Data HO & Site'!$Y$1:$Y$437,"Open",'Master Data HO & Site'!$BZ$1:$BZ$437,'Summary to Mgmt'!$AV$4,'Master Data HO & Site'!$N$1:$N$437,$H$2),COUNTIFS('Master Data HO & Site'!$S$1:$S$437,'Summary to Mgmt'!$C7,'Master Data HO & Site'!$Y$1:$Y$437,"Open",'Master Data HO & Site'!$BZ$1:$BZ$437,'Summary to Mgmt'!$AV$4,'Master Data HO & Site'!$N$1:$N$437,$H$2)),IF(C7="Jakarta",COUNTIFS('Master Data HO & Site'!$F$1:$F$437,'Summary to Mgmt'!$D7,'Master Data HO & Site'!$H$1:$H$437,'Summary to Mgmt'!$E7,'Master Data HO & Site'!$Y$1:$Y$437,"Open",'Master Data HO & Site'!$BZ$1:$BZ$437,'Summary to Mgmt'!$AV$4,'Master Data HO & Site'!$N$1:$N$437,$H$2),COUNTIFS('Master Data HO & Site'!$S$1:$S$437,'Summary to Mgmt'!$C7,'Master Data HO & Site'!$Y$1:$Y$437,"Open",'Master Data HO & Site'!$BZ$1:$BZ$437,'Summary to Mgmt'!$AV$4,'Master Data HO & Site'!$N$1:$N$437,$H$2)))) -> 0 | AW7: =IF($H$2="All",IF(C7="Jakarta",COUNTIFS('Master Data HO & Site'!$F$1:$F$437,'Summary to Mgmt'!$D7,'Master Data HO & Site'!$H$1:$H$437,'Summary to Mgmt'!$E7,'Master Data HO & Site'!$Y$1:$Y$437,"Open",'Master Data HO & Site'!$BZ$1:$BZ$437,'Summary to Mgmt'!$AW$4),COUNTIFS('Master Data HO & Site'!$S$1:$S$437,'Summary to Mgmt'!$C7,'Master Data HO & Site'!$Y$1:$Y$437,"Open",'Master Data HO & Site'!$BZ$1:$BZ$437,'Summary to Mgmt'!$AW$4)),IF($H$2="Urgent",IF(C7="Jakarta",COUNTIFS('Master Data HO & Site'!$F$1:$F$437,'Summary to Mgmt'!$D7,'Master Data HO & Site'!$H$1:$H$437,'Summary to Mgmt'!$E7,'Master Data HO & Site'!$Y$1:$Y$437,"Open",'Master Data HO & Site'!$BZ$1:$BZ$437,'Summary to Mgmt'!$AW$4,'Master Data HO & Site'!$N$1:$N$437,$H$2),COUNTIFS('Master Data HO & Site'!$S$1:$S$437,'Summary to Mgmt'!$C7,'Master Data HO & Site'!$Y$1:$Y$437,"Open",'Master Data HO & Site'!$BZ$1:$BZ$437,'Summary to Mgmt'!$AW$4,'Master Data HO & Site'!$N$1:$N$437,$H$2)),IF(C7="Jakarta",COUNTIFS('Master Data HO & Site'!$F$1:$F$437,'Summary to Mgmt'!$D7,'Master Data HO & Site'!$H$1:$H$437,'Summary to Mgmt'!$E7,'Master Data HO & Site'!$Y$1:$Y$437,"Open",'Master Data HO & Site'!$BZ$1:$BZ$437,'Summary to Mgmt'!$AW$4,'Master Data HO & Site'!$N$1:$N$437,$H$2),COUNTIFS('Master Data HO & Site'!$S$1:$S$437,'Summary to Mgmt'!$C7,'Master Data HO & Site'!$Y$1:$Y$437,"Open",'Master Data HO & Site'!$BZ$1:$BZ$437,'Summary to Mgmt'!$AW$4,'Master Data HO & Site'!$N$1:$N$437,$H$2)))) -> 0 | AX7: =IF($H$2="All",IF(C7="Jakarta",COUNTIFS('Master Data HO & Site'!$F$1:$F$437,'Summary to Mgmt'!$D7,'Master Data HO & Site'!$H$1:$H$437,'Summary to Mgmt'!$E7,'Master Data HO & Site'!$Y$1:$Y$437,"Open",'Master Data HO & Site'!$BZ$1:$BZ$437,'Summary to Mgmt'!$AX$4),COUNTIFS('Master Data HO & Site'!$S$1:$S$437,'Summary to Mgmt'!$C7,'Master Data HO & Site'!$Y$1:$Y$437,"Open",'Master Data HO & Site'!$BZ$1:$BZ$437,'Summary to Mgmt'!$AX$4)),IF($H$2="Urgent",IF(C7="Jakarta",COUNTIFS('Master Data HO & Site'!$F$1:$F$437,'Summary to Mgmt'!$D7,'Master Data HO & Site'!$H$1:$H$437,'Summary to Mgmt'!$E7,'Master Data HO & Site'!$Y$1:$Y$437,"Open",'Master Data HO & Site'!$BZ$1:$BZ$437,'Summary to Mgmt'!$AX$4,'Master Data HO & Site'!$N$1:$N$437,$H$2),COUNTIFS('Master Data HO & Site'!$S$1:$S$437,'Summary to Mgmt'!$C7,'Master Data HO & Site'!$Y$1:$Y$437,"Open",'Master Data HO & Site'!$BZ$1:$BZ$437,'Summary to Mgmt'!$AX$4,'Master Data HO & Site'!$N$1:$N$437,$H$2)),IF(C7="Jakarta",COUNTIFS('Master Data HO & Site'!$F$1:$F$437,'Summary to Mgmt'!$D7,'Master Data HO & Site'!$H$1:$H$437,'Summary to Mgmt'!$E7,'Master Data HO & Site'!$Y$1:$Y$437,"Open",'Master Data HO & Site'!$BZ$1:$BZ$437,'Summary to Mgmt'!$AX$4,'Master Data HO & Site'!$N$1:$N$437,$H$2),COUNTIFS('Master Data HO & Site'!$S$1:$S$437,'Summary to Mgmt'!$C7,'Master Data HO & Site'!$Y$1:$Y$437,"Open",'Master Data HO & Site'!$BZ$1:$BZ$437,'Summary to Mgmt'!$AX$4,'Master Data HO & Site'!$N$1:$N$437,$H$2)))) -> 1
C8: Jakarta | D8: Commercial | E8: Asset Management | F8: =G8+H8 -> 1 | G8: =IF($H$2="All",IF(C8="Jakarta",SUMIFS('Master Data HO & Site'!$BM$1:$BM$437,'Master Data HO & Site'!$S$1:$S$437,'Summary to Mgmt'!C8,'Master Data HO & Site'!$F$1:$F$437,'Summary to Mgmt'!$D8,'Master Data HO & Site'!$H$1:$H$437,'Summary to Mgmt'!$E8,'Master Data HO & Site'!$Y$1:$Y$437,"Closed"),SUMIFS('Master Data HO & Site'!$BM$1:$BM$437,'Master Data HO & Site'!$S$1:$S$437,'Summary to Mgmt'!C8,'Master Data HO & Site'!$Y$1:$Y$437,"Closed")),IF(C8="Jakarta",SUMIFS('Master Data HO & Site'!$BM$1:$BM$437,'Master Data HO & Site'!$S$1:$S$437,'Summary to Mgmt'!C8,'Master Data HO & Site'!$F$1:$F$437,'Summary to Mgmt'!$D8,'Master Data HO & Site'!$H$1:$H$437,'Summary to Mgmt'!E8,'Master Data HO & Site'!$N$1:$N$437,'Summary to Mgmt'!$H$2,'Master Data HO & Site'!$Y$1:$Y$437,"Closed"),SUMIFS('Master Data HO & Site'!$BM$1:$BM$437,'Master Data HO & Site'!$S$1:$S$437,'Summary to Mgmt'!C8,'Master Data HO & Site'!$N$1:$N$437,'Summary to Mgmt'!$H$2,'Master Data HO & Site'!$Y$1:$Y$437,"Closed"))) -> 0 | H8: =IF($H$2="All",IF(C8="Jakarta",COUNTIFS('Master Data HO & Site'!$S$1:$S$437,'Summary to Mgmt'!$C8,'Master Data HO & Site'!$F$1:$F$437,'Summary to Mgmt'!$D8,'Master Data HO & Site'!$H$1:$H$437,'Summary to Mgmt'!$E8,'Master Data HO & Site'!$Y$1:$Y$437,"Open"),COUNTIFS('Master Data HO & Site'!$S$1:$S$437,'Summary to Mgmt'!$C8,'Master Data HO & Site'!$Y$1:$Y$437,"Open")),IF($H$2="Urgent",IF(C8="Jakarta",COUNTIFS('Master Data HO & Site'!$S$1:$S$437,'Summary to Mgmt'!$C8,'Master Data HO & Site'!$F$1:$F$437,'Summary to Mgmt'!$D8,'Master Data HO & Site'!$H$1:$H$437,'Summary to Mgmt'!$E8,'Master Data HO & Site'!$Y$1:$Y$437,"Open",'Master Data HO & Site'!$N$1:$N$437,$H$2),COUNTIFS('Master Data HO & Site'!$S$1:$S$437,'Summary to Mgmt'!$C8,'Master Data HO & Site'!$Y$1:$Y$437,"Open",'Master Data HO & Site'!$N$1:$N$437,$H$2)),IF(C8="Jakarta",COUNTIFS('Master Data HO & Site'!$F$1:$F$437,'Summary to Mgmt'!$D8,'Master Data HO & Site'!$H$1:$H$437,'Summary to Mgmt'!$E8,'Master Data HO & Site'!$Y$1:$Y$437,"Open",'Master Data HO & Site'!$N$1:$N$437,$H$2),COUNTIFS('Master Data HO & Site'!$S$1:$S$437,'Summary to Mgmt'!$C8,'Master Data HO & Site'!$Y$1:$Y$437,"Open",'Master Data HO & Site'!$N$1:$N$437,$H$2)))) -> 1 | I8: =IF($H$2="All",IF(C8="Jakarta",COUNTIFS('Master Data HO & Site'!$F$1:$F$437,'Summary to Mgmt'!$D8,'Master Data HO & Site'!$H$1:$H$437,'Summary to Mgmt'!$E8,'Master Data HO & Site'!$Y$1:$Y$437,"Open",'Master Data HO & Site'!$D$1:$D$437,"pending FKTK"),COUNTIFS('Master Data HO & Site'!$S$1:$S$437,'Summary to Mgmt'!$C8,'Master Data HO & Site'!$Y$1:$Y$437,"Open",'Master Data HO & Site'!$D$1:$D$437,"pending FKTK")),IF($H$2="Urgent",IF(C8="Jakarta",COUNTIFS('Master Data HO & Site'!$F$1:$F$437,'Summary to Mgmt'!$D8,'Master Data HO & Site'!$H$1:$H$437,'Summary to Mgmt'!$E8,'Master Data HO & Site'!$Y$1:$Y$437,"Open",'Master Data HO & Site'!$N$1:$N$437,$H$2,'Master Data HO & Site'!$D$1:$D$437,"pending FKTK"),COUNTIFS('Master Data HO & Site'!$S$1:$S$437,'Summary to Mgmt'!$C8,'Master Data HO & Site'!$Y$1:$Y$437,"Open",'Master Data HO & Site'!$N$1:$N$437,$H$2,'Master Data HO & Site'!$D$1:$D$437,"pending FKTK")),IF(C8="Jakarta",COUNTIFS('Master Data HO & Site'!$F$1:$F$437,'Summary to Mgmt'!$D8,'Master Data HO & Site'!$H$1:$H$437,'Summary to Mgmt'!$E8,'Master Data HO & Site'!$Y$1:$Y$437,"Open",'Master Data HO & Site'!$N$1:$N$437,$H$2,'Master Data HO & Site'!$D$1:$D$437,"pending FKTK"),COUNTIFS('Master Data HO & Site'!$S$1:$S$437,'Summary to Mgmt'!$C8,'Master Data HO & Site'!$Y$1:$Y$437,"Open",'Master Data HO & Site'!$N$1:$N$437,$H$2,'Master Data HO & Site'!$D$1:$D$437,"pending FKTK")))) -> 1 | J8: =IF($H$2="All",IF(C8="Jakarta",SUMIFS('Master Data HO & Site'!$AB$1:$AB$437,'Master Data HO & Site'!$F$1:$F$437,'Summary to Mgmt'!$D8,'Master Data HO & Site'!$H$1:$H$437,'Summary to Mgmt'!$E8,'Master Data HO & Site'!$Y$1:$Y$437,"Open"),SUMIFS('Master Data HO & Site'!$AB$1:$AB$437,'Master Data HO & Site'!$S$1:$S$437,'Summary to Mgmt'!$C8,'Master Data HO & Site'!$Y$1:$Y$437,"Open")),IF($H$2="Urgent",IF(C8="Jakarta",SUMIFS('Master Data HO & Site'!$AB$1:$AB$437,'Master Data HO & Site'!$F$1:$F$437,'Summary to Mgmt'!$D8,'Master Data HO & Site'!$H$1:$H$437,'Summary to Mgmt'!$E8,'Master Data HO & Site'!$Y$1:$Y$437,"Open",'Master Data HO & Site'!$N$1:$N$437,$H$2),SUMIFS('Master Data HO & Site'!$AB$1:$AB$437,'Master Data HO & Site'!$S$1:$S$437,'Summary to Mgmt'!$C8,'Master Data HO & Site'!$Y$1:$Y$437,"Open",'Master Data HO & Site'!$N$1:$N$437,$H$2)),IF(C8="Jakarta",SUMIFS('Master Data HO & Site'!$AB$1:$AB$437,'Master Data HO & Site'!$F$1:$F$437,'Summary to Mgmt'!$D8,'Master Data HO & Site'!$H$1:$H$437,'Summary to Mgmt'!$E8,'Master Data HO & Site'!$Y$1:$Y$437,"Open",'Master Data HO & Site'!$N$1:$N$437,$H$2),SUMIFS('Master Data HO & Site'!$AB$1:$AB$437,'Master Data HO & Site'!$S$1:$S$437,'Summary to Mgmt'!$C8,'Master Data HO & Site'!$Y$1:$Y$437,"Open",'Master Data HO & Site'!$N$1:$N$437,$H$2)))) -> 0 | K8: =IF($H$2="All",IF(C8="Jakarta",SUMIFS('Master Data HO & Site'!$AC$1:$AC$437,'Master Data HO & Site'!$F$1:$F$437,'Summary to Mgmt'!$D8,'Master Data HO & Site'!$H$1:$H$437,'Summary to Mgmt'!$E8,'Master Data HO & Site'!$Y$1:$Y$437,"Open"),SUMIFS('Master Data HO & Site'!$AC$1:$AC$437,'Master Data HO & Site'!$S$1:$S$437,'Summary to Mgmt'!$C8,'Master Data HO & Site'!$Y$1:$Y$437,"Open")),IF($H$2="Urgent",IF(C8="Jakarta",SUMIFS('Master Data HO & Site'!$AC$1:$AC$437,'Master Data HO & Site'!$F$1:$F$437,'Summary to Mgmt'!$D8,'Master Data HO & Site'!$H$1:$H$437,'Summary to Mgmt'!$E8,'Master Data HO & Site'!$Y$1:$Y$437,"Open",'Master Data HO & Site'!$N$1:$N$437,$H$2),SUMIFS('Master Data HO & Site'!$AC$1:$AC$437,'Master Data HO & Site'!$S$1:$S$437,'Summary to Mgmt'!$C8,'Master Data HO & Site'!$Y$1:$Y$437,"Open",'Master Data HO & Site'!$N$1:$N$437,$H$2)),IF(C8="Jakarta",SUMIFS('Master Data HO & Site'!$AC$1:$AC$437,'Master Data HO & Site'!$F$1:$F$437,'Summary to Mgmt'!$D8,'Master Data HO & Site'!$H$1:$H$437,'Summary to Mgmt'!$E8,'Master Data HO & Site'!$Y$1:$Y$437,"Open",'Master Data HO & Site'!$N$1:$N$437,$H$2),SUMIFS('Master Data HO & Site'!$AC$1:$AC$437,'Master Data HO & Site'!$S$1:$S$437,'Summary to Mgmt'!$C8,'Master Data HO & Site'!$Y$1:$Y$437,"Open",'Master Data HO & Site'!$N$1:$N$437,$H$2)))) -> 0 | L8: =IF($H$2="All",IF(C8="Jakarta",SUMIFS('Master Data HO & Site'!$AD$1:$AD$437,'Master Data HO & Site'!$F$1:$F$437,'Summary to Mgmt'!$D8,'Master Data HO & Site'!$H$1:$H$437,'Summary to Mgmt'!$E8,'Master Data HO & Site'!$Y$1:$Y$437,"Open"),SUMIFS('Master Data HO & Site'!$AD$1:$AD$437,'Master Data HO & Site'!$S$1:$S$437,'Summary to Mgmt'!$C8,'Master Data HO & Site'!$Y$1:$Y$437,"Open")),IF($H$2="Urgent",IF(C8="Jakarta",SUMIFS('Master Data HO & Site'!$AD$1:$AD$437,'Master Data HO & Site'!$F$1:$F$437,'Summary to Mgmt'!$D8,'Master Data HO & Site'!$H$1:$H$437,'Summary to Mgmt'!$E8,'Master Data HO & Site'!$Y$1:$Y$437,"Open",'Master Data HO & Site'!$N$1:$N$437,$H$2),SUMIFS('Master Data HO & Site'!$AD$1:$AD$437,'Master Data HO & Site'!$S$1:$S$437,'Summary to Mgmt'!$C8,'Master Data HO & Site'!$Y$1:$Y$437,"Open",'Master Data HO & Site'!$N$1:$N$437,$H$2)),IF(C8="Jakarta",SUMIFS('Master Data HO & Site'!$AD$1:$AD$437,'Master Data HO & Site'!$F$1:$F$437,'Summary to Mgmt'!$D8,'Master Data HO & Site'!$H$1:$H$437,'Summary to Mgmt'!$E8,'Master Data HO & Site'!$Y$1:$Y$437,"Open",'Master Data HO & Site'!$N$1:$N$437,$H$2),SUMIFS('Master Data HO & Site'!$AD$1:$AD$437,'Master Data HO & Site'!$S$1:$S$437,'Summary to Mgmt'!$C8,'Master Data HO & Site'!$Y$1:$Y$437,"Open",'Master Data HO & Site'!$N$1:$N$437,$H$2)))) -> 0 | M8: =IF($H$2="All",IF(C8="Jakarta",SUMIFS('Master Data HO & Site'!$AE$1:$AE$437,'Master Data HO & Site'!$F$1:$F$437,'Summary to Mgmt'!$D8,'Master Data HO & Site'!$H$1:$H$437,'Summary to Mgmt'!$E8,'Master Data HO & Site'!$Y$1:$Y$437,"Open"),SUMIFS('Master Data HO & Site'!$AE$1:$AE$437,'Master Data HO & Site'!$S$1:$S$437,'Summary to Mgmt'!$C8,'Master Data HO & Site'!$Y$1:$Y$437,"Open")),IF($H$2="Urgent",IF(C8="Jakarta",SUMIFS('Master Data HO & Site'!$AE$1:$AE$437,'Master Data HO & Site'!$F$1:$F$437,'Summary to Mgmt'!$D8,'Master Data HO & Site'!$H$1:$H$437,'Summary to Mgmt'!$E8,'Master Data HO & Site'!$Y$1:$Y$437,"Open",'Master Data HO & Site'!$N$1:$N$437,$H$2),SUMIFS('Master Data HO & Site'!$AE$1:$AE$437,'Master Data HO & Site'!$S$1:$S$437,'Summary to Mgmt'!$C8,'Master Data HO & Site'!$Y$1:$Y$437,"Open",'Master Data HO & Site'!$N$1:$N$437,$H$2)),IF(C8="Jakarta",SUMIFS('Master Data HO & Site'!$AE$1:$AE$437,'Master Data HO & Site'!$F$1:$F$437,'Summary to Mgmt'!$D8,'Master Data HO & Site'!$H$1:$H$437,'Summary to Mgmt'!$E8,'Master Data HO & Site'!$Y$1:$Y$437,"Open",'Master Data HO & Site'!$N$1:$N$437,$H$2),SUMIFS('Master Data HO & Site'!$AE$1:$AE$437,'Master Data HO & Site'!$S$1:$S$437,'Summary to Mgmt'!$C8,'Master Data HO & Site'!$Y$1:$Y$437,"Open",'Master Data HO & Site'!$N$1:$N$437,$H$2)))) -> 0 | N8: =IF($H$2="All",IF(C8="Jakarta",SUMIFS('Master Data HO & Site'!$AF$1:$AF$437,'Master Data HO & Site'!$F$1:$F$437,'Summary to Mgmt'!$D8,'Master Data HO & Site'!$H$1:$H$437,'Summary to Mgmt'!$E8,'Master Data HO & Site'!$Y$1:$Y$437,"Open"),SUMIFS('Master Data HO & Site'!$AF$1:$AF$437,'Master Data HO & Site'!$S$1:$S$437,'Summary to Mgmt'!$C8,'Master Data HO & Site'!$Y$1:$Y$437,"Open")),IF($H$2="Urgent",IF(C8="Jakarta",SUMIFS('Master Data HO & Site'!$AF$1:$AF$437,'Master Data HO & Site'!$F$1:$F$437,'Summary to Mgmt'!$D8,'Master Data HO & Site'!$H$1:$H$437,'Summary to Mgmt'!$E8,'Master Data HO & Site'!$Y$1:$Y$437,"Open",'Master Data HO & Site'!$N$1:$N$437,$H$2),SUMIFS('Master Data HO & Site'!$AF$1:$AF$437,'Master Data HO & Site'!$S$1:$S$437,'Summary to Mgmt'!$C8,'Master Data HO & Site'!$Y$1:$Y$437,"Open",'Master Data HO & Site'!$N$1:$N$437,$H$2)),IF(C8="Jakarta",SUMIFS('Master Data HO & Site'!$AF$1:$AF$437,'Master Data HO & Site'!$F$1:$F$437,'Summary to Mgmt'!$D8,'Master Data HO & Site'!$H$1:$H$437,'Summary to Mgmt'!$E8,'Master Data HO & Site'!$Y$1:$Y$437,"Open",'Master Data HO & Site'!$N$1:$N$437,$H$2),SUMIFS('Master Data HO & Site'!$AF$1:$AF$437,'Master Data HO & Site'!$S$1:$S$437,'Summary to Mgmt'!$C8,'Master Data HO & Site'!$Y$1:$Y$437,"Open",'Master Data HO & Site'!$N$1:$N$437,$H$2)))) -> 0 | O8: =IF($H$2="All",IF(C8="Jakarta",SUMIFS('Master Data HO & Site'!$AG$1:$AG$437,'Master Data HO & Site'!$S$1:$S$437,'Summary to Mgmt'!$C8,'Master Data HO & Site'!$F$1:$F$437,'Summary to Mgmt'!$D8,'Master Data HO & Site'!$H$1:$H$437,'Summary to Mgmt'!$E8,'Master Data HO & Site'!$Y$1:$Y$437,"Open"),SUMIFS('Master Data HO & Site'!$AG$1:$AG$437,'Master Data HO & Site'!$S$1:$S$437,'Summary to Mgmt'!$C8,'Master Data HO & Site'!$Y$1:$Y$437,"Open")),IF($H$2="Urgent",IF(C8="Jakarta",SUMIFS('Master Data HO & Site'!$AG$1:$AG$437,'Master Data HO & Site'!$F$1:$F$437,'Summary to Mgmt'!$D8,'Master Data HO & Site'!$H$1:$H$437,'Summary to Mgmt'!$E8,'Master Data HO & Site'!$Y$1:$Y$437,"Open",'Master Data HO & Site'!$N$1:$N$437,$H$2),SUMIFS('Master Data HO & Site'!$AG$1:$AG$437,'Master Data HO & Site'!$S$1:$S$437,'Summary to Mgmt'!$C8,'Master Data HO & Site'!$Y$1:$Y$437,"Open",'Master Data HO & Site'!$N$1:$N$437,$H$2)),IF(C8="Jakarta",SUMIFS('Master Data HO & Site'!$AG$1:$AG$437,'Master Data HO & Site'!$F$1:$F$437,'Summary to Mgmt'!$D8,'Master Data HO & Site'!$H$1:$H$437,'Summary to Mgmt'!$E8,'Master Data HO & Site'!$Y$1:$Y$437,"Open",'Master Data HO & Site'!$N$1:$N$437,$H$2),SUMIFS('Master Data HO & Site'!$AG$1:$AG$437,'Master Data HO & Site'!$S$1:$S$437,'Summary to Mgmt'!$C8,'Master Data HO & Site'!$Y$1:$Y$437,"Open",'Master Data HO & Site'!$N$1:$N$437,$H$2)))) -> 1 | P8: =IF($H$2="All",IF(C8="Jakarta",SUMIFS('Master Data HO & Site'!$AH$1:$AH$437,'Master Data HO & Site'!$F$1:$F$437,'Summary to Mgmt'!$D8,'Master Data HO & Site'!$H$1:$H$437,'Summary to Mgmt'!$E8,'Master Data HO & Site'!$Y$1:$Y$437,"Open"),SUMIFS('Master Data HO & Site'!$AH$1:$AH$437,'Master Data HO & Site'!$S$1:$S$437,'Summary to Mgmt'!$C8,'Master Data HO & Site'!$Y$1:$Y$437,"Open")),IF($H$2="Urgent",IF(C8="Jakarta",SUMIFS('Master Data HO & Site'!$AH$1:$AH$437,'Master Data HO & Site'!$F$1:$F$437,'Summary to Mgmt'!$D8,'Master Data HO & Site'!$H$1:$H$437,'Summary to Mgmt'!$E8,'Master Data HO & Site'!$Y$1:$Y$437,"Open",'Master Data HO & Site'!$N$1:$N$437,$H$2),SUMIFS('Master Data HO & Site'!$AH$1:$AH$437,'Master Data HO & Site'!$S$1:$S$437,'Summary to Mgmt'!$C8,'Master Data HO & Site'!$Y$1:$Y$437,"Open",'Master Data HO & Site'!$N$1:$N$437,$H$2)),IF(C8="Jakarta",SUMIFS('Master Data HO & Site'!$AH$1:$AH$437,'Master Data HO & Site'!$F$1:$F$437,'Summary to Mgmt'!$D8,'Master Data HO & Site'!$H$1:$H$437,'Summary to Mgmt'!$E8,'Master Data HO & Site'!$Y$1:$Y$437,"Open",'Master Data HO & Site'!$N$1:$N$437,$H$2),SUMIFS('Master Data HO & Site'!$AH$1:$AH$437,'Master Data HO & Site'!$S$1:$S$437,'Summary to Mgmt'!$C8,'Master Data HO & Site'!$Y$1:$Y$437,"Open",'Master Data HO & Site'!$N$1:$N$437,$H$2)))) -> 0 | Q8: =IF($H$2="All",IF(C8="Jakarta",SUMIFS('Master Data HO & Site'!$AI$1:$AI$437,'Master Data HO & Site'!$F$1:$F$437,'Summary to Mgmt'!$D8,'Master Data HO & Site'!$H$1:$H$437,'Summary to Mgmt'!$E8,'Master Data HO & Site'!$Y$1:$Y$437,"Open"),SUMIFS('Master Data HO & Site'!$AI$1:$AI$437,'Master Data HO & Site'!$S$1:$S$437,'Summary to Mgmt'!$C8,'Master Data HO & Site'!$Y$1:$Y$437,"Open")),IF($H$2="Urgent",IF(C8="Jakarta",SUMIFS('Master Data HO & Site'!$AI$1:$AI$437,'Master Data HO & Site'!$F$1:$F$437,'Summary to Mgmt'!$D8,'Master Data HO & Site'!$H$1:$H$437,'Summary to Mgmt'!$E8,'Master Data HO & Site'!$Y$1:$Y$437,"Open",'Master Data HO & Site'!$N$1:$N$437,$H$2),SUMIFS('Master Data HO & Site'!$AI$1:$AI$437,'Master Data HO & Site'!$S$1:$S$437,'Summary to Mgmt'!$C8,'Master Data HO & Site'!$Y$1:$Y$437,"Open",'Master Data HO & Site'!$N$1:$N$437,$H$2)),IF(C8="Jakarta",SUMIFS('Master Data HO & Site'!$AI$1:$AI$437,'Master Data HO & Site'!$F$1:$F$437,'Summary to Mgmt'!$D8,'Master Data HO & Site'!$H$1:$H$437,'Summary to Mgmt'!$E8,'Master Data HO & Site'!$Y$1:$Y$437,"Open",'Master Data HO & Site'!$N$1:$N$437,$H$2),SUMIFS('Master Data HO & Site'!$AI$1:$AI$437,'Master Data HO & Site'!$S$1:$S$437,'Summary to Mgmt'!$C8,'Master Data HO & Site'!$Y$1:$Y$437,"Open",'Master Data HO & Site'!$N$1:$N$437,$H$2)))) -> 0 | R8: =IF($H$2="All",IF(C8="Jakarta",SUMIFS('Master Data HO & Site'!$AJ$1:$AJ$437,'Master Data HO & Site'!$F$1:$F$437,'Summary to Mgmt'!$D8,'Master Data HO & Site'!$H$1:$H$437,'Summary to Mgmt'!$E8,'Master Data HO & Site'!$Y$1:$Y$437,"Open"),SUMIFS('Master Data HO & Site'!$AJ$1:$AJ$437,'Master Data HO & Site'!$S$1:$S$437,'Summary to Mgmt'!$C8,'Master Data HO & Site'!$Y$1:$Y$437,"Open")),IF($H$2="Urgent",IF(C8="Jakarta",SUMIFS('Master Data HO & Site'!$AJ$1:$AJ$437,'Master Data HO & Site'!$F$1:$F$437,'Summary to Mgmt'!$D8,'Master Data HO & Site'!$H$1:$H$437,'Summary to Mgmt'!$E8,'Master Data HO & Site'!$Y$1:$Y$437,"Open",'Master Data HO & Site'!$N$1:$N$437,$H$2),SUMIFS('Master Data HO & Site'!$AJ$1:$AJ$437,'Master Data HO & Site'!$S$1:$S$437,'Summary to Mgmt'!$C8,'Master Data HO & Site'!$Y$1:$Y$437,"Open",'Master Data HO & Site'!$N$1:$N$437,$H$2)),IF(C8="Jakarta",SUMIFS('Master Data HO & Site'!$AJ$1:$AJ$437,'Master Data HO & Site'!$F$1:$F$437,'Summary to Mgmt'!$D8,'Master Data HO & Site'!$H$1:$H$437,'Summary to Mgmt'!$E8,'Master Data HO & Site'!$Y$1:$Y$437,"Open",'Master Data HO & Site'!$N$1:$N$437,$H$2),SUMIFS('Master Data HO & Site'!$AJ$1:$AJ$437,'Master Data HO & Site'!$S$1:$S$437,'Summary to Mgmt'!$C8,'Master Data HO & Site'!$Y$1:$Y$437,"Open",'Master Data HO & Site'!$N$1:$N$437,$H$2)))) -> 0 | S8: =IF($H$2="All",IF(C8="Jakarta",SUMIFS('Master Data HO & Site'!$AK$1:$AK$437,'Master Data HO & Site'!$F$1:$F$437,'Summary to Mgmt'!$D8,'Master Data HO & Site'!$H$1:$H$437,'Summary to Mgmt'!$E8,'Master Data HO & Site'!$Y$1:$Y$437,"Open"),SUMIFS('Master Data HO & Site'!$AK$1:$AK$437,'Master Data HO & Site'!$S$1:$S$437,'Summary to Mgmt'!$C8,'Master Data HO & Site'!$Y$1:$Y$437,"Open")),IF($H$2="Urgent",IF(C8="Jakarta",SUMIFS('Master Data HO & Site'!$AK$1:$AK$437,'Master Data HO & Site'!$F$1:$F$437,'Summary to Mgmt'!$D8,'Master Data HO & Site'!$H$1:$H$437,'Summary to Mgmt'!$E8,'Master Data HO & Site'!$Y$1:$Y$437,"Open",'Master Data HO & Site'!$N$1:$N$437,$H$2),SUMIFS('Master Data HO & Site'!$AK$1:$AK$437,'Master Data HO & Site'!$S$1:$S$437,'Summary to Mgmt'!$C8,'Master Data HO & Site'!$Y$1:$Y$437,"Open",'Master Data HO & Site'!$N$1:$N$437,$H$2)),IF(C8="Jakarta",SUMIFS('Master Data HO & Site'!$AK$1:$AK$437,'Master Data HO & Site'!$F$1:$F$437,'Summary to Mgmt'!$D8,'Master Data HO & Site'!$H$1:$H$437,'Summary to Mgmt'!$E8,'Master Data HO & Site'!$Y$1:$Y$437,"Open",'Master Data HO & Site'!$N$1:$N$437,$H$2),SUMIFS('Master Data HO & Site'!$AK$1:$AK$437,'Master Data HO & Site'!$S$1:$S$437,'Summary to Mgmt'!$C8,'Master Data HO & Site'!$Y$1:$Y$437,"Open",'Master Data HO & Site'!$N$1:$N$437,$H$2)))) -> 0 | T8: =IF($H$2="All",IF(C8="Jakarta",SUMIFS('Master Data HO & Site'!$AL$1:$AL$437,'Master Data HO & Site'!$F$1:$F$437,'Summary to Mgmt'!$D8,'Master Data HO & Site'!$H$1:$H$437,'Summary to Mgmt'!$E8,'Master Data HO & Site'!$Y$1:$Y$437,"Open"),SUMIFS('Master Data HO & Site'!$AL$1:$AL$437,'Master Data HO & Site'!$S$1:$S$437,'Summary to Mgmt'!$C8,'Master Data HO & Site'!$Y$1:$Y$437,"Open")),IF($H$2="Urgent",IF(C8="Jakarta",SUMIFS('Master Data HO & Site'!$AL$1:$AL$437,'Master Data HO & Site'!$F$1:$F$437,'Summary to Mgmt'!$D8,'Master Data HO & Site'!$H$1:$H$437,'Summary to Mgmt'!$E8,'Master Data HO & Site'!$Y$1:$Y$437,"Open",'Master Data HO & Site'!$N$1:$N$437,$H$2),SUMIFS('Master Data HO & Site'!$AL$1:$AL$437,'Master Data HO & Site'!$S$1:$S$437,'Summary to Mgmt'!$C8,'Master Data HO & Site'!$Y$1:$Y$437,"Open",'Master Data HO & Site'!$N$1:$N$437,$H$2)),IF(C8="Jakarta",SUMIFS('Master Data HO & Site'!$AL$1:$AL$437,'Master Data HO & Site'!$F$1:$F$437,'Summary to Mgmt'!$D8,'Master Data HO & Site'!$H$1:$H$437,'Summary to Mgmt'!$E8,'Master Data HO & Site'!$Y$1:$Y$437,"Open",'Master Data HO & Site'!$N$1:$N$437,$H$2),SUMIFS('Master Data HO & Site'!$AL$1:$AL$437,'Master Data HO & Site'!$S$1:$S$437,'Summary to Mgmt'!$C8,'Master Data HO & Site'!$Y$1:$Y$437,"Open",'Master Data HO & Site'!$N$1:$N$437,$H$2)))) -> 0 | U8: =IF($H$2="All",IF(C8="Jakarta",SUMIFS('Master Data HO & Site'!$AM$1:$AM$437,'Master Data HO & Site'!$S$1:$S$437,'Summary to Mgmt'!$C8,'Master Data HO & Site'!$F$1:$F$437,'Summary to Mgmt'!$D8,'Master Data HO & Site'!$H$1:$H$437,'Summary to Mgmt'!$E8,'Master Data HO & Site'!$Y$1:$Y$437,"Open"),SUMIFS('Master Data HO & Site'!$AM$1:$AM$437,'Master Data HO & Site'!$S$1:$S$437,'Summary to Mgmt'!$C8,'Master Data HO & Site'!$Y$1:$Y$437,"Open")),IF($H$2="Urgent",IF(C8="Jakarta",SUMIFS('Master Data HO & Site'!$AM$1:$AM$437,'Master Data HO & Site'!$F$1:$F$437,'Summary to Mgmt'!$D8,'Master Data HO & Site'!$H$1:$H$437,'Summary to Mgmt'!$E8,'Master Data HO & Site'!$Y$1:$Y$437,"Open",'Master Data HO & Site'!$N$1:$N$437,$H$2),SUMIFS('Master Data HO & Site'!$AM$1:$AM$437,'Master Data HO & Site'!$S$1:$S$437,'Summary to Mgmt'!$C8,'Master Data HO & Site'!$Y$1:$Y$437,"Open",'Master Data HO & Site'!$N$1:$N$437,$H$2)),IF(C8="Jakarta",SUMIFS('Master Data HO & Site'!$AM$1:$AM$437,'Master Data HO & Site'!$F$1:$F$437,'Summary to Mgmt'!$D8,'Master Data HO & Site'!$H$1:$H$437,'Summary to Mgmt'!$E8,'Master Data HO & Site'!$Y$1:$Y$437,"Open",'Master Data HO & Site'!$N$1:$N$437,$H$2),SUMIFS('Master Data HO & Site'!$AM$1:$AM$437,'Master Data HO & Site'!$S$1:$S$437,'Summary to Mgmt'!$C8,'Master Data HO & Site'!$Y$1:$Y$437,"Open",'Master Data HO & Site'!$N$1:$N$437,$H$2)))) -> 0 | V8: =IF($H$2="All",IF(C8="Jakarta",SUMIFS('Master Data HO & Site'!$AN$1:$AN$437,'Master Data HO & Site'!$F$1:$F$437,'Summary to Mgmt'!$D8,'Master Data HO & Site'!$H$1:$H$437,'Summary to Mgmt'!$E8,'Master Data HO & Site'!$Y$1:$Y$437,"Open"),SUMIFS('Master Data HO & Site'!$AN$1:$AN$437,'Master Data HO & Site'!$S$1:$S$437,'Summary to Mgmt'!$C8,'Master Data HO & Site'!$Y$1:$Y$437,"Open")),IF($H$2="Urgent",IF(C8="Jakarta",SUMIFS('Master Data HO & Site'!$AN$1:$AN$437,'Master Data HO & Site'!$F$1:$F$437,'Summary to Mgmt'!$D8,'Master Data HO & Site'!$H$1:$H$437,'Summary to Mgmt'!$E8,'Master Data HO & Site'!$Y$1:$Y$437,"Open",'Master Data HO & Site'!$N$1:$N$437,$H$2),SUMIFS('Master Data HO & Site'!$AN$1:$AN$437,'Master Data HO & Site'!$S$1:$S$437,'Summary to Mgmt'!$C8,'Master Data HO & Site'!$Y$1:$Y$437,"Open",'Master Data HO & Site'!$N$1:$N$437,$H$2)),IF(C8="Jakarta",SUMIFS('Master Data HO & Site'!$AN$1:$AN$437,'Master Data HO & Site'!$F$1:$F$437,'Summary to Mgmt'!$D8,'Master Data HO & Site'!$H$1:$H$437,'Summary to Mgmt'!$E8,'Master Data HO & Site'!$Y$1:$Y$437,"Open",'Master Data HO & Site'!$N$1:$N$437,$H$2),SUMIFS('Master Data HO & Site'!$AN$1:$AN$437,'Master Data HO & Site'!$S$1:$S$437,'Summary to Mgmt'!$C8,'Master Data HO & Site'!$Y$1:$Y$437,"Open",'Master Data HO & Site'!$N$1:$N$437,$H$2)))) -> 0 | W8: =IF($H$2="All",IF(C8="Jakarta",SUMIFS('Master Data HO & Site'!$AO$1:$AO$437,'Master Data HO & Site'!$F$1:$F$437,'Summary to Mgmt'!$D8,'Master Data HO & Site'!$H$1:$H$437,'Summary to Mgmt'!$E8,'Master Data HO & Site'!$Y$1:$Y$437,"Open"),SUMIFS('Master Data HO & Site'!$AO$1:$AO$437,'Master Data HO & Site'!$S$1:$S$437,'Summary to Mgmt'!$C8,'Master Data HO & Site'!$Y$1:$Y$437,"Open")),IF($H$2="Urgent",IF(C8="Jakarta",SUMIFS('Master Data HO & Site'!$AO$1:$AO$437,'Master Data HO & Site'!$F$1:$F$437,'Summary to Mgmt'!$D8,'Master Data HO & Site'!$H$1:$H$437,'Summary to Mgmt'!$E8,'Master Data HO & Site'!$Y$1:$Y$437,"Open",'Master Data HO & Site'!$N$1:$N$437,$H$2),SUMIFS('Master Data HO & Site'!$AO$1:$AO$437,'Master Data HO & Site'!$S$1:$S$437,'Summary to Mgmt'!$C8,'Master Data HO & Site'!$Y$1:$Y$437,"Open",'Master Data HO & Site'!$N$1:$N$437,$H$2)),IF(C8="Jakarta",SUMIFS('Master Data HO & Site'!$AO$1:$AO$437,'Master Data HO & Site'!$F$1:$F$437,'Summary to Mgmt'!$D8,'Master Data HO & Site'!$H$1:$H$437,'Summary to Mgmt'!$E8,'Master Data HO & Site'!$Y$1:$Y$437,"Open",'Master Data HO & Site'!$N$1:$N$437,$H$2),SUMIFS('Master Data HO & Site'!$AO$1:$AO$437,'Master Data HO & Site'!$S$1:$S$437,'Summary to Mgmt'!$C8,'Master Data HO & Site'!$Y$1:$Y$437,"Open",'Master Data HO & Site'!$N$1:$N$437,$H$2)))) -> 0 | X8: =IF($H$2="All",IF(C8="Jakarta",SUMIFS('Master Data HO & Site'!$AP$1:$AP$437,'Master Data HO & Site'!$F$1:$F$437,'Summary to Mgmt'!$D8,'Master Data HO & Site'!$H$1:$H$437,'Summary to Mgmt'!$E8,'Master Data HO & Site'!$Y$1:$Y$437,"Open"),SUMIFS('Master Data HO & Site'!$AP$1:$AP$437,'Master Data HO & Site'!$S$1:$S$437,'Summary to Mgmt'!$C8,'Master Data HO & Site'!$Y$1:$Y$437,"Open")),IF($H$2="Urgent",IF(C8="Jakarta",SUMIFS('Master Data HO & Site'!$AP$1:$AP$437,'Master Data HO & Site'!$F$1:$F$437,'Summary to Mgmt'!$D8,'Master Data HO & Site'!$H$1:$H$437,'Summary to Mgmt'!$E8,'Master Data HO & Site'!$Y$1:$Y$437,"Open",'Master Data HO & Site'!$N$1:$N$437,$H$2),SUMIFS('Master Data HO & Site'!$AP$1:$AP$437,'Master Data HO & Site'!$S$1:$S$437,'Summary to Mgmt'!$C8,'Master Data HO & Site'!$Y$1:$Y$437,"Open",'Master Data HO & Site'!$N$1:$N$437,$H$2)),IF(C8="Jakarta",SUMIFS('Master Data HO & Site'!$AP$1:$AP$437,'Master Data HO & Site'!$F$1:$F$437,'Summary to Mgmt'!$D8,'Master Data HO & Site'!$H$1:$H$437,'Summary to Mgmt'!$E8,'Master Data HO & Site'!$Y$1:$Y$437,"Open",'Master Data HO & Site'!$N$1:$N$437,$H$2),SUMIFS('Master Data HO & Site'!$AP$1:$AP$437,'Master Data HO & Site'!$S$1:$S$437,'Summary to Mgmt'!$C8,'Master Data HO & Site'!$Y$1:$Y$437,"Open",'Master Data HO & Site'!$N$1:$N$437,$H$2)))) -> 0 | Y8: =IF($H$2="All",IF(C8="Jakarta",SUMIFS('Master Data HO & Site'!$AQ$1:$AQ$437,'Master Data HO & Site'!$F$1:$F$437,'Summary to Mgmt'!$D8,'Master Data HO & Site'!$H$1:$H$437,'Summary to Mgmt'!$E8,'Master Data HO & Site'!$Y$1:$Y$437,"Open"),SUMIFS('Master Data HO & Site'!$AQ$1:$AQ$437,'Master Data HO & Site'!$S$1:$S$437,'Summary to Mgmt'!$C8,'Master Data HO & Site'!$Y$1:$Y$437,"Open")),IF($H$2="Urgent",IF(C8="Jakarta",SUMIFS('Master Data HO & Site'!$AQ$1:$AQ$437,'Master Data HO & Site'!$F$1:$F$437,'Summary to Mgmt'!$D8,'Master Data HO & Site'!$H$1:$H$437,'Summary to Mgmt'!$E8,'Master Data HO & Site'!$Y$1:$Y$437,"Open",'Master Data HO & Site'!$N$1:$N$437,$H$2),SUMIFS('Master Data HO & Site'!$AQ$1:$AQ$437,'Master Data HO & Site'!$S$1:$S$437,'Summary to Mgmt'!$C8,'Master Data HO & Site'!$Y$1:$Y$437,"Open",'Master Data HO & Site'!$N$1:$N$437,$H$2)),IF(C8="Jakarta",SUMIFS('Master Data HO & Site'!$AQ$1:$AQ$437,'Master Data HO & Site'!$F$1:$F$437,'Summary to Mgmt'!$D8,'Master Data HO & Site'!$H$1:$H$437,'Summary to Mgmt'!$E8,'Master Data HO & Site'!$Y$1:$Y$437,"Open",'Master Data HO & Site'!$N$1:$N$437,$H$2),SUMIFS('Master Data HO & Site'!$AQ$1:$AQ$437,'Master Data HO & Site'!$S$1:$S$437,'Summary to Mgmt'!$C8,'Master Data HO & Site'!$Y$1:$Y$437,"Open",'Master Data HO & Site'!$N$1:$N$437,$H$2)))) -> 0 | Z8: =IF($H$2="All",IF(C8="Jakarta",SUMIFS('Master Data HO & Site'!$AR$1:$AR$437,'Master Data HO & Site'!$F$1:$F$437,'Summary to Mgmt'!$D8,'Master Data HO & Site'!$H$1:$H$437,'Summary to Mgmt'!$E8,'Master Data HO & Site'!$Y$1:$Y$437,"Open"),SUMIFS('Master Data HO & Site'!$AR$1:$AR$437,'Master Data HO & Site'!$S$1:$S$437,'Summary to Mgmt'!$C8,'Master Data HO & Site'!$Y$1:$Y$437,"Open")),IF($H$2="Urgent",IF(C8="Jakarta",SUMIFS('Master Data HO & Site'!$AR$1:$AR$437,'Master Data HO & Site'!$F$1:$F$437,'Summary to Mgmt'!$D8,'Master Data HO & Site'!$H$1:$H$437,'Summary to Mgmt'!$E8,'Master Data HO & Site'!$Y$1:$Y$437,"Open",'Master Data HO & Site'!$N$1:$N$437,$H$2),SUMIFS('Master Data HO & Site'!$AR$1:$AR$437,'Master Data HO & Site'!$S$1:$S$437,'Summary to Mgmt'!$C8,'Master Data HO & Site'!$Y$1:$Y$437,"Open",'Master Data HO & Site'!$N$1:$N$437,$H$2)),IF(C8="Jakarta",SUMIFS('Master Data HO & Site'!$AR$1:$AR$437,'Master Data HO & Site'!$F$1:$F$437,'Summary to Mgmt'!$D8,'Master Data HO & Site'!$H$1:$H$437,'Summary to Mgmt'!$E8,'Master Data HO & Site'!$Y$1:$Y$437,"Open",'Master Data HO & Site'!$N$1:$N$437,$H$2),SUMIFS('Master Data HO & Site'!$AR$1:$AR$437,'Master Data HO & Site'!$S$1:$S$437,'Summary to Mgmt'!$C8,'Master Data HO & Site'!$Y$1:$Y$437,"Open",'Master Data HO & Site'!$N$1:$N$437,$H$2)))) -> 0 | AA8: =IF($H$2="All",IF(C8="Jakarta",SUMIFS('Master Data HO & Site'!$AS$1:$AS$437,'Master Data HO & Site'!$S$1:$S$437,'Summary to Mgmt'!$C8,'Master Data HO & Site'!$F$1:$F$437,'Summary to Mgmt'!$D8,'Master Data HO & Site'!$H$1:$H$437,'Summary to Mgmt'!$E8,'Master Data HO & Site'!$Y$1:$Y$437,"Open"),SUMIFS('Master Data HO & Site'!$AS$1:$AS$437,'Master Data HO & Site'!$S$1:$S$437,'Summary to Mgmt'!$C8,'Master Data HO & Site'!$Y$1:$Y$437,"Open")),IF($H$2="Urgent",IF(C8="Jakarta",SUMIFS('Master Data HO & Site'!$AS$1:$AS$437,'Master Data HO & Site'!$F$1:$F$437,'Summary to Mgmt'!$D8,'Master Data HO & Site'!$H$1:$H$437,'Summary to Mgmt'!$E8,'Master Data HO & Site'!$Y$1:$Y$437,"Open",'Master Data HO & Site'!$N$1:$N$437,$H$2),SUMIFS('Master Data HO & Site'!$AS$1:$AS$437,'Master Data HO & Site'!$S$1:$S$437,'Summary to Mgmt'!$C8,'Master Data HO & Site'!$Y$1:$Y$437,"Open",'Master Data HO & Site'!$N$1:$N$437,$H$2)),IF(C8="Jakarta",SUMIFS('Master Data HO & Site'!$AS$1:$AS$437,'Master Data HO & Site'!$F$1:$F$437,'Summary to Mgmt'!$D8,'Master Data HO & Site'!$H$1:$H$437,'Summary to Mgmt'!$E8,'Master Data HO & Site'!$Y$1:$Y$437,"Open",'Master Data HO & Site'!$N$1:$N$437,$H$2),SUMIFS('Master Data HO & Site'!$AS$1:$AS$437,'Master Data HO & Site'!$S$1:$S$437,'Summary to Mgmt'!$C8,'Master Data HO & Site'!$Y$1:$Y$437,"Open",'Master Data HO & Site'!$N$1:$N$437,$H$2)))) -> 0 | AB8: =IF($H$2="All",IF(C8="Jakarta",SUMIFS('Master Data HO & Site'!$AT$1:$AT$437,'Master Data HO & Site'!$F$1:$F$437,'Summary to Mgmt'!$D8,'Master Data HO & Site'!$H$1:$H$437,'Summary to Mgmt'!$E8,'Master Data HO & Site'!$Y$1:$Y$437,"Open"),SUMIFS('Master Data HO & Site'!$AT$1:$AT$437,'Master Data HO & Site'!$S$1:$S$437,'Summary to Mgmt'!$C8,'Master Data HO & Site'!$Y$1:$Y$437,"Open")),IF($H$2="Urgent",IF(C8="Jakarta",SUMIFS('Master Data HO & Site'!$AT$1:$AT$437,'Master Data HO & Site'!$F$1:$F$437,'Summary to Mgmt'!$D8,'Master Data HO & Site'!$H$1:$H$437,'Summary to Mgmt'!$E8,'Master Data HO & Site'!$Y$1:$Y$437,"Open",'Master Data HO & Site'!$N$1:$N$437,$H$2),SUMIFS('Master Data HO & Site'!$AT$1:$AT$437,'Master Data HO & Site'!$S$1:$S$437,'Summary to Mgmt'!$C8,'Master Data HO & Site'!$Y$1:$Y$437,"Open",'Master Data HO & Site'!$N$1:$N$437,$H$2)),IF(C8="Jakarta",SUMIFS('Master Data HO & Site'!$AT$1:$AT$437,'Master Data HO & Site'!$F$1:$F$437,'Summary to Mgmt'!$D8,'Master Data HO & Site'!$H$1:$H$437,'Summary to Mgmt'!$E8,'Master Data HO & Site'!$Y$1:$Y$437,"Open",'Master Data HO & Site'!$N$1:$N$437,$H$2),SUMIFS('Master Data HO & Site'!$AT$1:$AT$437,'Master Data HO & Site'!$S$1:$S$437,'Summary to Mgmt'!$C8,'Master Data HO & Site'!$Y$1:$Y$437,"Open",'Master Data HO & Site'!$N$1:$N$437,$H$2)))) -> 0 | AC8: =IF($H$2="All",IF(C8="Jakarta",SUMIFS('Master Data HO & Site'!$AU$1:$AU$437,'Master Data HO & Site'!$F$1:$F$437,'Summary to Mgmt'!$D8,'Master Data HO & Site'!$H$1:$H$437,'Summary to Mgmt'!$E8,'Master Data HO & Site'!$Y$1:$Y$437,"Open"),SUMIFS('Master Data HO & Site'!$AU$1:$AU$437,'Master Data HO & Site'!$S$1:$S$437,'Summary to Mgmt'!$C8,'Master Data HO & Site'!$Y$1:$Y$437,"Open")),IF($H$2="Urgent",IF(C8="Jakarta",SUMIFS('Master Data HO & Site'!$AU$1:$AU$437,'Master Data HO & Site'!$F$1:$F$437,'Summary to Mgmt'!$D8,'Master Data HO & Site'!$H$1:$H$437,'Summary to Mgmt'!$E8,'Master Data HO & Site'!$Y$1:$Y$437,"Open",'Master Data HO & Site'!$N$1:$N$437,$H$2),SUMIFS('Master Data HO & Site'!$AU$1:$AU$437,'Master Data HO & Site'!$S$1:$S$437,'Summary to Mgmt'!$C8,'Master Data HO & Site'!$Y$1:$Y$437,"Open",'Master Data HO & Site'!$N$1:$N$437,$H$2)),IF(C8="Jakarta",SUMIFS('Master Data HO & Site'!$AU$1:$AU$437,'Master Data HO & Site'!$F$1:$F$437,'Summary to Mgmt'!$D8,'Master Data HO & Site'!$H$1:$H$437,'Summary to Mgmt'!$E8,'Master Data HO & Site'!$Y$1:$Y$437,"Open",'Master Data HO & Site'!$N$1:$N$437,$H$2),SUMIFS('Master Data HO & Site'!$AU$1:$AU$437,'Master Data HO & Site'!$S$1:$S$437,'Summary to Mgmt'!$C8,'Master Data HO & Site'!$Y$1:$Y$437,"Open",'Master Data HO & Site'!$N$1:$N$437,$H$2)))) -> 0 | AD8: =IF($H$2="All",IF(C8="Jakarta",SUMIFS('Master Data HO & Site'!$AV$1:$AV$437,'Master Data HO & Site'!$F$1:$F$437,'Summary to Mgmt'!$D8,'Master Data HO & Site'!$H$1:$H$437,'Summary to Mgmt'!$E8,'Master Data HO & Site'!$Y$1:$Y$437,"Open"),SUMIFS('Master Data HO & Site'!$AV$1:$AV$437,'Master Data HO & Site'!$S$1:$S$437,'Summary to Mgmt'!$C8,'Master Data HO & Site'!$Y$1:$Y$437,"Open")),IF($H$2="Urgent",IF(C8="Jakarta",SUMIFS('Master Data HO & Site'!$AV$1:$AV$437,'Master Data HO & Site'!$F$1:$F$437,'Summary to Mgmt'!$D8,'Master Data HO & Site'!$H$1:$H$437,'Summary to Mgmt'!$E8,'Master Data HO & Site'!$Y$1:$Y$437,"Open",'Master Data HO & Site'!$N$1:$N$437,$H$2),SUMIFS('Master Data HO & Site'!$AV$1:$AV$437,'Master Data HO & Site'!$S$1:$S$437,'Summary to Mgmt'!$C8,'Master Data HO & Site'!$Y$1:$Y$437,"Open",'Master Data HO & Site'!$N$1:$N$437,$H$2)),IF(C8="Jakarta",SUMIFS('Master Data HO & Site'!$AV$1:$AV$437,'Master Data HO & Site'!$F$1:$F$437,'Summary to Mgmt'!$D8,'Master Data HO & Site'!$H$1:$H$437,'Summary to Mgmt'!$E8,'Master Data HO & Site'!$Y$1:$Y$437,"Open",'Master Data HO & Site'!$N$1:$N$437,$H$2),SUMIFS('Master Data HO & Site'!$AV$1:$AV$437,'Master Data HO & Site'!$S$1:$S$437,'Summary to Mgmt'!$C8,'Master Data HO & Site'!$Y$1:$Y$437,"Open",'Master Data HO & Site'!$N$1:$N$437,$H$2)))) -> 0 | AE8: =IF($H$2="All",IF(C8="Jakarta",SUMIFS('Master Data HO & Site'!$AW$1:$AW$437,'Master Data HO & Site'!$F$1:$F$437,'Summary to Mgmt'!$D8,'Master Data HO & Site'!$H$1:$H$437,'Summary to Mgmt'!$E8,'Master Data HO & Site'!$Y$1:$Y$437,"Open"),SUMIFS('Master Data HO & Site'!$AW$1:$AW$437,'Master Data HO & Site'!$S$1:$S$437,'Summary to Mgmt'!$C8,'Master Data HO & Site'!$Y$1:$Y$437,"Open")),IF($H$2="Urgent",IF(C8="Jakarta",SUMIFS('Master Data HO & Site'!$AW$1:$AW$437,'Master Data HO & Site'!$F$1:$F$437,'Summary to Mgmt'!$D8,'Master Data HO & Site'!$H$1:$H$437,'Summary to Mgmt'!$E8,'Master Data HO & Site'!$Y$1:$Y$437,"Open",'Master Data HO & Site'!$N$1:$N$437,$H$2),SUMIFS('Master Data HO & Site'!$AW$1:$AW$437,'Master Data HO & Site'!$S$1:$S$437,'Summary to Mgmt'!$C8,'Master Data HO & Site'!$Y$1:$Y$437,"Open",'Master Data HO & Site'!$N$1:$N$437,$H$2)),IF(C8="Jakarta",SUMIFS('Master Data HO & Site'!$AW$1:$AW$437,'Master Data HO & Site'!$F$1:$F$437,'Summary to Mgmt'!$D8,'Master Data HO & Site'!$H$1:$H$437,'Summary to Mgmt'!$E8,'Master Data HO & Site'!$Y$1:$Y$437,"Open",'Master Data HO & Site'!$N$1:$N$437,$H$2),SUMIFS('Master Data HO & Site'!$AW$1:$AW$437,'Master Data HO & Site'!$S$1:$S$437,'Summary to Mgmt'!$C8,'Master Data HO & Site'!$Y$1:$Y$437,"Open",'Master Data HO & Site'!$N$1:$N$437,$H$2)))) -> 0 | AF8: =IF($H$2="All",IF(C8="Jakarta",SUMIFS('Master Data HO & Site'!$AX$1:$AX$437,'Master Data HO & Site'!$F$1:$F$437,'Summary to Mgmt'!$D8,'Master Data HO & Site'!$H$1:$H$437,'Summary to Mgmt'!$E8,'Master Data HO & Site'!$Y$1:$Y$437,"Open"),SUMIFS('Master Data HO & Site'!$AX$1:$AX$437,'Master Data HO & Site'!$S$1:$S$437,'Summary to Mgmt'!$C8,'Master Data HO & Site'!$Y$1:$Y$437,"Open")),IF($H$2="Urgent",IF(C8="Jakarta",SUMIFS('Master Data HO & Site'!$AX$1:$AX$437,'Master Data HO & Site'!$F$1:$F$437,'Summary to Mgmt'!$D8,'Master Data HO & Site'!$H$1:$H$437,'Summary to Mgmt'!$E8,'Master Data HO & Site'!$Y$1:$Y$437,"Open",'Master Data HO & Site'!$N$1:$N$437,$H$2),SUMIFS('Master Data HO & Site'!$AX$1:$AX$437,'Master Data HO & Site'!$S$1:$S$437,'Summary to Mgmt'!$C8,'Master Data HO & Site'!$Y$1:$Y$437,"Open",'Master Data HO & Site'!$N$1:$N$437,$H$2)),IF(C8="Jakarta",SUMIFS('Master Data HO & Site'!$AX$1:$AX$437,'Master Data HO & Site'!$F$1:$F$437,'Summary to Mgmt'!$D8,'Master Data HO & Site'!$H$1:$H$437,'Summary to Mgmt'!$E8,'Master Data HO & Site'!$Y$1:$Y$437,"Open",'Master Data HO & Site'!$N$1:$N$437,$H$2),SUMIFS('Master Data HO & Site'!$AX$1:$AX$437,'Master Data HO & Site'!$S$1:$S$437,'Summary to Mgmt'!$C8,'Master Data HO & Site'!$Y$1:$Y$437,"Open",'Master Data HO & Site'!$N$1:$N$437,$H$2)))) -> 0 | AG8: =IF($H$2="All",IF(C8="Jakarta",SUMIFS('Master Data HO & Site'!$AY$1:$AY$437,'Master Data HO & Site'!$S$1:$S$437,'Summary to Mgmt'!$C8,'Master Data HO & Site'!$F$1:$F$437,'Summary to Mgmt'!$D8,'Master Data HO & Site'!$H$1:$H$437,'Summary to Mgmt'!$E8,'Master Data HO & Site'!$Y$1:$Y$437,"Open"),SUMIFS('Master Data HO & Site'!$AY$1:$AY$437,'Master Data HO & Site'!$S$1:$S$437,'Summary to Mgmt'!$C8,'Master Data HO & Site'!$Y$1:$Y$437,"Open")),IF($H$2="Urgent",IF(C8="Jakarta",SUMIFS('Master Data HO & Site'!$AY$1:$AY$437,'Master Data HO & Site'!$F$1:$F$437,'Summary to Mgmt'!$D8,'Master Data HO & Site'!$H$1:$H$437,'Summary to Mgmt'!$E8,'Master Data HO & Site'!$Y$1:$Y$437,"Open",'Master Data HO & Site'!$N$1:$N$437,$H$2),SUMIFS('Master Data HO & Site'!$AY$1:$AY$437,'Master Data HO & Site'!$S$1:$S$437,'Summary to Mgmt'!$C8,'Master Data HO & Site'!$Y$1:$Y$437,"Open",'Master Data HO & Site'!$N$1:$N$437,$H$2)),IF(C8="Jakarta",SUMIFS('Master Data HO & Site'!$AY$1:$AY$437,'Master Data HO & Site'!$F$1:$F$437,'Summary to Mgmt'!$D8,'Master Data HO & Site'!$H$1:$H$437,'Summary to Mgmt'!$E8,'Master Data HO & Site'!$Y$1:$Y$437,"Open",'Master Data HO & Site'!$N$1:$N$437,$H$2),SUMIFS('Master Data HO & Site'!$AY$1:$AY$437,'Master Data HO & Site'!$S$1:$S$437,'Summary to Mgmt'!$C8,'Master Data HO & Site'!$Y$1:$Y$437,"Open",'Master Data HO & Site'!$N$1:$N$437,$H$2)))) -> 0 | AH8: =IF($H$2="All",IF(C8="Jakarta",SUMIFS('Master Data HO & Site'!$AZ$1:$AZ$437,'Master Data HO & Site'!$F$1:$F$437,'Summary to Mgmt'!$D8,'Master Data HO & Site'!$H$1:$H$437,'Summary to Mgmt'!$E8,'Master Data HO & Site'!$Y$1:$Y$437,"Open"),SUMIFS('Master Data HO & Site'!$AZ$1:$AZ$437,'Master Data HO & Site'!$S$1:$S$437,'Summary to Mgmt'!$C8,'Master Data HO & Site'!$Y$1:$Y$437,"Open")),IF($H$2="Urgent",IF(C8="Jakarta",SUMIFS('Master Data HO & Site'!$AZ$1:$AZ$437,'Master Data HO & Site'!$F$1:$F$437,'Summary to Mgmt'!$D8,'Master Data HO & Site'!$H$1:$H$437,'Summary to Mgmt'!$E8,'Master Data HO & Site'!$Y$1:$Y$437,"Open",'Master Data HO & Site'!$N$1:$N$437,$H$2),SUMIFS('Master Data HO & Site'!$AZ$1:$AZ$437,'Master Data HO & Site'!$S$1:$S$437,'Summary to Mgmt'!$C8,'Master Data HO & Site'!$Y$1:$Y$437,"Open",'Master Data HO & Site'!$N$1:$N$437,$H$2)),IF(C8="Jakarta",SUMIFS('Master Data HO & Site'!$AZ$1:$AZ$437,'Master Data HO & Site'!$F$1:$F$437,'Summary to Mgmt'!$D8,'Master Data HO & Site'!$H$1:$H$437,'Summary to Mgmt'!$E8,'Master Data HO & Site'!$Y$1:$Y$437,"Open",'Master Data HO & Site'!$N$1:$N$437,$H$2),SUMIFS('Master Data HO & Site'!$AZ$1:$AZ$437,'Master Data HO & Site'!$S$1:$S$437,'Summary to Mgmt'!$C8,'Master Data HO & Site'!$Y$1:$Y$437,"Open",'Master Data HO & Site'!$N$1:$N$437,$H$2)))) -> 0 | AI8: =IF($H$2="All",IF(C8="Jakarta",SUMIFS('Master Data HO & Site'!$AZ$1:$AZ$437,'Master Data HO & Site'!$F$1:$F$437,'Summary to Mgmt'!$D8,'Master Data HO & Site'!$H$1:$H$437,'Summary to Mgmt'!$E8,'Master Data HO & Site'!$Y$1:$Y$437,"Open"),SUMIFS('Master Data HO & Site'!$AZ$1:$AZ$437,'Master Data HO & Site'!$S$1:$S$437,'Summary to Mgmt'!$C8,'Master Data HO & Site'!$Y$1:$Y$437,"Open")),IF($H$2="Urgent",IF(C8="Jakarta",SUMIFS('Master Data HO & Site'!$AZ$1:$AZ$437,'Master Data HO & Site'!$F$1:$F$437,'Summary to Mgmt'!$D8,'Master Data HO & Site'!$H$1:$H$437,'Summary to Mgmt'!$E8,'Master Data HO & Site'!$Y$1:$Y$437,"Open",'Master Data HO & Site'!$N$1:$N$437,$H$2),SUMIFS('Master Data HO & Site'!$AZ$1:$AZ$437,'Master Data HO & Site'!$S$1:$S$437,'Summary to Mgmt'!$C8,'Master Data HO & Site'!$Y$1:$Y$437,"Open",'Master Data HO & Site'!$N$1:$N$437,$H$2)),IF(C8="Jakarta",SUMIFS('Master Data HO & Site'!$AZ$1:$AZ$437,'Master Data HO & Site'!$F$1:$F$437,'Summary to Mgmt'!$D8,'Master Data HO & Site'!$H$1:$H$437,'Summary to Mgmt'!$E8,'Master Data HO & Site'!$Y$1:$Y$437,"Open",'Master Data HO & Site'!$N$1:$N$437,$H$2),SUMIFS('Master Data HO & Site'!$AZ$1:$AZ$437,'Master Data HO & Site'!$S$1:$S$437,'Summary to Mgmt'!$C8,'Master Data HO & Site'!$Y$1:$Y$437,"Open",'Master Data HO & Site'!$N$1:$N$437,$H$2)))) -> 0 | AJ8: =IF($H$2="All",IF(C8="Jakarta",SUMIFS('Master Data HO & Site'!$BB$1:$BB$437,'Master Data HO & Site'!$F$1:$F$437,'Summary to Mgmt'!$D8,'Master Data HO & Site'!$H$1:$H$437,'Summary to Mgmt'!$E8,'Master Data HO & Site'!$Y$1:$Y$437,"Open"),SUMIFS('Master Data HO & Site'!$BB$1:$BB$437,'Master Data HO & Site'!$S$1:$S$437,'Summary to Mgmt'!$C8,'Master Data HO & Site'!$Y$1:$Y$437,"Open")),IF($H$2="Urgent",IF(C8="Jakarta",SUMIFS('Master Data HO & Site'!$BB$1:$BB$437,'Master Data HO & Site'!$F$1:$F$437,'Summary to Mgmt'!$D8,'Master Data HO & Site'!$H$1:$H$437,'Summary to Mgmt'!$E8,'Master Data HO & Site'!$Y$1:$Y$437,"Open",'Master Data HO & Site'!$N$1:$N$437,$H$2),SUMIFS('Master Data HO & Site'!$BB$1:$BB$437,'Master Data HO & Site'!$S$1:$S$437,'Summary to Mgmt'!$C8,'Master Data HO & Site'!$Y$1:$Y$437,"Open",'Master Data HO & Site'!$N$1:$N$437,$H$2)),IF(C8="Jakarta",SUMIFS('Master Data HO & Site'!$BB$1:$BB$437,'Master Data HO & Site'!$F$1:$F$437,'Summary to Mgmt'!$D8,'Master Data HO & Site'!$H$1:$H$437,'Summary to Mgmt'!$E8,'Master Data HO & Site'!$Y$1:$Y$437,"Open",'Master Data HO & Site'!$N$1:$N$437,$H$2),SUMIFS('Master Data HO & Site'!$BB$1:$BB$437,'Master Data HO & Site'!$S$1:$S$437,'Summary to Mgmt'!$C8,'Master Data HO & Site'!$Y$1:$Y$437,"Open",'Master Data HO & Site'!$N$1:$N$437,$H$2)))) -> 0 | AK8: =IF($H$2="All",IF(C8="Jakarta",SUMIFS('Master Data HO & Site'!$BC$1:$BC$437,'Master Data HO & Site'!$F$1:$F$437,'Summary to Mgmt'!$D8,'Master Data HO & Site'!$H$1:$H$437,'Summary to Mgmt'!$E8,'Master Data HO & Site'!$Y$1:$Y$437,"Open"),SUMIFS('Master Data HO & Site'!$BC$1:$BC$437,'Master Data HO & Site'!$S$1:$S$437,'Summary to Mgmt'!$C8,'Master Data HO & Site'!$Y$1:$Y$437,"Open")),IF($H$2="Urgent",IF(C8="Jakarta",SUMIFS('Master Data HO & Site'!$BC$1:$BC$437,'Master Data HO & Site'!$F$1:$F$437,'Summary to Mgmt'!$D8,'Master Data HO & Site'!$H$1:$H$437,'Summary to Mgmt'!$E8,'Master Data HO & Site'!$Y$1:$Y$437,"Open",'Master Data HO & Site'!$N$1:$N$437,$H$2),SUMIFS('Master Data HO & Site'!$BC$1:$BC$437,'Master Data HO & Site'!$S$1:$S$437,'Summary to Mgmt'!$C8,'Master Data HO & Site'!$Y$1:$Y$437,"Open",'Master Data HO & Site'!$N$1:$N$437,$H$2)),IF(C8="Jakarta",SUMIFS('Master Data HO & Site'!$BC$1:$BC$437,'Master Data HO & Site'!$F$1:$F$437,'Summary to Mgmt'!$D8,'Master Data HO & Site'!$H$1:$H$437,'Summary to Mgmt'!$E8,'Master Data HO & Site'!$Y$1:$Y$437,"Open",'Master Data HO & Site'!$N$1:$N$437,$H$2),SUMIFS('Master Data HO & Site'!$BC$1:$BC$437,'Master Data HO & Site'!$S$1:$S$437,'Summary to Mgmt'!$C8,'Master Data HO & Site'!$Y$1:$Y$437,"Open",'Master Data HO & Site'!$N$1:$N$437,$H$2)))) -> 0 | AL8: =IF($H$2="All",IF(C8="Jakarta",SUMIFS('Master Data HO & Site'!$BD$1:$BD$437,'Master Data HO & Site'!$F$1:$F$437,'Summary to Mgmt'!$D8,'Master Data HO & Site'!$H$1:$H$437,'Summary to Mgmt'!$E8,'Master Data HO & Site'!$Y$1:$Y$437,"Open"),SUMIFS('Master Data HO & Site'!$BD$1:$BD$437,'Master Data HO & Site'!$S$1:$S$437,'Summary to Mgmt'!$C8,'Master Data HO & Site'!$Y$1:$Y$437,"Open")),IF($H$2="Urgent",IF(C8="Jakarta",SUMIFS('Master Data HO & Site'!$BD$1:$BD$437,'Master Data HO & Site'!$F$1:$F$437,'Summary to Mgmt'!$D8,'Master Data HO & Site'!$H$1:$H$437,'Summary to Mgmt'!$E8,'Master Data HO & Site'!$Y$1:$Y$437,"Open",'Master Data HO & Site'!$N$1:$N$437,$H$2),SUMIFS('Master Data HO & Site'!$BD$1:$BD$437,'Master Data HO & Site'!$S$1:$S$437,'Summary to Mgmt'!$C8,'Master Data HO & Site'!$Y$1:$Y$437,"Open",'Master Data HO & Site'!$N$1:$N$437,$H$2)),IF(C8="Jakarta",SUMIFS('Master Data HO & Site'!$BD$1:$BD$437,'Master Data HO & Site'!$F$1:$F$437,'Summary to Mgmt'!$D8,'Master Data HO & Site'!$H$1:$H$437,'Summary to Mgmt'!$E8,'Master Data HO & Site'!$Y$1:$Y$437,"Open",'Master Data HO & Site'!$N$1:$N$437,$H$2),SUMIFS('Master Data HO & Site'!$BD$1:$BD$437,'Master Data HO & Site'!$S$1:$S$437,'Summary to Mgmt'!$C8,'Master Data HO & Site'!$Y$1:$Y$437,"Open",'Master Data HO & Site'!$N$1:$N$437,$H$2)))) -> 0 | AM8: =IF($H$2="All",IF(C8="Jakarta",SUMIFS('Master Data HO & Site'!$BE$1:$BE$437,'Master Data HO & Site'!$S$1:$S$437,'Summary to Mgmt'!$C8,'Master Data HO & Site'!$F$1:$F$437,'Summary to Mgmt'!$D8,'Master Data HO & Site'!$H$1:$H$437,'Summary to Mgmt'!$E8,'Master Data HO & Site'!$Y$1:$Y$437,"Open"),SUMIFS('Master Data HO & Site'!$BE$1:$BE$437,'Master Data HO & Site'!$S$1:$S$437,'Summary to Mgmt'!$C8,'Master Data HO & Site'!$Y$1:$Y$437,"Open")),IF($H$2="Urgent",IF(C8="Jakarta",SUMIFS('Master Data HO & Site'!$BE$1:$BE$437,'Master Data HO & Site'!$F$1:$F$437,'Summary to Mgmt'!$D8,'Master Data HO & Site'!$H$1:$H$437,'Summary to Mgmt'!$E8,'Master Data HO & Site'!$Y$1:$Y$437,"Open",'Master Data HO & Site'!$N$1:$N$437,$H$2),SUMIFS('Master Data HO & Site'!$BE$1:$BE$437,'Master Data HO & Site'!$S$1:$S$437,'Summary to Mgmt'!$C8,'Master Data HO & Site'!$Y$1:$Y$437,"Open",'Master Data HO & Site'!$N$1:$N$437,$H$2)),IF(C8="Jakarta",SUMIFS('Master Data HO & Site'!$BE$1:$BE$437,'Master Data HO & Site'!$F$1:$F$437,'Summary to Mgmt'!$D8,'Master Data HO & Site'!$H$1:$H$437,'Summary to Mgmt'!$E8,'Master Data HO & Site'!$Y$1:$Y$437,"Open",'Master Data HO & Site'!$N$1:$N$437,$H$2),SUMIFS('Master Data HO & Site'!$BE$1:$BE$437,'Master Data HO & Site'!$S$1:$S$437,'Summary to Mgmt'!$C8,'Master Data HO & Site'!$Y$1:$Y$437,"Open",'Master Data HO & Site'!$N$1:$N$437,$H$2)))) -> 0 | AN8: =IF($H$2="All",IF(C8="Jakarta",SUMIFS('Master Data HO & Site'!$BF$1:$BF$437,'Master Data HO & Site'!$F$1:$F$437,'Summary to Mgmt'!$D8,'Master Data HO & Site'!$H$1:$H$437,'Summary to Mgmt'!$E8,'Master Data HO & Site'!$Y$1:$Y$437,"Open"),SUMIFS('Master Data HO & Site'!$BF$1:$BF$437,'Master Data HO & Site'!$S$1:$S$437,'Summary to Mgmt'!$C8,'Master Data HO & Site'!$Y$1:$Y$437,"Open")),IF($H$2="Urgent",IF(C8="Jakarta",SUMIFS('Master Data HO & Site'!$BF$1:$BF$437,'Master Data HO & Site'!$F$1:$F$437,'Summary to Mgmt'!$D8,'Master Data HO & Site'!$H$1:$H$437,'Summary to Mgmt'!$E8,'Master Data HO & Site'!$Y$1:$Y$437,"Open",'Master Data HO & Site'!$N$1:$N$437,$H$2),SUMIFS('Master Data HO & Site'!$BF$1:$BF$437,'Master Data HO & Site'!$S$1:$S$437,'Summary to Mgmt'!$C8,'Master Data HO & Site'!$Y$1:$Y$437,"Open",'Master Data HO & Site'!$N$1:$N$437,$H$2)),IF(C8="Jakarta",SUMIFS('Master Data HO & Site'!$BF$1:$BF$437,'Master Data HO & Site'!$F$1:$F$437,'Summary to Mgmt'!$D8,'Master Data HO & Site'!$H$1:$H$437,'Summary to Mgmt'!$E8,'Master Data HO & Site'!$Y$1:$Y$437,"Open",'Master Data HO & Site'!$N$1:$N$437,$H$2),SUMIFS('Master Data HO & Site'!$BF$1:$BF$437,'Master Data HO & Site'!$S$1:$S$437,'Summary to Mgmt'!$C8,'Master Data HO & Site'!$Y$1:$Y$437,"Open",'Master Data HO & Site'!$N$1:$N$437,$H$2)))) -> 0 | AO8: =IF($H$2="All",IF(C8="Jakarta",SUMIFS('Master Data HO & Site'!$BG$1:$BG$437,'Master Data HO & Site'!$F$1:$F$437,'Summary to Mgmt'!$D8,'Master Data HO & Site'!$H$1:$H$437,'Summary to Mgmt'!$E8,'Master Data HO & Site'!$Y$1:$Y$437,"Open"),SUMIFS('Master Data HO & Site'!$BG$1:$BG$437,'Master Data HO & Site'!$S$1:$S$437,'Summary to Mgmt'!$C8,'Master Data HO & Site'!$Y$1:$Y$437,"Open")),IF($H$2="Urgent",IF(C8="Jakarta",SUMIFS('Master Data HO & Site'!$BG$1:$BG$437,'Master Data HO & Site'!$F$1:$F$437,'Summary to Mgmt'!$D8,'Master Data HO & Site'!$H$1:$H$437,'Summary to Mgmt'!$E8,'Master Data HO & Site'!$Y$1:$Y$437,"Open",'Master Data HO & Site'!$N$1:$N$437,$H$2),SUMIFS('Master Data HO & Site'!$BG$1:$BG$437,'Master Data HO & Site'!$S$1:$S$437,'Summary to Mgmt'!$C8,'Master Data HO & Site'!$Y$1:$Y$437,"Open",'Master Data HO & Site'!$N$1:$N$437,$H$2)),IF(C8="Jakarta",SUMIFS('Master Data HO & Site'!$BG$1:$BG$437,'Master Data HO & Site'!$F$1:$F$437,'Summary to Mgmt'!$D8,'Master Data HO & Site'!$H$1:$H$437,'Summary to Mgmt'!$E8,'Master Data HO & Site'!$Y$1:$Y$437,"Open",'Master Data HO & Site'!$N$1:$N$437,$H$2),SUMIFS('Master Data HO & Site'!$BG$1:$BG$437,'Master Data HO & Site'!$S$1:$S$437,'Summary to Mgmt'!$C8,'Master Data HO & Site'!$Y$1:$Y$437,"Open",'Master Data HO & Site'!$N$1:$N$437,$H$2)))) -> 0 | AP8: =IF($H$2="All",IF(C8="Jakarta",SUMIFS('Master Data HO & Site'!$BH$1:$BH$437,'Master Data HO & Site'!$F$1:$F$437,'Summary to Mgmt'!$D8,'Master Data HO & Site'!$H$1:$H$437,'Summary to Mgmt'!$E8,'Master Data HO & Site'!$Y$1:$Y$437,"Open"),SUMIFS('Master Data HO & Site'!$BH$1:$BH$437,'Master Data HO & Site'!$S$1:$S$437,'Summary to Mgmt'!$C8,'Master Data HO & Site'!$Y$1:$Y$437,"Open")),IF($H$2="Urgent",IF(C8="Jakarta",SUMIFS('Master Data HO & Site'!$BH$1:$BH$437,'Master Data HO & Site'!$F$1:$F$437,'Summary to Mgmt'!$D8,'Master Data HO & Site'!$H$1:$H$437,'Summary to Mgmt'!$E8,'Master Data HO & Site'!$Y$1:$Y$437,"Open",'Master Data HO & Site'!$N$1:$N$437,$H$2),SUMIFS('Master Data HO & Site'!$BH$1:$BH$437,'Master Data HO & Site'!$S$1:$S$437,'Summary to Mgmt'!$C8,'Master Data HO & Site'!$Y$1:$Y$437,"Open",'Master Data HO & Site'!$N$1:$N$437,$H$2)),IF(C8="Jakarta",SUMIFS('Master Data HO & Site'!$BH$1:$BH$437,'Master Data HO & Site'!$F$1:$F$437,'Summary to Mgmt'!$D8,'Master Data HO & Site'!$H$1:$H$437,'Summary to Mgmt'!$E8,'Master Data HO & Site'!$Y$1:$Y$437,"Open",'Master Data HO & Site'!$N$1:$N$437,$H$2),SUMIFS('Master Data HO & Site'!$BH$1:$BH$437,'Master Data HO & Site'!$S$1:$S$437,'Summary to Mgmt'!$C8,'Master Data HO & Site'!$Y$1:$Y$437,"Open",'Master Data HO & Site'!$N$1:$N$437,$H$2)))) -> 0 | AQ8: =IF($H$2="All",IF(C8="Jakarta",SUMIFS('Master Data HO & Site'!$BI$1:$BI$437,'Master Data HO & Site'!$F$1:$F$437,'Summary to Mgmt'!$D8,'Master Data HO & Site'!$H$1:$H$437,'Summary to Mgmt'!$E8,'Master Data HO & Site'!$Y$1:$Y$437,"Open"),SUMIFS('Master Data HO & Site'!$BI$1:$BI$437,'Master Data HO & Site'!$S$1:$S$437,'Summary to Mgmt'!$C8,'Master Data HO & Site'!$Y$1:$Y$437,"Open")),IF($H$2="Urgent",IF(C8="Jakarta",SUMIFS('Master Data HO & Site'!$BI$1:$BI$437,'Master Data HO & Site'!$F$1:$F$437,'Summary to Mgmt'!$D8,'Master Data HO & Site'!$H$1:$H$437,'Summary to Mgmt'!$E8,'Master Data HO & Site'!$Y$1:$Y$437,"Open",'Master Data HO & Site'!$N$1:$N$437,$H$2),SUMIFS('Master Data HO & Site'!$BI$1:$BI$437,'Master Data HO & Site'!$S$1:$S$437,'Summary to Mgmt'!$C8,'Master Data HO & Site'!$Y$1:$Y$437,"Open",'Master Data HO & Site'!$N$1:$N$437,$H$2)),IF(C8="Jakarta",SUMIFS('Master Data HO & Site'!$BI$1:$BI$437,'Master Data HO & Site'!$F$1:$F$437,'Summary to Mgmt'!$D8,'Master Data HO & Site'!$H$1:$H$437,'Summary to Mgmt'!$E8,'Master Data HO & Site'!$Y$1:$Y$437,"Open",'Master Data HO & Site'!$N$1:$N$437,$H$2),SUMIFS('Master Data HO & Site'!$BI$1:$BI$437,'Master Data HO & Site'!$S$1:$S$437,'Summary to Mgmt'!$C8,'Master Data HO & Site'!$Y$1:$Y$437,"Open",'Master Data HO & Site'!$N$1:$N$437,$H$2)))) -> 0 | AR8: =IF($H$2="All",IF(C8="Jakarta",SUMIFS('Master Data HO & Site'!$BJ$1:$BJ$437,'Master Data HO & Site'!$F$1:$F$437,'Summary to Mgmt'!$D8,'Master Data HO & Site'!$H$1:$H$437,'Summary to Mgmt'!$E8,'Master Data HO & Site'!$Y$1:$Y$437,"Open"),SUMIFS('Master Data HO & Site'!$BJ$1:$BJ$437,'Master Data HO & Site'!$S$1:$S$437,'Summary to Mgmt'!$C8,'Master Data HO & Site'!$Y$1:$Y$437,"Open")),IF($H$2="Urgent",IF(C8="Jakarta",SUMIFS('Master Data HO & Site'!$BJ$1:$BJ$437,'Master Data HO & Site'!$F$1:$F$437,'Summary to Mgmt'!$D8,'Master Data HO & Site'!$H$1:$H$437,'Summary to Mgmt'!$E8,'Master Data HO & Site'!$Y$1:$Y$437,"Open",'Master Data HO & Site'!$N$1:$N$437,$H$2),SUMIFS('Master Data HO & Site'!$BJ$1:$BJ$437,'Master Data HO & Site'!$S$1:$S$437,'Summary to Mgmt'!$C8,'Master Data HO & Site'!$Y$1:$Y$437,"Open",'Master Data HO & Site'!$N$1:$N$437,$H$2)),IF(C8="Jakarta",SUMIFS('Master Data HO & Site'!$BJ$1:$BJ$437,'Master Data HO & Site'!$F$1:$F$437,'Summary to Mgmt'!$D8,'Master Data HO & Site'!$H$1:$H$437,'Summary to Mgmt'!$E8,'Master Data HO & Site'!$Y$1:$Y$437,"Open",'Master Data HO & Site'!$N$1:$N$437,$H$2),SUMIFS('Master Data HO & Site'!$BJ$1:$BJ$437,'Master Data HO & Site'!$S$1:$S$437,'Summary to Mgmt'!$C8,'Master Data HO & Site'!$Y$1:$Y$437,"Open",'Master Data HO & Site'!$N$1:$N$437,$H$2)))) -> 0 | AS8: =IF($H$2="All",IF(C8="Jakarta",SUMIFS('Master Data HO & Site'!$BK$1:$BK$437,'Master Data HO & Site'!$S$1:$S$437,'Summary to Mgmt'!$C8,'Master Data HO & Site'!$F$1:$F$437,'Summary to Mgmt'!$D8,'Master Data HO & Site'!$H$1:$H$437,'Summary to Mgmt'!$E8,'Master Data HO & Site'!$Y$1:$Y$437,"Open"),SUMIFS('Master Data HO & Site'!$BK$1:$BK$437,'Master Data HO & Site'!$S$1:$S$437,'Summary to Mgmt'!$C8,'Master Data HO & Site'!$Y$1:$Y$437,"Open")),IF($H$2="Urgent",IF(C8="Jakarta",SUMIFS('Master Data HO & Site'!$BK$1:$BK$437,'Master Data HO & Site'!$F$1:$F$437,'Summary to Mgmt'!$D8,'Master Data HO & Site'!$H$1:$H$437,'Summary to Mgmt'!$E8,'Master Data HO & Site'!$Y$1:$Y$437,"Open",'Master Data HO & Site'!$N$1:$N$437,$H$2),SUMIFS('Master Data HO & Site'!$BK$1:$BK$437,'Master Data HO & Site'!$S$1:$S$437,'Summary to Mgmt'!$C8,'Master Data HO & Site'!$Y$1:$Y$437,"Open",'Master Data HO & Site'!$N$1:$N$437,$H$2)),IF(C8="Jakarta",SUMIFS('Master Data HO & Site'!$BK$1:$BK$437,'Master Data HO & Site'!$F$1:$F$437,'Summary to Mgmt'!$D8,'Master Data HO & Site'!$H$1:$H$437,'Summary to Mgmt'!$E8,'Master Data HO & Site'!$Y$1:$Y$437,"Open",'Master Data HO & Site'!$N$1:$N$437,$H$2),SUMIFS('Master Data HO & Site'!$BK$1:$BK$437,'Master Data HO & Site'!$S$1:$S$437,'Summary to Mgmt'!$C8,'Master Data HO & Site'!$Y$1:$Y$437,"Open",'Master Data HO & Site'!$N$1:$N$437,$H$2)))) -> 0 | AU8: =IF($H$2="All",IF(C8="Jakarta",COUNTIFS('Master Data HO & Site'!$F$1:$F$437,'Summary to Mgmt'!$D8,'Master Data HO & Site'!$H$1:$H$437,'Summary to Mgmt'!$E8,'Master Data HO & Site'!$Y$1:$Y$437,"Open",'Master Data HO & Site'!$BZ$1:$BZ$437,'Summary to Mgmt'!$AU$4),COUNTIFS('Master Data HO & Site'!$S$1:$S$437,'Summary to Mgmt'!$C8,'Master Data HO & Site'!$Y$1:$Y$437,"Open",'Master Data HO & Site'!$BZ$1:$BZ$437,'Summary to Mgmt'!$AU$4)),IF($H$2="Urgent",IF(C8="Jakarta",COUNTIFS('Master Data HO & Site'!$F$1:$F$437,'Summary to Mgmt'!$D8,'Master Data HO & Site'!$H$1:$H$437,'Summary to Mgmt'!$E8,'Master Data HO & Site'!$Y$1:$Y$437,"Open",'Master Data HO & Site'!$BZ$1:$BZ$437,'Summary to Mgmt'!$AU$4,'Master Data HO & Site'!$N$1:$N$437,$H$2),COUNTIFS('Master Data HO & Site'!$S$1:$S$437,'Summary to Mgmt'!$C8,'Master Data HO & Site'!$Y$1:$Y$437,"Open",'Master Data HO & Site'!$BZ$1:$BZ$437,'Summary to Mgmt'!$AU$4,'Master Data HO & Site'!$N$1:$N$437,$H$2)),IF(C8="Jakarta",COUNTIFS('Master Data HO & Site'!$F$1:$F$437,'Summary to Mgmt'!$D8,'Master Data HO & Site'!$H$1:$H$437,'Summary to Mgmt'!$E8,'Master Data HO & Site'!$Y$1:$Y$437,"Open",'Master Data HO & Site'!$BZ$1:$BZ$437,'Summary to Mgmt'!$AU$4,'Master Data HO & Site'!$N$1:$N$437,$H$2),COUNTIFS('Master Data HO & Site'!$S$1:$S$437,'Summary to Mgmt'!$C8,'Master Data HO & Site'!$Y$1:$Y$437,"Open",'Master Data HO & Site'!$BZ$1:$BZ$437,'Summary to Mgmt'!$AU$4,'Master Data HO & Site'!$N$1:$N$437,$H$2)))) -> 1 | AV8: =IF($H$2="All",IF(C8="Jakarta",COUNTIFS('Master Data HO & Site'!$F$1:$F$437,'Summary to Mgmt'!$D8,'Master Data HO & Site'!$H$1:$H$437,'Summary to Mgmt'!$E8,'Master Data HO & Site'!$Y$1:$Y$437,"Open",'Master Data HO & Site'!$BZ$1:$BZ$437,'Summary to Mgmt'!$AV$4),COUNTIFS('Master Data HO & Site'!$S$1:$S$437,'Summary to Mgmt'!$C8,'Master Data HO & Site'!$Y$1:$Y$437,"Open",'Master Data HO & Site'!$BZ$1:$BZ$437,'Summary to Mgmt'!$AV$4)),IF($H$2="Urgent",IF(C8="Jakarta",COUNTIFS('Master Data HO & Site'!$F$1:$F$437,'Summary to Mgmt'!$D8,'Master Data HO & Site'!$H$1:$H$437,'Summary to Mgmt'!$E8,'Master Data HO & Site'!$Y$1:$Y$437,"Open",'Master Data HO & Site'!$BZ$1:$BZ$437,'Summary to Mgmt'!$AV$4,'Master Data HO & Site'!$N$1:$N$437,$H$2),COUNTIFS('Master Data HO & Site'!$S$1:$S$437,'Summary to Mgmt'!$C8,'Master Data HO & Site'!$Y$1:$Y$437,"Open",'Master Data HO & Site'!$BZ$1:$BZ$437,'Summary to Mgmt'!$AV$4,'Master Data HO & Site'!$N$1:$N$437,$H$2)),IF(C8="Jakarta",COUNTIFS('Master Data HO & Site'!$F$1:$F$437,'Summary to Mgmt'!$D8,'Master Data HO & Site'!$H$1:$H$437,'Summary to Mgmt'!$E8,'Master Data HO & Site'!$Y$1:$Y$437,"Open",'Master Data HO & Site'!$BZ$1:$BZ$437,'Summary to Mgmt'!$AV$4,'Master Data HO & Site'!$N$1:$N$437,$H$2),COUNTIFS('Master Data HO & Site'!$S$1:$S$437,'Summary to Mgmt'!$C8,'Master Data HO & Site'!$Y$1:$Y$437,"Open",'Master Data HO & Site'!$BZ$1:$BZ$437,'Summary to Mgmt'!$AV$4,'Master Data HO & Site'!$N$1:$N$437,$H$2)))) -> 0 | AW8: =IF($H$2="All",IF(C8="Jakarta",COUNTIFS('Master Data HO & Site'!$F$1:$F$437,'Summary to Mgmt'!$D8,'Master Data HO & Site'!$H$1:$H$437,'Summary to Mgmt'!$E8,'Master Data HO & Site'!$Y$1:$Y$437,"Open",'Master Data HO & Site'!$BZ$1:$BZ$437,'Summary to Mgmt'!$AW$4),COUNTIFS('Master Data HO & Site'!$S$1:$S$437,'Summary to Mgmt'!$C8,'Master Data HO & Site'!$Y$1:$Y$437,"Open",'Master Data HO & Site'!$BZ$1:$BZ$437,'Summary to Mgmt'!$AW$4)),IF($H$2="Urgent",IF(C8="Jakarta",COUNTIFS('Master Data HO & Site'!$F$1:$F$437,'Summary to Mgmt'!$D8,'Master Data HO & Site'!$H$1:$H$437,'Summary to Mgmt'!$E8,'Master Data HO & Site'!$Y$1:$Y$437,"Open",'Master Data HO & Site'!$BZ$1:$BZ$437,'Summary to Mgmt'!$AW$4,'Master Data HO & Site'!$N$1:$N$437,$H$2),COUNTIFS('Master Data HO & Site'!$S$1:$S$437,'Summary to Mgmt'!$C8,'Master Data HO & Site'!$Y$1:$Y$437,"Open",'Master Data HO & Site'!$BZ$1:$BZ$437,'Summary to Mgmt'!$AW$4,'Master Data HO & Site'!$N$1:$N$437,$H$2)),IF(C8="Jakarta",COUNTIFS('Master Data HO & Site'!$F$1:$F$437,'Summary to Mgmt'!$D8,'Master Data HO & Site'!$H$1:$H$437,'Summary to Mgmt'!$E8,'Master Data HO & Site'!$Y$1:$Y$437,"Open",'Master Data HO & Site'!$BZ$1:$BZ$437,'Summary to Mgmt'!$AW$4,'Master Data HO & Site'!$N$1:$N$437,$H$2),COUNTIFS('Master Data HO & Site'!$S$1:$S$437,'Summary to Mgmt'!$C8,'Master Data HO & Site'!$Y$1:$Y$437,"Open",'Master Data HO & Site'!$BZ$1:$BZ$437,'Summary to Mgmt'!$AW$4,'Master Data HO & Site'!$N$1:$N$437,$H$2)))) -> 0 | AX8: =IF($H$2="All",IF(C8="Jakarta",COUNTIFS('Master Data HO & Site'!$F$1:$F$437,'Summary to Mgmt'!$D8,'Master Data HO & Site'!$H$1:$H$437,'Summary to Mgmt'!$E8,'Master Data HO & Site'!$Y$1:$Y$437,"Open",'Master Data HO & Site'!$BZ$1:$BZ$437,'Summary to Mgmt'!$AX$4),COUNTIFS('Master Data HO & Site'!$S$1:$S$437,'Summary to Mgmt'!$C8,'Master Data HO & Site'!$Y$1:$Y$437,"Open",'Master Data HO & Site'!$BZ$1:$BZ$437,'Summary to Mgmt'!$AX$4)),IF($H$2="Urgent",IF(C8="Jakarta",COUNTIFS('Master Data HO & Site'!$F$1:$F$437,'Summary to Mgmt'!$D8,'Master Data HO & Site'!$H$1:$H$437,'Summary to Mgmt'!$E8,'Master Data HO & Site'!$Y$1:$Y$437,"Open",'Master Data HO & Site'!$BZ$1:$BZ$437,'Summary to Mgmt'!$AX$4,'Master Data HO & Site'!$N$1:$N$437,$H$2),COUNTIFS('Master Data HO & Site'!$S$1:$S$437,'Summary to Mgmt'!$C8,'Master Data HO & Site'!$Y$1:$Y$437,"Open",'Master Data HO & Site'!$BZ$1:$BZ$437,'Summary to Mgmt'!$AX$4,'Master Data HO & Site'!$N$1:$N$437,$H$2)),IF(C8="Jakarta",COUNTIFS('Master Data HO & Site'!$F$1:$F$437,'Summary to Mgmt'!$D8,'Master Data HO & Site'!$H$1:$H$437,'Summary to Mgmt'!$E8,'Master Data HO & Site'!$Y$1:$Y$437,"Open",'Master Data HO & Site'!$BZ$1:$BZ$437,'Summary to Mgmt'!$AX$4,'Master Data HO & Site'!$N$1:$N$437,$H$2),COUNTIFS('Master Data HO & Site'!$S$1:$S$437,'Summary to Mgmt'!$C8,'Master Data HO & Site'!$Y$1:$Y$437,"Open",'Master Data HO & Site'!$BZ$1:$BZ$437,'Summary to Mgmt'!$AX$4,'Master Data HO & Site'!$N$1:$N$437,$H$2)))) -> 0
